Workbook
Name d_Category: 'Cleaned Data'!$D$2:$D$2001
Name d_City: 'Cleaned Data'!$U$2:$U$2001
Name d_COGS: 'Cleaned Data'!$M$2:$M$2001
Name d_Cust: 'Cleaned Data'!$S$2:$S$2001
Name d_Date: 'Cleaned Data'!$B$2:$B$2001
Name d_Disc: 'Cleaned Data'!$G$2:$G$2001
Name d_GP: 'Cleaned Data'!$N$2:$N$2001
Name d_Inv: 'Cleaned Data'!$A$2:$A$2001
Name d_NetQty: 'Cleaned Data'!$K$2:$K$2001
Name d_NetSales: 'Cleaned Data'!$L$2:$L$2001
Name d_NP: 'Cleaned Data'!$Q$2:$Q$2001
Name d_Opex: 'Cleaned Data'!$P$2:$P$2001
Name d_Pay: 'Cleaned Data'!$T$2:$T$2001
Name d_Product: 'Cleaned Data'!$C$2:$C$2001
Name d_Qty: 'Cleaned Data'!$E$2:$E$2001
Name d_RetQty: 'Cleaned Data'!$I$2:$I$2001
Name d_Sales: 'Cleaned Data'!$H$2:$H$2001
Name d_SalesRet: 'Cleaned Data'!$J$2:$J$2001
Name fCat: Calc!$C$5
Name fCity: Calc!$C$6
Name fCust: Calc!$C$7
Name fEnd: Calc!$C$13
Name fPay: Calc!$C$8
Name fStart: Calc!$C$12

Sheet Requirements
A1: Requirement | B1: Details
A2: Client / Retail Store | B2: Mega Market
A3: Raw Dataset | B3: 2,000+ retail transaction rows; raw data may contain duplicates, blanks, inconsistent text formatting, mixed data types, and other realistic data-quality issues.
A4: Deliverable 1 — Data Cleaning | B4: Clean duplicates; standardize product/category/payment/customer/city text; handle missing values; convert dates and numeric fields to consistent formats; validate quantities and financial calculations.
A5: Deliverable 2 — Data Organization | B5: Create a structured, analysis-ready dataset with consistent column names, logical ordering, and calculated fields such as Net Qty, Net Sales, Gross Profit, and Net Profit.
A6: Deliverable 3 — Formatting | B6: Apply professional Excel formatting: headers, currency/percentage/number/date formats, filters, freeze panes, readable column widths, and conditional formatting where useful.
A7: Deliverable 4 — HTML Dashboard | B7: Create a professional interactive HTML dashboard for Mega Market using the cleaned data. Include KPI cards, sales/profit trends, product/category analysis, and useful filters/charts.
A8: Dashboard KPI Requirements | B8: Total Sales, Net Sales, Gross Profit, Net Profit, Total Quantity Sold, Average Order Value, Return Rate, and Gross/Net Profit Margin.
A9: Product Analysis | B9: Identify highest-selling product, lowest-selling product, highest-revenue product, lowest-revenue product, and products with weak sales performance.
A10: Category Analysis | B10: Compare categories by Net Sales, Quantity, Gross Profit, Net Profit, and margins. Highlight strong and weak categories.
A11: Trend Analysis | B11: Show monthly Net Sales, Gross Profit, Net Profit, and transaction/order trends. Identify peak and weak periods.
A12: Customer & Payment Analysis | B12: Analyze customer type, payment method, and city contribution to sales.
... A18: Important | B18: Do not change valid business values merely to make the dataset look perfect. Document assumptions used while cleaning missing or inconsistent values.

Sheet Raw Data
A1: Invoice ID | B1: Date | C1: Product | D1: Category | E1: Qty | F1: Unit Price (₹) | G1: Discount (%) | H1: Sales (₹) | I1: Return Qty | J1: Sales Return (₹) | K1: Net Qty | L1: Net Sales (₹) | M1: COGS (₹) | N1: Gross Profit (₹) | O1: Operating Expense (₹) | P1: Net Profit (₹) | Q1: Customer Type | R1: Payment Method | S1: City
A2: MM-0001 | B2: 45872 | C2: Biscuits Pack | D2: Snacks | E2: 5 | F2: 40 | G2: 0 | H2: 200 | I2: 0 | J2: 0 | K2: 5 | L2: 200 | M2: 161.43 | N2: 38.57 | O2: 17.13 | P2: 21.44 | Q2: Member | R2: Card | S2: Ghaziabad
A3: MM-0002 | B3: 45849 | C3: Cooking Oil 1L | D3: Groceries | E3: 1 | F3: 145 | G3: 2 | H3: 142.1 | I3: 0 | J3: 0 | K3: 1 | L3: 142.1 | M3: 90.03 | N3: 52.07 | O3: 17.77 | P3: 34.3 | Q3: Walk-in | R3: Cash | S3: Delhi
A4: MM-0003 | B4: 45845 | C4: Shampoo 340ml | D4: Personal Care | E4: 3 | F4: 210 | G4: 0 | H4: 630 | I4: 0 | J4: 0 | K4: 3 | L4: 630 | M4: 394.09 | N4: 235.91 | O4: 51.65 | P4: 184.26 | Q4: Walk-in | R4: Card | S4: Noida
A5: MM-0004 | B5: 45792 | C5: Laundry Detergent 2kg | D5: Household | E5: 3 | F5: 280 | G5: 0 | H5: 840 | I5: 0 | J5: 0 | K5: 3 | L5: 840 | M5: 719.02 | N5: 120.98 | O5: 99.79 | P5: 21.19 | Q5: Regular | R5: Cash | S5: Gurugram
A6: MM-0005 | B6: 45820 | C6: LED Bulb 9W | D6: Electronics | E6: 8 | F6: 120 | G6: 15 | H6: 816 | I6: 0 | J6: 0 | K6: 8 | L6: 816 | M6: 664.24 | N6: 151.76 | O6: 47.18 | P6: 104.58 | Q6: Walk-in | R6: Card | S6: Ghaziabad
A7: MM-0006 | B7: 45659 | C7: Biscuits Pack | D7: Snacks | E7: 3 | F7: 40 | G7: 5 | H7: 114 | I7: 0 | J7: 0 | K7: 3 | L7: 114 | M7: 75.42 | N7: 38.58 | O7: 7.36 | P7: 31.22 | Q7: New | R7: UPI | S7: Noida
A8: MM-0007 | B8: 45927 | C8: Soft Drink 750ml | D8: Beverages | E8: 3 | F8: 48 | G8: 0 | H8: 144 | I8: 0 | J8: 0 | K8: 3 | L8: 144 | M8: 118.39 | N8: 25.61 | O8: 11.75 | P8: 13.86 | Q8: Member | R8: Wallet | S8: Gurugram
A9: MM-0008 | B9: 45710 | C9: Potato Chips | D9: Snacks | E9: 3 | F9: 30 | G9: 0 | H9: 90 | I9: 0 | J9: 0 | K9: 3 | L9: 90 | M9: 76.56 | N9: 13.44 | O9: 9.88 | P9: 3.56 | Q9: Walk-in | R9: UPI | S9: Delhi
A10: MM-0009 | B10: 45793 | C10: Soap Bar | D10: Personal Care | E10: 1 | F10: 38 | G10: 5 | H10: 36.1 | I10: 0 | J10: 0 | K10: 1 | L10: 36.1 | M10: 23.03 | N10: 13.07 | O10: 4.04 | P10: 9.03 | Q10: Walk-in | R10: Card | S10: Gurugram
A11: MM-0010 | B11: 45698 | C11: Batteries Pack | D11: Electronics | E11: 4 | F11: 85 | G11: 5 | H11: 323 | I11: 0 | J11: 0 | K11: 4 | L11: 323 | M11: 260.05 | N11: 62.95 | O11: 25.41 | P11: 37.54 | Q11: Walk-in | R11: Card | S11: Delhi
A12: MM-0011 | B12: 45829 | C12: Potato Chips | D12: Snacks | E12: 3 | F12: 30 | G12: 0 | H12: 90 | I12: 0 | J12: 0 | K12: 3 | L12: 90 | M12: 63.81 | N12: 26.19 | O12: 9.29 | P12: 16.9 | Q12: Walk-in | R12: UPI | S12: Gurugram
A13: MM-0012 | B13: 45912 | C13: Sugar 1kg | D13: Groceries | E13: 3 | F13: 52 | G13: 0 | H13: 156 | I13: 0 | J13: 0 | K13: 3 | L13: 156 | M13: 123.42 | N13: 32.58 | O13: 14.8 | P13: 17.78 | Q13: New | R13: Card | S13: Gurugram
A14: MM-0013 | B14: 45898 | C14: Chocolate Bar | D14: Snacks | E14: 4 | F14: 55 | G14: 0 | H14: 220 | I14: 0 | J14: 0 | K14: 4 | L14: 220 | M14: 159.6 | N14: 60.4 | O14: 26.77 | P14: 33.63 | Q14: Walk-in | R14: Cash | S14: Ghaziabad
... A23: MM-0022 | B23: 45785 | C23: Cooking Oil 1L | D23: Groceries | E23: 1 | F23: 145 | G23: 0 | H23: 145 | I23: 0 | J23: 0 | K23: 1 | L23: 145 | M23: 97.78 | N23: 47.22 | O23: 9.27 | P23: 37.95 | Q23: Member | R23: UPI | S23: Ghaziabad
A24: MM-0023 | B24: 45920 | C24: Rice 5kg | D24: Groceries | E24: 4 | F24: 420 | G24: 5 | H24: 1596 | I24: 0 | J24: 0 | K24: 4 | L24: 1596 | M24: 1069.6 | N24: 526.4 | O24: 168.64 | P24: 357.76 | Q24: Walk-in | R24: Wallet | S24: Noida
A25: MM-0024 | B25: 45694 | C25: Dishwash Liquid 500ml | D25: Household | E25: 3 | F25: 95 | G25: 0 | H25: 285 | I25: 0 | J25: 0 | K25: 3 | L25: 285 | M25: 193.24 | N25: 91.76 | O25: 34.71 | P25: 57.05 | Q25: Walk-in | R25: Card | S25: Gurugram
A26: MM-0025 | B26: 45818 | C26: Chocolate Bar | D26: Snacks | E26: 2 | F26: 55 | G26: 5 | H26: 104.5 | I26: 0 | J26: 0 | K26: 2 | L26: 104.5 | M26: 86.02 | N26: 18.48 | O26: 8.61 | P26: 9.87 | Q26: Walk-in | R26: Wallet | S26: Gurugram
A27: MM-0026 | B27: 45810 | C27: Floor Cleaner 1L | D27: Household | E27: 1 | F27: 125 | G27: 10 | H27: 112.5 | I27: 1 | J27: 112.5 | K27: 0 | L27: 0 | M27: 0 | N27: 0 | O27: 0 | P27: 0 | Q27: Regular | R27: UPI | S27: Ghaziabad
A28: MM-0027 | B28: 45946 | C28: Toothpaste 150g | D28: Personal Care | E28: 3 | F28: 110 | G28: 2 | H28: 323.4 | I28: 0 | J28: 0 | K28: 3 | L28: 323.4 | M28: 251.11 | N28: 72.29 | O28: 34.6 | P28: 37.69 | Q28: New | R28: Cash | S28: Ghaziabad
A29: MM-0028 | B29: 45679 | C29: Notebook | D29: Stationery | E29: 2 | F29: 65 | G29: 5 | H29: 123.5 | I29: 0 | J29: 0 | K29: 2 | L29: 123.5 | M29: 97.94 | N29: 25.56 | O29: 11.54 | P29: 14.02 | Q29: New | R29: UPI | S29: Noida
A30: MM-0029 | B30: 45941 | C30: Coffee 200g | D30: Beverages | E30: 2 | F30: 180 | G30: 10 | H30: 324 | I30: 0 | J30: 0 | K30: 2 | L30: 324 | M30: 249.96 | N30: 74.04 | O30: 29.23 | P30: 44.81 | Q30: Member | R30: Wallet | S30: Delhi
A31: MM-0030 | B31: 45829 | C31: Tea 250g | D31: Beverages | E31: 2 | F31: 125 | G31: 0 | H31: 250 | I31: 0 | J31: 0 | K31: 2 | L31: 250 | M31: 189.32 | N31: 60.68 | O31: 13.37 | P31: 47.31 | Q31: Walk-in | R31: UPI | S31: Delhi
A32: MM-0031 | B32: 45838 | C32: Toothpaste 150g | D32: Personal Care | E32: 6 | F32: 110 | G32: 0 | H32: 660 | I32: 0 | J32: 0 | K32: 6 | L32: 660 | M32: 411.65 | N32: 248.35 | O32: 55.61 | P32: 192.74 | Q32: Member | R32: Card | S32: Ghaziabad
A33: MM-0032 | B33: 45675 | C33: Rice 5kg | D33: groceries | E33: 1 | F33: 420 | G33: 0 | H33: 420 | I33: 0 | J33: 0 | K33: 1 | L33: 420 | M33: 279.64 | N33: 140.36 | O33: 37.31 | P33: 103.05 | Q33: Regular | R33: UPI | S33: Gurugram
A34: MM-0033 | B34: 45812 | C34: Sugar 1kg | D34: Groceries | E34: 3 | F34: 52 | G34: 0 | H34: 156 | I34: 0 | J34: 0 | K34: 3 | L34: 156 | M34: 119.75 | N34: 36.25 | O34: 9.55 | P34: 26.7 | Q34: New | R34: UPI | S34: Noida
A35: MM-0034 | B35: 45683 | C35: Floor Cleaner 1L | D35: Household | E35: 5 | F35: 125 | G35: 0 | H35: 625 | I35: 0 | J35: 0 | K35: 5 | L35: 625 | M35: 493.84 | N35: 131.16 | O35: 46.08 | P35: 85.08 | Q35: Member | R35: UPI
A36: MM-0035 | B36: 45799 | C36: Soap Bar | D36: Personal Care | E36: 1 | F36: 38 | G36: 0 | H36: 38 | I36: 0 | J36: 0 | K36: 1 | L36: 38 | M36: 29.29 | N36: 8.71 | O36: 2.12 | P36: 6.59 | Q36: Walk-in | R36: Card | S36: Gurugram
A37: MM-0036 | B37: 45720 | C37: Laundry Detergent 2kg | D37: Household | E37: 2 | F37: 280 | G37: 0 | H37: 560 | I37: 0 | J37: 0 | K37: 2 | L37: 560 | M37: 424.92 | N37: 135.08 | O37: 48.86 | P37: 86.22 | Q37: New | R37: Cash | S37: Noida
A38: MM-0037 | B38: 45710 | C38: Floor Cleaner 1L | D38: Household | E38: 1 | F38: 125 | G38: 5 | H38: 118.75 | I38: 0 | J38: 0 | K38: 1 | L38: 118.75 | M38: 83.89 | N38: 34.86 | O38: 10.9 | P38: 23.96 | Q38: Walk-in | R38: Wallet | S38: Ghaziabad
A39: MM-0038 | B39: 45965 | C39: Tea 250g | D39: Beverages | E39: 3 | F39: 125 | G39: 5 | H39: 356.25 | I39: 0 | J39: 0 | K39: 3 | L39: 356.25 | M39: 237.49 | N39: 118.76 | O39: 37.75 | P39: 81.01 | Q39: Walk-in | R39: Cash | S39: Noida
A40: MM-0039 | B40: 45886 | C40: Soft Drink 750ml | D40: Beverages | E40: 2 | F40: 48 | G40: 5 | H40: 91.2 | I40: 0 | J40: 0 | K40: 2 | L40: 91.2 | M40: 62.47 | N40: 28.73 | O40: 5.13 | P40: 23.6 | Q40: New | R40: Cash | S40: Noida
A41: MM-0040 | B41: 45775 | C41: Chocolate Bar | D41: Snacks | E41: 4 | F41: 55 | G41: 0 | H41: 220 | I41: 0 | J41: 0 | K41: 4 | L41: 220 | M41: 184.72 | N41: 35.28 | O41: 15.22 | P41: 20.06 | R41: Cash | S41: Ghaziabad
A42: MM-0041 | B42: 45904 | C42: Soap Bar | D42: Personal Care | E42: 2 | F42: 38 | G42: 15 | H42: 64.6 | I42: 0 | J42: 0 | K42: 2 | L42: 64.6 | M42: 51.49 | N42: 13.11 | O42: 6.39 | P42: 6.72 | Q42: Member | R42: Wallet | S42: Noida
A43: MM-0042 | B43: 45751 | C43: Dishwash Liquid 500ml | D43: Household | E43: 1 | F43: 95 | G43: 0 | H43: 95 | I43: 0 | J43: 0 | K43: 1 | L43: 95 | M43: 66.69 | N43: 28.31 | O43: 5.47 | P43: 22.84 | Q43: New | R43: UPI | S43: Ghaziabad
A44: MM-0043 | B44: 45879 | C44: Tea 250g | D44: Beverages | E44: 3 | F44: 125 | G44: 0 | H44: 375 | I44: 0 | J44: 0 | K44: 3 | L44: 375 | M44: 276.75 | N44: 98.25 | O44: 23.95 | P44: 74.3 | Q44: Regular | R44: Card | S44: Noida
A45: MM-0044 | B45: 45914 | C45: Soft Drink 750ml | D45: Beverages | E45: 8 | F45: 48 | G45: 10 | H45: 345.6 | I45: 1 | J45: 43.2 | K45: 7 | L45: 302.4 | M45: 206.42 | N45: 95.98 | O45: 27.29 | P45: 68.69 | Q45: Walk-in | R45: Cash | S45: Delhi
A46: MM-0045 | B46: 45997 | C46: Cooking Oil 1L | D46: Groceries | E46: 3 | F46: 145 | G46: 10 | H46: 391.5 | I46: 0 | J46: 0 | K46: 3 | L46: 391.5 | M46: 331.45 | N46: 60.05 | O46: 39.51 | P46: 20.54 | Q46: Walk-in | R46: Wallet | S46: Noida
A47: MM-0046 | B47: 45825 | C47: Sugar 1kg | D47: Groceries | E47: 4 | F47: 52 | G47: 0 | H47: 208 | I47: 0 | J47: 0 | K47: 4 | L47: 208 | M47: 156.2 | N47: 51.8 | O47: 16.82 | P47: 34.98 | Q47: New | R47: Card | S47: Ghaziabad
A48: MM-0047 | B48: 45747 | C48: Soap Bar | D48: Personal Care | E48: 1 | F48: 38 | G48: 0 | H48: 38 | I48: 0 | J48: 0 | K48: 1 | L48: 38 | M48: 23.92 | N48: 14.08 | O48: 2.92 | P48: 11.16 | Q48: Walk-in | R48: Cash | S48: Noida
A49: MM-0048 | B49: 45732 | C49: Soft Drink 750ml | D49: Beverages | E49: 1 | F49: 48 | G49: 5 | H49: 45.6 | I49: 0 | J49: 0 | K49: 1 | L49: 45.6 | M49: 31.36 | N49: 14.24 | O49: 4.82 | P49: 9.42 | Q49: Regular | R49: Wallet | S49: Ghaziabad
A50: MM-0049 | B50: 45753 | C50: Cooking Oil 1L | D50: Groceries | E50: 1 | F50: 145 | G50: 5 | H50: 137.75 | I50: 0 | J50: 0 | K50: 1 | L50: 137.75 | M50: 112.08 | N50: 25.67 | O50: 11.43 | P50: 14.24 | Q50: Walk-in | R50: Card | S50: Noida
A51: MM-0050 | B51: 45719 | C51: Tea 250g | D51: Beverages | E51: 2 | F51: 125 | G51: 2 | H51: 245 | I51: 0 | J51: 0 | K51: 2 | L51: 245 | M51: 195.41 | N51: 49.59 | O51: 19.65 | P51: 29.94 | Q51: Walk-in | R51: Wallet | S51: Delhi
A52: MM-0051 | B52: 45941 | C52: Soap Bar | D52: Personal Care | E52: 6 | F52: 38 | G52: 0 | H52: 228 | I52: 0 | J52: 0 | K52: 6 | L52: 228 | M52: 141.95 | N52: 86.05 | O52: 13.07 | P52: 72.98 | Q52: New | R52: Card | S52: Ghaziabad
A53: MM-0052 | B53: 45710 | C53: Notebook | D53: Stationery | E53: 3 | F53: 65 | G53: 2 | H53: 191.1 | I53: 0 | J53: 0 | K53: 3 | L53: 191.1 | M53: 139.05 | N53: 52.05 | O53: 14.58 | P53: 37.47 | Q53: Member | R53: Wallet | S53: Delhi
... A81: MM-0080 | B81: 45682 | C81: Tea 250g | D81: Beverages | E81: 1 | F81: 125 | G81: 2 | H81: 122.5 | I81: 0 | J81: 0 | K81: 1 | L81: 122.5 | M81: 100.67 | N81: 21.83 | O81: 11.37 | P81: 10.46 | Q81: Regular | R81: Cash | S81: Ghaziabad
A82: MM-0081 | B82: 45768 | C82: Cooking Oil 1L | D82: Groceries | E82: 2 | F82: 145 | G82: 2 | H82: 284.2 | I82: 0 | J82: 0 | K82: 2 | L82: 284.2 | M82: 208.92 | N82: 75.28 | O82: 30.96 | P82: 44.32 | Q82: Walk-in | S82: Delhi
A83: MM-0082 | B83: 45972 | C83: Shampoo 340ml | D83: Personal Care | E83: 1 | F83: 210 | G83: 0 | H83: 210 | I83: 0 | J83: 0 | K83: 1 | L83: 210 | M83: 148.5 | N83: 61.5 | O83: 20.09 | P83: 41.41 | Q83: Regular | R83: UPI | S83: Delhi
A84: MM-0083 | B84: 45975 | C84: RICE 5KG | D84: Groceries | E84: 1 | F84: 420 | G84: 0 | H84: 420 | I84: 0 | J84: 0 | K84: 1 | L84: 420 | M84: 297.23 | N84: 122.77 | O84: 49.59 | P84: 73.18 | Q84: New | R84: Card | S84: Ghaziabad
A85: MM-0084 | B85: 45979 | C85: Chocolate Bar | D85: Snacks | E85: 1 | F85: 55 | G85: 0 | H85: 55 | I85: 0 | J85: 0 | K85: 1 | L85: 55 | M85: 39.52 | N85: 15.48 | O85: 3.24 | P85: 12.24 | Q85: Walk-in | R85: Wallet | S85: Gurugram
A86: MM-0085 | B86: 45851 | C86: Cooking Oil 1L | D86: Groceries | E86: 1 | F86: 145 | G86: 15 | H86: 123.25 | I86: 0 | J86: 0 | K86: 1 | L86: 123.25 | M86: 90.93 | N86: 32.32 | O86: 14.26 | P86: 18.06 | Q86: Member | R86: Card | S86: Ghaziabad
A87: MM-0086 | B87: 45677 | C87: Batteries Pack | D87: Electronics | E87: 5 | F87: 85 | G87: 0 | H87: 425 | I87: 0 | J87: 0 | K87: 5 | L87: 425 | M87: 362.24 | N87: 62.76 | O87: 28.03 | P87: 34.73 | Q87: Regular | R87: Wallet | S87: Gurugram
A88: MM-0087 | B88: 45916 | C88: Rice 5kg | D88: Groceries | E88: 3 | F88: 420 | G88: 0 | H88: 1260 | I88: 0 | J88: 0 | K88: 3 | L88: 1260 | M88: 956.97 | N88: 303.03 | O88: 111.5 | P88: 191.53 | Q88: Regular | R88: UPI | S88: Noida
A89: MM-0088 | B89: 45976 | C89: Soft Drink 750ml | D89: Beverages | E89: 3 | F89: 48 | G89: 0 | H89: 144 | I89: 0 | J89: 0 | K89: 3 | L89: 144 | M89: 96.25 | N89: 47.75 | O89: 8.21 | P89: 39.54 | Q89: Regular | R89: Cash | S89: Delhi
A90: MM-0089 | B90: 45975 | C90: Chocolate Bar | D90: Snacks | E90: 3 | F90: 55 | G90: 0 | H90: 165 | I90: 0 | J90: 0 | K90: 3 | L90: 165 | M90: 118.61 | N90: 46.39 | O90: 20.52 | P90: 25.87 | Q90: Walk-in | R90: Wallet | S90: Noida
A91: MM-0090 | B91: 45977 | C91: Toothpaste 150g | D91: Personal Care | E91: 8 | F91: 110 | G91: 15 | H91: 748 | I91: 0 | J91: 0 | K91: 8 | L91: 748 | M91: 500.56 | N91: 247.44 | O91: 92.84 | P91: 154.6 | Q91: New | R91: Wallet | S91: Ghaziabad
A92: MM-0091 | B92: 45996 | C92: Potato Chips | D92: Snacks | E92: 5 | F92: 30 | G92: 5 | H92: 142.5 | I92: 0 | J92: 0 | K92: 5 | L92: 142.5 | M92: 115.69 | N92: 26.81 | O92: 9.25 | P92: 17.56 | Q92: Member | R92: UPI | S92: Noida
A93: MM-0092 | B93: 45945 | C93: Cooking Oil 1L | D93: Groceries | E93: 2 | F93: 145 | G93: 2 | H93: 284.2 | I93: 0 | J93: 0 | K93: 2 | L93: 284.2 | M93: 222.79 | N93: 61.41 | O93: 30.44 | P93: 30.97 | Q93: Member | R93: Cash | S93: Noida
A94: MM-0093 | B94: 45966 | C94: Rice 5kg | D94: Groceries | E94: 4 | F94: 420 | G94: 0 | H94: 1680 | I94: 0 | J94: 0 | K94: 4 | L94: 1680 | M94: 1135.23 | N94: 544.77 | O94: 135.59 | P94: 409.18 | Q94: Walk-in | R94: Wallet | S94: Gurugram
... A130: MM-0129 | B130: 46021 | C130: Sugar 1kg | D130: Groceries | E130: 3 | F130: 52 | G130: 0 | H130: 156 | I130: 0 | J130: 0 | K130: 3 | L130: 156 | M130: 129.85 | N130: 26.15 | O130: 13.3 | P130: 12.85 | Q130: Member | R130: Card | S130: Ghaziabad
A131: MM-0130 | B131: 45765 | C131: Floor Cleaner 1L | D131: Household | E131: 3 | F131: 125 | G131: 2 | H131: 367.5 | I131: 0 | J131: 0 | K131: 3 | L131: 367.5 | M131: 292.93 | N131: 74.57 | O131: 30.92 | P131: 43.65 | Q131: New | R131: UPI
A132: MM-0131 | B132: 45884 | C132: Sugar 1kg | D132: Groceries | E132: 6 | F132: 52 | G132: 0 | H132: 312 | I132: 0 | J132: 0 | K132: 6 | L132: 312 | M132: 258.94 | N132: 53.06 | O132: 39.04 | P132: 14.02 | Q132: Member | R132: Card | S132: Noida
A133: MM-0132 | B133: 45893 | C133: Notebook | D133: Stationery | E133: 1 | F133: 65 | G133: 0 | H133: 65 | I133: 0 | J133: 0 | K133: 1 | L133: 65 | M133: 40.89 | N133: 24.11 | O133: 6.27 | P133: 17.84 | Q133: Member | R133: Cash | S133: Noida
A134: MM-0133 | B134: 45981 | C134: Biscuits Pack | D134: Snacks | E134: 3 | F134: 40 | G134: 5 | H134: 114 | I134: 0 | J134: 0 | K134: 3 | L134: 114 | M134: 70.77 | N134: 43.23 | O134: 8.41 | P134: 34.82 | Q134: New | R134: UPI | S134: Delhi
A135: MM-0134 | B135: 45797 | C135: Dishwash Liquid 500ml | D135: Household | E135: 1 | F135: 95 | G135: 15 | H135: 80.75 | I135: 0 | J135: 0 | K135: 1 | L135: 80.75 | M135: 58.36 | N135: 22.39 | O135: 8.43 | P135: 13.96 | Q135: Member | R135: UPI | S135: Delhi
A136: MM-0135 | B136: 45990 | C136: Tea 250g | D136: Beverages | E136: 1 | F136: 125 | G136: 0 | H136: 125 | I136: 0 | J136: 0 | K136: 1 | L136: 125 | M136: 103.87 | N136: 21.13 | O136: 10.92 | P136: 10.21 | Q136: New | R136: Cash | S136: Gurugram
A137: MM-0136 | B137: 45987 | C137: Notebook | D137: Stationery | E137: 1 | F137: 65 | G137: 0 | H137: 65 | I137: 0 | J137: 0 | K137: 1 | L137: 65 | M137: 53.37 | N137: 11.63 | O137: 7.57 | P137: 4.06 | Q137: Member | R137: UPI | S137: Delhi
A138: MM-0137 | B138: 45834 | C138: Chocolate Bar | D138: Snacks | E138: 1 | F138: 55 | G138: 5 | H138: 52.25 | I138: 0 | J138: 0 | K138: 1 | L138: 52.25 | M138: 36.79 | N138: 15.46 | O138: 6.66 | P138: 8.8 | Q138: Regular | R138: Card | S138: Ghaziabad
A139: MM-0138 | B139: 45817 | C139: Floor Cleaner 1L | D139: household | E139: 1 | F139: 125 | G139: 0 | H139: 125 | I139: 0 | J139: 0 | K139: 1 | L139: 125 | M139: 100.25 | N139: 24.75 | O139: 7.79 | P139: 16.96 | Q139: Member | R139: UPI | S139: Delhi
A140: MM-0139 | B140: 45780 | C140: Laundry Detergent 2kg | D140: Household | E140: 1 | F140: 280 | G140: 10 | H140: 252 | I140: 0 | J140: 0 | K140: 1 | L140: 252 | M140: 208.26 | N140: 43.74 | O140: 20.49 | P140: 23.25 | Q140: Walk-in | R140: Cash | S140: Delhi
A141: MM-0140 | B141: 45883 | C141: Sugar 1kg | D141: Groceries | E141: 8 | F141: 52 | G141: 10 | H141: 374.4 | I141: 0 | J141: 0 | K141: 8 | L141: 374.4 | M141: 304.87 | N141: 69.53 | O141: 35.22 | P141: 34.31 | Q141: Walk-in | R141: Wallet | S141: Gurugram
A142: MM-0141 | B142: 45941 | C142: Coffee 200g | D142: Beverages | E142: 2 | F142: 180 | G142: 5 | H142: 342 | I142: 0 | J142: 0 | K142: 2 | L142: 342 | M142: 252.74 | N142: 89.26 | O142: 23.12 | P142: 66.14 | Q142: Regular | R142: Cash | S142: Delhi
A143: MM-0142 | B143: 46011 | C143: LED Bulb 9W | D143: Electronics | E143: 3 | F143: 120 | G143: 0 | H143: 360 | I143: 0 | J143: 0 | K143: 3 | L143: 360 | M143: 274.38 | N143: 85.62 | O143: 28.02 | P143: 57.6 | Q143: Walk-in | R143: Card | S143: Delhi
A144: MM-0143 | B144: 45961 | C144: Soap Bar | D144: Personal Care | E144: 4 | F144: 38 | G144: 0 | H144: 152 | I144: 0 | J144: 0 | K144: 4 | L144: 152 | M144: 125.91 | N144: 26.09 | O144: 9.51 | P144: 16.58 | Q144: Regular | R144: Cash | S144: Gurugram
A145: MM-0144 | B145: 45892 | C145: Soap Bar | D145: Personal Care | E145: 4 | F145: 38 | G145: 2 | H145: 148.96 | I145: 0 | J145: 0 | K145: 4 | L145: 148.96 | M145: 114.47 | N145: 34.49 | O145: 9.34 | P145: 25.15 | Q145: Regular | S145: Delhi
A146: MM-0145 | B146: 45739 | C146: Batteries Pack | D146: Electronics | E146: 6 | F146: 85 | G146: 0 | H146: 510 | I146: 0 | J146: 0 | K146: 6 | L146: 510 | M146: 416.56 | N146: 93.44 | O146: 62.58 | P146: 30.86 | Q146: Walk-in | R146: UPI | S146: Noida
A147: MM-0146 | B147: 45674 | C147: Soap Bar | D147: Personal Care | E147: 3 | F147: 38 | G147: 0 | H147: 114 | I147: 0 | J147: 0 | K147: 3 | L147: 114 | M147: 78.53 | N147: 35.47 | O147: 14.65 | P147: 20.82 | Q147: Walk-in | R147: Card | S147: Noida
A148: MM-0147 | B148: 45976 | C148: Soap Bar | D148: Personal Care | E148: 5 | F148: 38 | G148: 0 | H148: 190 | I148: 0 | J148: 0 | K148: 5 | L148: 190 | M148: 152.5 | N148: 37.5 | O148: 24.14 | P148: 13.36 | Q148: Walk-in | R148: Wallet | S148: Gurugram
A149: MM-0148 | B149: 45674 | C149: Tea 250g | D149: Beverages | E149: 1 | F149: 125 | G149: 10 | H149: 112.5 | I149: 0 | J149: 0 | K149: 1 | L149: 112.5 | M149: 88.32 | N149: 24.18 | O149: 8.33 | P149: 15.85 | Q149: Walk-in | R149: UPI | S149: Delhi
A150: MM-0149 | B150: 45832 | C150: Soft Drink 750ml | D150: Beverages | E150: 3 | F150: 48 | G150: 0 | H150: 144 | I150: 0 | J150: 0 | K150: 3 | L150: 144 | M150: 91.86 | N150: 52.14 | O150: 18.61 | P150: 33.53 | Q150: Regular | R150: Wallet | S150: Ghaziabad
A151: MM-0150 | B151: 45715 | C151: Sugar 1kg | D151: Groceries | E151: 3 | F151: 52 | G151: 0 | H151: 156 | I151: 0 | J151: 0 | K151: 3 | L151: 156 | M151: 99.18 | N151: 56.82 | O151: 12.44 | P151: 44.38 | R151: UPI | S151: Noida
A152: MM-0151 | B152: 45942 | C152: Toothpaste 150g | D152: Personal Care | E152: 3 | F152: 110 | G152: 10 | H152: 297 | I152: 0 | J152: 0 | K152: 3 | L152: 297 | M152: 191.42 | N152: 105.58 | O152: 27.37 | P152: 78.21 | Q152: Regular | R152: Card | S152: Ghaziabad
A153: MM-0152 | B153: 45749 | C153: Wheat Flour 5kg | D153: Groceries | E153: 5 | F153: 310 | G153: 0 | H153: 1550 | I153: 0 | J153: 0 | K153: 5 | L153: 1550 | M153: 1009.86 | N153: 540.14 | O153: 196.94 | P153: 343.2 | Q153: Regular | R153: Cash | S153: Gurugram
A154: MM-0153 | B154: 45715 | C154: Dishwash Liquid 500ml | D154: Household | E154: 6 | F154: 95 | G154: 15 | H154: 484.5 | I154: 0 | J154: 0 | K154: 6 | L154: 484.5 | M154: 388.77 | N154: 95.73 | O154: 36.32 | P154: 59.41 | Q154: Walk-in | R154: UPI | S154: Gurugram
A155: MM-0154 | B155: 45865 | C155: Wheat Flour 5kg | D155: Groceries | E155: 1 | F155: 310 | G155: 0 | H155: 310 | I155: 0 | J155: 0 | K155: 1 | L155: 310 | M155: 240.68 | N155: 69.32 | O155: 36.94 | P155: 32.38 | R155: Wallet | S155: Ghaziabad
A156: MM-0155 | B156: 45856 | C156: Toothpaste 150g | D156: Personal Care | E156: 1 | F156: 110 | G156: 0 | H156: 110 | I156: 0 | J156: 0 | K156: 1 | L156: 110 | M156: 72.26 | N156: 37.74 | O156: 10.17 | P156: 27.57 | Q156: Member | R156: Cash | S156: Ghaziabad
A157: MM-0156 | B157: 45863 | C157: Shampoo 340ml | D157: Personal Care | E157: 1 | F157: 210 | G157: 10 | H157: 189 | I157: 0 | J157: 0 | K157: 1 | L157: 189 | M157: 145.15 | N157: 43.85 | O157: 16.73 | P157: 27.12 | Q157: Member | R157: Cash | S157: Noida
A158: MM-0157 | B158: 45774 | C158: Shampoo 340ml | D158: Personal Care | E158: 2 | F158: 210 | G158: 2 | H158: 411.6 | I158: 0 | J158: 0 | K158: 2 | L158: 411.6 | M158: 277.47 | N158: 134.13 | O158: 42.03 | P158: 92.1 | Q158: New | R158: Wallet | S158: Ghaziabad
A159: MM-0158 | B159: 45752 | C159: Mineral Water 1L | D159: Beverages | E159: 10 | F159: 20 | G159: 0 | H159: 200 | I159: 0 | J159: 0 | K159: 10 | L159: 200 | M159: 146.3 | N159: 53.7 | O159: 16.33 | P159: 37.37 | Q159: New | R159: Wallet | S159: Gurugram
A160: MM-0159 | B160: 45698 | C160: Soap Bar | D160: Personal Care | E160: 5 | F160: 38 | G160: 15 | H160: 161.5 | I160: 0 | J160: 0 | K160: 5 | L160: 161.5 | M160: 135.32 | N160: 26.18 | O160: 17.75 | P160: 8.43 | Q160: Regular | R160: Wallet | S160: Delhi
A161: MM-0160 | B161: 45899 | C161: Toothpaste 150g | D161: Personal Care | E161: 1 | F161: 110 | G161: 0 | H161: 110 | I161: 0 | J161: 0 | K161: 1 | L161: 110 | M161: 84.52 | N161: 25.48 | O161: 10.42 | P161: 15.06 | Q161: Walk-in | R161: Cash | S161: Noida
A162: MM-0161 | B162: 45851 | C162: Rice 5kg | D162: Groceries | E162: 1 | F162: 420 | G162: 0 | H162: 420 | I162: 0 | J162: 0 | K162: 1 | L162: 420 | M162: 263.75 | N162: 156.25 | O162: 34.34 | P162: 121.91 | Q162: New | R162: Card | S162: Noida
A163: MM-0162 | B163: 45974 | C163: Toothpaste 150g | D163: Personal Care | E163: 4 | F163: 110 | G163: 5 | H163: 418 | I163: 0 | J163: 0 | K163: 4 | L163: 418 | M163: 263.29 | N163: 154.71 | O163: 52.72 | P163: 101.99 | Q163: Member | R163: Card | S163: Noida
A164: MM-0163 | B164: 45835 | C164: Chocolate Bar | D164: Snacks | E164: 8 | F164: 55 | G164: 0 | H164: 440 | I164: 0 | J164: 0 | K164: 8 | L164: 440 | M164: 329.96 | N164: 110.04 | O164: 52.66 | P164: 57.38 | Q164: Walk-in | R164: UPI | S164: Ghaziabad
A165: MM-0164 | B165: 45660 | C165: LAUNDRY DETERGENT 2KG | D165: Household | E165: 5 | F165: 280 | G165: 0 | H165: 1400 | I165: 0 | J165: 0 | K165: 5 | L165: 1400 | M165: 1168.66 | N165: 231.34 | O165: 161.54 | P165: 69.8 | Q165: Member | R165: Cash | S165: Ghaziabad
A166: MM-0165 | B166: 45900 | C166: Soft Drink 750ml | D166: Beverages | E166: 2 | F166: 48 | G166: 5 | H166: 91.2 | I166: 0 | J166: 0 | K166: 2 | L166: 91.2 | M166: 69.53 | N166: 21.67 | O166: 8.06 | P166: 13.61 | Q166: New | R166: Card | S166: Gurugram
A167: MM-0166 | B167: 45739 | C167: Toothpaste 150g | D167: Personal Care | E167: 2 | F167: 110 | G167: 0 | H167: 220 | I167: 0 | J167: 0 | K167: 2 | L167: 220 | M167: 178.1 | N167: 41.9 | O167: 19.77 | P167: 22.13 | Q167: New | R167: UPI | S167: Gurugram
... A171: MM-0170 | B171: 45925 | C171: Laundry Detergent 2kg | D171: Household | E171: 6 | F171: 280 | G171: 0 | H171: 1680 | I171: 0 | J171: 0 | K171: 6 | L171: 1680 | M171: 1153.22 | N171: 526.78 | O171: 206.62 | P171: 320.16 | Q171: Member | R171: Cash | S171: Noida
A172: MM-0171 | B172: 45955 | C172: Potato Chips | D172: Snacks | E172: 5 | F172: 30 | G172: 0 | H172: 150 | I172: 0 | J172: 0 | K172: 5 | L172: 150 | M172: 120.94 | N172: 29.06 | O172: 14.72 | P172: 14.34 | Q172: Walk-in | R172: UPI | S172: Noida
A173: MM-0172 | B173: 45768 | C173: WHEAT FLOUR 5KG | D173: Groceries | E173: 1 | F173: 310 | G173: 10 | H173: 279 | I173: 0 | J173: 0 | K173: 1 | L173: 279 | M173: 205.94 | N173: 73.06 | O173: 33.39 | P173: 39.67 | Q173: New | R173: Wallet | S173: Gurugram
...

Sheet Cleaned Data
A1: Invoice ID | B1: Date | C1: Product | D1: Category | E1: Qty | F1: Unit Price (₹) | G1: Discount (%) | H1: Sales (₹) | I1: Return Qty | J1: Sales Return (₹) | K1: Net Qty | L1: Net Sales (₹) | M1: COGS (₹) | N1: Gross Profit (₹) | O1: Gross Profit Margin | P1: Operating Expense (₹) | Q1: Net Profit (₹) | R1: Net Profit Margin | S1: Customer Type | T1: Payment Method | U1: City
A2: MM-0001 | B2: 45872 | C2: Biscuits Pack | D2: Snacks | E2: 5 | F2: 40 | G2: 0 | H2: 200 | I2: 0 | J2: 0 | K2: 5 | L2: 200 | M2: 161.43 | N2: 38.57 | O2: =N2/L2 -> 0.19285 | P2: 17.13 | Q2: 21.44 | R2: =Q2/L2 -> 0.1072 | S2: Member | T2: Card | U2: Ghaziabad
A3: MM-0002 | B3: 45849 | C3: Cooking Oil 1L | D3: Groceries | E3: 1 | F3: 145 | G3: 0.02 | H3: 142.1 | I3: 0 | J3: 0 | K3: 1 | L3: 142.1 | M3: 90.03 | N3: 52.07 | O3: =N3/L3 -> 0.36643209 | P3: 17.77 | Q3: 34.3 | R3: =Q3/L3 -> 0.24137931 | S3: Walk-in | T3: Cash | U3: Delhi
A4: MM-0003 | B4: 45845 | C4: Shampoo 340ml | D4: Personal Care | E4: 3 | F4: 210 | G4: 0 | H4: 630 | I4: 0 | J4: 0 | K4: 3 | L4: 630 | M4: 394.09 | N4: 235.91 | O4: =N4/L4 -> 0.37446032 | P4: 51.65 | Q4: 184.26 | R4: =Q4/L4 -> 0.29247619 | S4: Walk-in | T4: Card | U4: Noida
A5: MM-0004 | B5: 45792 | C5: Laundry Detergent 2kg | D5: Household | E5: 3 | F5: 280 | G5: 0 | H5: 840 | I5: 0 | J5: 0 | K5: 3 | L5: 840 | M5: 719.02 | N5: 120.98 | O5: =N5/L5 -> 0.14402381 | P5: 99.79 | Q5: 21.19 | R5: =Q5/L5 -> 0.02522619 | S5: Regular | T5: Cash | U5: Gurugram
A6: MM-0005 | B6: 45820 | C6: LED Bulb 9W | D6: Electronics | E6: 8 | F6: 120 | G6: 0.15 | H6: 816 | I6: 0 | J6: 0 | K6: 8 | L6: 816 | M6: 664.24 | N6: 151.76 | O6: =N6/L6 -> 0.18598039 | P6: 47.18 | Q6: 104.58 | R6: =Q6/L6 -> 0.12816176 | S6: Walk-in | T6: Card | U6: Ghaziabad
A7: MM-0006 | B7: 45659 | C7: Biscuits Pack | D7: Snacks | E7: 3 | F7: 40 | G7: 0.05 | H7: 114 | I7: 0 | J7: 0 | K7: 3 | L7: 114 | M7: 75.42 | N7: 38.58 | O7: =N7/L7 -> 0.33842105 | P7: 7.36 | Q7: 31.22 | R7: =Q7/L7 -> 0.27385965 | S7: New | T7: UPI | U7: Noida
A8: MM-0007 | B8: 45927 | C8: Soft Drink 750ml | D8: Beverages | E8: 3 | F8: 48 | G8: 0 | H8: 144 | I8: 0 | J8: 0 | K8: 3 | L8: 144 | M8: 118.39 | N8: 25.61 | O8: =N8/L8 -> 0.17784722 | P8: 11.75 | Q8: 13.86 | R8: =Q8/L8 -> 0.09625 | S8: Member | T8: Wallet | U8: Gurugram
A9: MM-0008 | B9: 45710 | C9: Potato Chips | D9: Snacks | E9: 3 | F9: 30 | G9: 0 | H9: 90 | I9: 0 | J9: 0 | K9: 3 | L9: 90 | M9: 76.56 | N9: 13.44 | O9: =N9/L9 -> 0.14933333 | P9: 9.88 | Q9: 3.56 | R9: =Q9/L9 -> 0.039555556 | S9: Walk-in | T9: UPI | U9: Delhi
A10: MM-0009 | B10: 45793 | C10: Soap Bar | D10: Personal Care | E10: 1 | F10: 38 | G10: 0.05 | H10: 36.1 | I10: 0 | J10: 0 | K10: 1 | L10: 36.1 | M10: 23.03 | N10: 13.07 | O10: =N10/L10 -> 0.36204986 | P10: 4.04 | Q10: 9.03 | R10: =Q10/L10 -> 0.2501385 | S10: Walk-in | T10: Card | U10: Gurugram
A11: MM-0010 | B11: 45698 | C11: Batteries Pack | D11: Electronics | E11: 4 | F11: 85 | G11: 0.05 | H11: 323 | I11: 0 | J11: 0 | K11: 4 | L11: 323 | M11: 260.05 | N11: 62.95 | O11: =N11/L11 -> 0.19489164 | P11: 25.41 | Q11: 37.54 | R11: =Q11/L11 -> 0.11622291 | S11: Walk-in | T11: Card | U11: Delhi
A12: MM-0011 | B12: 45829 | C12: Potato Chips | D12: Snacks | E12: 3 | F12: 30 | G12: 0 | H12: 90 | I12: 0 | J12: 0 | K12: 3 | L12: 90 | M12: 63.81 | N12: 26.19 | O12: =N12/L12 -> 0.291 | P12: 9.29 | Q12: 16.9 | R12: =Q12/L12 -> 0.18777778 | S12: Walk-in | T12: UPI | U12: Gurugram
A13: MM-0012 | B13: 45912 | C13: Sugar 1kg | D13: Groceries | E13: 3 | F13: 52 | G13: 0 | H13: 156 | I13: 0 | J13: 0 | K13: 3 | L13: 156 | M13: 123.42 | N13: 32.58 | O13: =N13/L13 -> 0.20884615 | P13: 14.8 | Q13: 17.78 | R13: =Q13/L13 -> 0.11397436 | S13: New | T13: Card | U13: Gurugram
... A26: MM-0025 | B26: 45818 | C26: Chocolate Bar | D26: Snacks | E26: 2 | F26: 55 | G26: 0.05 | H26: 104.5 | I26: 0 | J26: 0 | K26: 2 | L26: 104.5 | M26: 86.02 | N26: 18.48 | O26: =N26/L26 -> 0.17684211 | P26: 8.61 | Q26: 9.87 | R26: =Q26/L26 -> 0.094449761 | S26: Walk-in | T26: Wallet | U26: Gurugram
A27: MM-0026 | B27: 45810 | C27: Floor Cleaner 1L | D27: Household | E27: 1 | F27: 125 | G27: 0.1 | H27: 112.5 | I27: 1 | J27: 112.5 | K27: 0 | L27: 0 | M27: 0 | N27: 0 | O27: 0 | P27: 0 | Q27: 0 | R27: 0 | S27: Regular | T27: UPI | U27: Ghaziabad
A28: MM-0027 | B28: 45946 | C28: Toothpaste 150g | D28: Personal Care | E28: 3 | F28: 110 | G28: 0.02 | H28: 323.4 | I28: 0 | J28: 0 | K28: 3 | L28: 323.4 | M28: 251.11 | N28: 72.29 | O28: =N28/L28 -> 0.22353123 | P28: 34.6 | Q28: 37.69 | R28: =Q28/L28 -> 0.11654298 | S28: New | T28: Cash | U28: Ghaziabad
A29: MM-0028 | B29: 45679 | C29: Notebook | D29: Stationery | E29: 2 | F29: 65 | G29: 0.05 | H29: 123.5 | I29: 0 | J29: 0 | K29: 2 | L29: 123.5 | M29: 97.94 | N29: 25.56 | O29: =N29/L29 -> 0.20696356 | P29: 11.54 | Q29: 14.02 | R29: =Q29/L29 -> 0.11352227 | S29: New | T29: UPI | U29: Noida
A30: MM-0029 | B30: 45941 | C30: Coffee 200g | D30: Beverages | E30: 2 | F30: 180 | G30: 0.1 | H30: 324 | I30: 0 | J30: 0 | K30: 2 | L30: 324 | M30: 249.96 | N30: 74.04 | O30: =N30/L30 -> 0.22851852 | P30: 29.23 | Q30: 44.81 | R30: =Q30/L30 -> 0.13830247 | S30: Member | T30: Wallet | U30: Delhi
A31: MM-0030 | B31: 45829 | C31: Tea 250g | D31: Beverages | E31: 2 | F31: 125 | G31: 0 | H31: 250 | I31: 0 | J31: 0 | K31: 2 | L31: 250 | M31: 189.32 | N31: 60.68 | O31: =N31/L31 -> 0.24272 | P31: 13.37 | Q31: 47.31 | R31: =Q31/L31 -> 0.18924 | S31: Walk-in | T31: UPI | U31: Delhi
A32: MM-0031 | B32: 45838 | C32: Toothpaste 150g | D32: Personal Care | E32: 6 | F32: 110 | G32: 0 | H32: 660 | I32: 0 | J32: 0 | K32: 6 | L32: 660 | M32: 411.65 | N32: 248.35 | O32: =N32/L32 -> 0.37628788 | P32: 55.61 | Q32: 192.74 | R32: =Q32/L32 -> 0.2920303 | S32: Member | T32: Card | U32: Ghaziabad
A33: MM-0032 | B33: 45675 | C33: Rice 5kg | D33: Groceries | E33: 1 | F33: 420 | G33: 0 | H33: 420 | I33: 0 | J33: 0 | K33: 1 | L33: 420 | M33: 279.64 | N33: 140.36 | O33: =N33/L33 -> 0.33419048 | P33: 37.31 | Q33: 103.05 | R33: =Q33/L33 -> 0.24535714 | S33: Regular | T33: UPI | U33: Gurugram
A34: MM-0033 | B34: 45812 | C34: Sugar 1kg | D34: Groceries | E34: 3 | F34: 52 | G34: 0 | H34: 156 | I34: 0 | J34: 0 | K34: 3 | L34: 156 | M34: 119.75 | N34: 36.25 | O34: =N34/L34 -> 0.23237179 | P34: 9.55 | Q34: 26.7 | R34: =Q34/L34 -> 0.17115385 | S34: New | T34: UPI | U34: Noida
A35: MM-0034 | B35: 45683 | C35: Floor Cleaner 1L | D35: Household | E35: 5 | F35: 125 | G35: 0 | H35: 625 | I35: 0 | J35: 0 | K35: 5 | L35: 625 | M35: 493.84 | N35: 131.16 | O35: =N35/L35 -> 0.209856 | P35: 46.08 | Q35: 85.08 | R35: =Q35/L35 -> 0.136128 | S35: Member | T35: UPI | U35: Unknown
A36: MM-0035 | B36: 45799 | C36: Soap Bar | D36: Personal Care | E36: 1 | F36: 38 | G36: 0 | H36: 38 | I36: 0 | J36: 0 | K36: 1 | L36: 38 | M36: 29.29 | N36: 8.71 | O36: =N36/L36 -> 0.22921053 | P36: 2.12 | Q36: 6.59 | R36: =Q36/L36 -> 0.17342105 | S36: Walk-in | T36: Card | U36: Gurugram
A37: MM-0036 | B37: 45720 | C37: Laundry Detergent 2kg | D37: Household | E37: 2 | F37: 280 | G37: 0 | H37: 560 | I37: 0 | J37: 0 | K37: 2 | L37: 560 | M37: 424.92 | N37: 135.08 | O37: =N37/L37 -> 0.24121429 | P37: 48.86 | Q37: 86.22 | R37: =Q37/L37 -> 0.15396429 | S37: New | T37: Cash | U37: Noida
A38: MM-0037 | B38: 45710 | C38: Floor Cleaner 1L | D38: Household | E38: 1 | F38: 125 | G38: 0.05 | H38: 118.75 | I38: 0 | J38: 0 | K38: 1 | L38: 118.75 | M38: 83.89 | N38: 34.86 | O38: =N38/L38 -> 0.29355789 | P38: 10.9 | Q38: 23.96 | R38: =Q38/L38 -> 0.20176842 | S38: Walk-in | T38: Wallet | U38: Ghaziabad
A39: MM-0038 | B39: 45965 | C39: Tea 250g | D39: Beverages | E39: 3 | F39: 125 | G39: 0.05 | H39: 356.25 | I39: 0 | J39: 0 | K39: 3 | L39: 356.25 | M39: 237.49 | N39: 118.76 | O39: =N39/L39 -> 0.3333614 | P39: 37.75 | Q39: 81.01 | R39: =Q39/L39 -> 0.22739649 | S39: Walk-in | T39: Cash | U39: Noida
... A57: MM-0056 | B57: 46021 | C57: Floor Cleaner 1L | D57: Household | E57: 8 | F57: 125 | G57: 0.15 | H57: 850 | I57: 0 | J57: 0 | K57: 8 | L57: 850 | M57: 680.69 | N57: 169.31 | O57: =N57/L57 -> 0.19918824 | P57: 48.18 | Q57: 121.13 | R57: =Q57/L57 -> 0.14250588 | S57: New | T57: Card | U57: Gurugram
A58: MM-0057 | B58: 45805 | C58: Soft Drink 750ml | D58: Beverages | E58: 6 | F58: 48 | G58: 0 | H58: 288 | I58: 6 | J58: 288 | K58: 0 | L58: 0 | M58: 0 | N58: 0 | O58: 0 | P58: 0 | Q58: 0 | R58: 0 | S58: Walk-in | T58: Wallet | U58: Delhi
A59: MM-0058 | B59: 45969 | C59: Chocolate Bar | D59: Snacks | E59: 4 | F59: 55 | G59: 0.02 | H59: 215.6 | I59: 0 | J59: 0 | K59: 4 | L59: 215.6 | M59: 145.96 | N59: 69.64 | O59: =N59/L59 -> 0.32300557 | P59: 19.02 | Q59: 50.62 | R59: =Q59/L59 -> 0.23478664 | S59: Regular | T59: UPI | U59: Delhi
A60: MM-0059 | B60: 45870 | C60: Coffee 200g | D60: Beverages | E60: 5 | F60: 180 | G60: 0.15 | H60: 765 | I60: 0 | J60: 0 | K60: 5 | L60: 765 | M60: 576.38 | N60: 188.62 | O60: =N60/L60 -> 0.24656209 | P60: 40.91 | Q60: 147.71 | R60: =Q60/L60 -> 0.19308497 | S60: Member | T60: Wallet | U60: Delhi
A61: MM-0060 | B61: 45658 | C61: Cooking Oil 1L | D61: Groceries | E61: 3 | F61: 145 | G61: 0.15 | H61: 369.75 | I61: 0 | J61: 0 | K61: 3 | L61: 369.75 | M61: 275.66 | N61: 94.09 | O61: =N61/L61 -> 0.25446924 | P61: 39.07 | Q61: 55.02 | R61: =Q61/L61 -> 0.14880325 | S61: Regular | T61: UPI | U61: Noida
A62: MM-0061 | B62: 45813 | C62: Sugar 1kg | D62: Groceries | E62: 6 | F62: 52 | G62: 0 | H62: 312 | I62: 0 | J62: 0 | K62: 6 | L62: 312 | M62: 214.48 | N62: 97.52 | O62: =N62/L62 -> 0.3125641 | P62: 37.82 | Q62: 59.7 | R62: =Q62/L62 -> 0.19134615 | S62: Regular | T62: Wallet | U62: Noida
A63: MM-0062 | B63: 45849 | C63: Cooking Oil 1L | D63: Groceries | E63: 3 | F63: 145 | G63: 0 | H63: 435 | I63: 0 | J63: 0 | K63: 3 | L63: 435 | M63: 330.63 | N63: 104.37 | O63: =N63/L63 -> 0.23993103 | P63: 55.66 | Q63: 48.71 | R63: =Q63/L63 -> 0.11197701 | S63: Member | T63: UPI | U63: Gurugram
A64: MM-0063 | B64: 45692 | C64: Floor Cleaner 1L | D64: Household | E64: 2 | F64: 125 | G64: 0 | H64: 250 | I64: 0 | J64: 0 | K64: 2 | L64: 250 | M64: 191.17 | N64: 58.83 | O64: =N64/L64 -> 0.23532 | P64: 15.16 | Q64: 43.67 | R64: =Q64/L64 -> 0.17468 | S64: Regular | T64: UPI | U64: Noida
A65: MM-0064 | B65: 46022 | C65: Batteries Pack | D65: Electronics | E65: 4 | F65: 85 | G65: 0.02 | H65: 333.2 | I65: 0 | J65: 0 | K65: 4 | L65: 333.2 | M65: 240.03 | N65: 93.17 | O65: =N65/L65 -> 0.27962185 | P65: 39.75 | Q65: 53.42 | R65: =Q65/L65 -> 0.16032413 | S65: Regular | T65: Card | U65: Ghaziabad
A66: MM-0065 | B66: 45874 | C66: Rice 5kg | D66: Groceries | E66: 5 | F66: 420 | G66: 0 | H66: 2100 | I66: 0 | J66: 0 | K66: 5 | L66: 2100 | M66: 1798.58 | N66: 301.42 | O66: =N66/L66 -> 0.14353333 | P66: 230.93 | Q66: 70.49 | R66: =Q66/L66 -> 0.033566667 | S66: New | T66: Card | U66: Gurugram
A67: MM-0066 | B67: 45663 | C67: Floor Cleaner 1L | D67: Household | E67: 5 | F67: 125 | G67: 0 | H67: 625 | I67: 0 | J67: 0 | K67: 5 | L67: 625 | M67: 449.72 | N67: 175.28 | O67: =N67/L67 -> 0.280448 | P67: 34.07 | Q67: 141.21 | R67: =Q67/L67 -> 0.225936 | S67: Walk-in | T67: Cash | U67: Delhi
A68: MM-0067 | B68: 45802 | C68: Tea 250g | D68: Beverages | E68: 10 | F68: 125 | G68: 0.02 | H68: 1225 | I68: 0 | J68: 0 | K68: 10 | L68: 1225 | M68: 985.58 | N68: 239.42 | O68: =N68/L68 -> 0.1954449 | P68: 144.52 | Q68: 94.9 | R68: =Q68/L68 -> 0.077469388 | S68: Regular | T68: UPI | U68: Delhi
A69: MM-0068 | B69: 45691 | C69: Toothpaste 150g | D69: Personal Care | E69: 2 | F69: 110 | G69: 0 | H69: 220 | I69: 0 | J69: 0 | K69: 2 | L69: 220 | M69: 147.34 | N69: 72.66 | O69: =N69/L69 -> 0.33027273 | P69: 24.32 | Q69: 48.34 | R69: =Q69/L69 -> 0.21972727 | S69: Walk-in | T69: Card | U69: Ghaziabad
A70: MM-0069 | B70: 45711 | C70: Biscuits Pack | D70: Snacks | E70: 4 | F70: 40 | G70: 0 | H70: 160 | I70: 0 | J70: 0 | K70: 4 | L70: 160 | M70: 128.86 | N70: 31.14 | O70: =N70/L70 -> 0.194625 | P70: 18.91 | Q70: 12.23 | R70: =Q70/L70 -> 0.0764375 | S70: Walk-in | T70: Cash | U70: Noida
... A77: MM-0076 | B77: 45730 | C77: Tea 250g | D77: Beverages | E77: 3 | F77: 125 | G77: 0 | H77: 375 | I77: 0 | J77: 0 | K77: 3 | L77: 375 | M77: 265.28 | N77: 109.72 | O77: =N77/L77 -> 0.29258667 | P77: 39.46 | Q77: 70.26 | R77: =Q77/L77 -> 0.18736 | S77: New | T77: Cash | U77: Gurugram
A78: MM-0077 | B78: 45770 | C78: Laundry Detergent 2kg | D78: Household | E78: 3 | F78: 280 | G78: 0 | H78: 840 | I78: 3 | J78: 840 | K78: 0 | L78: 0 | M78: 0 | N78: 0 | O78: 0 | P78: 0 | Q78: 0 | R78: 0 | S78: Member | T78: Cash | U78: Ghaziabad
A79: MM-0078 | B79: 46022 | C79: Laundry Detergent 2kg | D79: Household | E79: 3 | F79: 280 | G79: 0.1 | H79: 756 | I79: 0 | J79: 0 | K79: 3 | L79: 756 | M79: 511.56 | N79: 244.44 | O79: =N79/L79 -> 0.32333333 | P79: 69.93 | Q79: 174.51 | R79: =Q79/L79 -> 0.23083333 | S79: New | T79: UPI | U79: Gurugram
A80: MM-0079 | B80: 45951 | C80: Batteries Pack | D80: Electronics | E80: 4 | F80: 85 | G80: 0.1 | H80: 306 | I80: 0 | J80: 0 | K80: 4 | L80: 306 | M80: 227.3 | N80: 78.7 | O80: =N80/L80 -> 0.25718954 | P80: 17.92 | Q80: 60.78 | R80: =Q80/L80 -> 0.19862745 | S80: Member | T80: Card | U80: Gurugram
A81: MM-0080 | B81: 45682 | C81: Tea 250g | D81: Beverages | E81: 1 | F81: 125 | G81: 0.02 | H81: 122.5 | I81: 0 | J81: 0 | K81: 1 | L81: 122.5 | M81: 100.67 | N81: 21.83 | O81: =N81/L81 -> 0.17820408 | P81: 11.37 | Q81: 10.46 | R81: =Q81/L81 -> 0.085387755 | S81: Regular | T81: Cash | U81: Ghaziabad
A82: MM-0081 | B82: 45768 | C82: Cooking Oil 1L | D82: Groceries | E82: 2 | F82: 145 | G82: 0.02 | H82: 284.2 | I82: 0 | J82: 0 | K82: 2 | L82: 284.2 | M82: 208.92 | N82: 75.28 | O82: =N82/L82 -> 0.26488388 | P82: 30.96 | Q82: 44.32 | R82: =Q82/L82 -> 0.15594652 | S82: Walk-in | T82: Unknown | U82: Delhi
A83: MM-0082 | B83: 45972 | C83: Shampoo 340ml | D83: Personal Care | E83: 1 | F83: 210 | G83: 0 | H83: 210 | I83: 0 | J83: 0 | K83: 1 | L83: 210 | M83: 148.5 | N83: 61.5 | O83: =N83/L83 -> 0.29285714 | P83: 20.09 | Q83: 41.41 | R83: =Q83/L83 -> 0.19719048 | S83: Regular | T83: UPI | U83: Delhi
A84: MM-0083 | B84: 45975 | C84: Rice 5kg | D84: Groceries | E84: 1 | F84: 420 | G84: 0 | H84: 420 | I84: 0 | J84: 0 | K84: 1 | L84: 420 | M84: 297.23 | N84: 122.77 | O84: =N84/L84 -> 0.29230952 | P84: 49.59 | Q84: 73.18 | R84: =Q84/L84 -> 0.1742381 | S84: New | T84: Card | U84: Ghaziabad
A85: MM-0084 | B85: 45979 | C85: Chocolate Bar | D85: Snacks | E85: 1 | F85: 55 | G85: 0 | H85: 55 | I85: 0 | J85: 0 | K85: 1 | L85: 55 | M85: 39.52 | N85: 15.48 | O85: =N85/L85 -> 0.28145455 | P85: 3.24 | Q85: 12.24 | R85: =Q85/L85 -> 0.22254545 | S85: Walk-in | T85: Wallet | U85: Gurugram
A86: MM-0085 | B86: 45851 | C86: Cooking Oil 1L | D86: Groceries | E86: 1 | F86: 145 | G86: 0.15 | H86: 123.25 | I86: 0 | J86: 0 | K86: 1 | L86: 123.25 | M86: 90.93 | N86: 32.32 | O86: =N86/L86 -> 0.26223124 | P86: 14.26 | Q86: 18.06 | R86: =Q86/L86 -> 0.14653144 | S86: Member | T86: Card | U86: Ghaziabad
A87: MM-0086 | B87: 45677 | C87: Batteries Pack | D87: Electronics | E87: 5 | F87: 85 | G87: 0 | H87: 425 | I87: 0 | J87: 0 | K87: 5 | L87: 425 | M87: 362.24 | N87: 62.76 | O87: =N87/L87 -> 0.14767059 | P87: 28.03 | Q87: 34.73 | R87: =Q87/L87 -> 0.081717647 | S87: Regular | T87: Wallet | U87: Gurugram
A88: MM-0087 | B88: 45916 | C88: Rice 5kg | D88: Groceries | E88: 3 | F88: 420 | G88: 0 | H88: 1260 | I88: 0 | J88: 0 | K88: 3 | L88: 1260 | M88: 956.97 | N88: 303.03 | O88: =N88/L88 -> 0.2405 | P88: 111.5 | Q88: 191.53 | R88: =Q88/L88 -> 0.15200794 | S88: Regular | T88: UPI | U88: Noida
A89: MM-0088 | B89: 45976 | C89: Soft Drink 750ml | D89: Beverages | E89: 3 | F89: 48 | G89: 0 | H89: 144 | I89: 0 | J89: 0 | K89: 3 | L89: 144 | M89: 96.25 | N89: 47.75 | O89: =N89/L89 -> 0.33159722 | P89: 8.21 | Q89: 39.54 | R89: =Q89/L89 -> 0.27458333 | S89: Regular | T89: Cash | U89: Delhi
A90: MM-0089 | B90: 45975 | C90: Chocolate Bar | D90: Snacks | E90: 3 | F90: 55 | G90: 0 | H90: 165 | I90: 0 | J90: 0 | K90: 3 | L90: 165 | M90: 118.61 | N90: 46.39 | O90: =N90/L90 -> 0.28115152 | P90: 20.52 | Q90: 25.87 | R90: =Q90/L90 -> 0.15678788 | S90: Walk-in | T90: Wallet | U90: Noida
... A293: MM-0292 | B293: 45897 | C293: Potato Chips | D293: Snacks | E293: 2 | F293: 30 | G293: 0 | H293: 60 | I293: 0 | J293: 0 | K293: 2 | L293: 60 | M293: 50.27 | N293: 9.73 | O293: =N293/L293 -> 0.16216667 | P293: 5.92 | Q293: 3.81 | R293: =Q293/L293 -> 0.0635 | S293: Regular | T293: Cash | U293: Noida
A294: MM-0293 | B294: 45872 | C294: Biscuits Pack | D294: Snacks | E294: 8 | F294: 40 | G294: 0.05 | H294: 304 | I294: 8 | J294: 304 | K294: 0 | L294: 0 | M294: 0 | N294: 0 | O294: 0 | P294: 0 | Q294: 0 | R294: 0 | S294: Regular | T294: Card | U294: Ghaziabad
A295: MM-0294 | B295: 45896 | C295: LED Bulb 9W | D295: Electronics | E295: 2 | F295: 120 | G295: 0.02 | H295: 235.2 | I295: 0 | J295: 0 | K295: 2 | L295: 235.2 | M295: 191 | N295: 44.2 | O295: =N295/L295 -> 0.18792517 | P295: 13.5 | Q295: 30.7 | R295: =Q295/L295 -> 0.13052721 | S295: Walk-in | T295: Wallet | U295: Ghaziabad
A296: MM-0295 | B296: 45762 | C296: Floor Cleaner 1L | D296: Household | E296: 1 | F296: 125 | G296: 0 | H296: 125 | I296: 0 | J296: 0 | K296: 1 | L296: 125 | M296: 88.14 | N296: 36.86 | O296: =N296/L296 -> 0.29488 | P296: 12.94 | Q296: 23.92 | R296: =Q296/L296 -> 0.19136 | S296: New | T296: UPI | U296: Gurugram
A297: MM-0296 | B297: 45916 | C297: Mineral Water 1L | D297: Beverages | E297: 3 | F297: 20 | G297: 0 | H297: 60 | I297: 0 | J297: 0 | K297: 3 | L297: 60 | M297: 39.2 | N297: 20.8 | O297: =N297/L297 -> 0.34666667 | P297: 3.74 | Q297: 17.06 | R297: =Q297/L297 -> 0.28433333 | S297: Walk-in | T297: UPI | U297: Gurugram
A298: MM-0297 | B298: 45925 | C298: Wheat Flour 5kg | D298: Groceries | E298: 3 | F298: 310 | G298: 0.05 | H298: 883.5 | I298: 0 | J298: 0 | K298: 3 | L298: 883.5 | M298: 757.96 | N298: 125.54 | O298: =N298/L298 -> 0.14209394 | P298: 93.29 | Q298: 32.25 | R298: =Q298/L298 -> 0.036502547 | S298: Member | T298: Card | U298: Delhi
A299: MM-0298 | B299: 45951 | C299: Soap Bar | D299: Personal Care | E299: 2 | F299: 38 | G299: 0.1 | H299: 68.4 | I299: 0 | J299: 0 | K299: 2 | L299: 68.4 | M299: 55.67 | N299: 12.73 | O299: =N299/L299 -> 0.18611111 | P299: 5.97 | Q299: 6.76 | R299: =Q299/L299 -> 0.098830409 | S299: Walk-in | T299: Cash | U299: Noida
A300: MM-0299 | B300: 45845 | C300: Mineral Water 1L | D300: Beverages | E300: 2 | F300: 20 | G300: 0.02 | H300: 39.2 | I300: 0 | J300: 0 | K300: 2 | L300: 39.2 | M300: 26.89 | N300: 12.31 | O300: =N300/L300 -> 0.31403061 | P300: 4.43 | Q300: 7.88 | R300: =Q300/L300 -> 0.20102041 | S300: Walk-in | T300: UPI | U300: Ghaziabad
A301: MM-0300 | B301: 45817 | C301: Sugar 1kg | D301: Groceries | E301: 3 | F301: 52 | G301: 0.02 | H301: 152.88 | I301: 0 | J301: 0 | K301: 3 | L301: 152.88 | M301: 122.65 | N301: 30.23 | O301: =N301/L301 -> 0.19773679 | P301: 18.52 | Q301: 11.71 | R301: =Q301/L301 -> 0.076596023 | S301: New | T301: Card | U301: Delhi
A302: MM-0301 | B302: 45713 | C302: Cooking Oil 1L | D302: Groceries | E302: 2 | F302: 145 | G302: 0 | H302: 290 | I302: 0 | J302: 0 | K302: 2 | L302: 290 | M302: 215.41 | N302: 74.59 | O302: =N302/L302 -> 0.2572069 | P302: 29.48 | Q302: 45.11 | R302: =Q302/L302 -> 0.15555172 | S302: Regular | T302: Cash | U302: Gurugram
A303: MM-0302 | B303: 45783 | C303: Notebook | D303: Stationery | E303: 2 | F303: 65 | G303: 0 | H303: 130 | I303: 1 | J303: 65 | K303: 1 | L303: 65 | M303: 46.21 | N303: 18.79 | O303: =N303/L303 -> 0.28907692 | P303: 3.62 | Q303: 15.17 | R303: =Q303/L303 -> 0.23338462 | S303: Member | T303: Cash | U303: Delhi
A304: MM-0303 | B304: 45688 | C304: Coffee 200g | D304: Beverages | E304: 5 | F304: 180 | G304: 0 | H304: 900 | I304: 0 | J304: 0 | K304: 5 | L304: 900 | M304: 739.81 | N304: 160.19 | O304: =N304/L304 -> 0.17798889 | P304: 85.3 | Q304: 74.89 | R304: =Q304/L304 -> 0.083211111 | S304: Walk-in | T304: Cash | U304: Delhi
A305: MM-0304 | B305: 45812 | C305: LED Bulb 9W | D305: Electronics | E305: 3 | F305: 120 | G305: 0 | H305: 360 | I305: 0 | J305: 0 | K305: 3 | L305: 360 | M305: 266.87 | N305: 93.13 | O305: =N305/L305 -> 0.25869444 | P305: 29.07 | Q305: 64.06 | R305: =Q305/L305 -> 0.17794444 | S305: New | T305: UPI | U305: Gurugram
A306: MM-0305 | B306: 45779 | C306: Soft Drink 750ml | D306: Beverages | E306: 2 | F306: 48 | G306: 0 | H306: 96 | I306: 0 | J306: 0 | K306: 2 | L306: 96 | M306: 62.91 | N306: 33.09 | O306: =N306/L306 -> 0.3446875 | P306: 5.8 | Q306: 27.29 | R306: =Q306/L306 -> 0.28427083 | S306: Regular | T306: Cash | U306: Noida
... A387: MM-0386 | B387: 45807 | C387: Wheat Flour 5kg | D387: Groceries | E387: 6 | F387: 310 | G387: 0.1 | H387: 1674 | I387: 0 | J387: 0 | K387: 6 | L387: 1674 | M387: 1080.43 | N387: 593.57 | O387: =N387/L387 -> 0.35458184 | P387: 210.22 | Q387: 383.35 | R387: =Q387/L387 -> 0.22900239 | S387: Member | T387: Wallet | U387: Delhi
A388: MM-0387 | B388: 45794 | C388: Cooking Oil 1L | D388: Groceries | E388: 4 | F388: 145 | G388: 0.02 | H388: 568.4 | I388: 4 | J388: 568.4 | K388: 0 | L388: 0 | M388: 0 | N388: 0 | O388: 0 | P388: 0 | Q388: 0 | R388: 0 | S388: Walk-in | T388: Card | U388: Delhi
A389: MM-0388 | B389: 45802 | C389: Soft Drink 750ml | D389: Beverages | E389: 2 | F389: 48 | G389: 0.05 | H389: 91.2 | I389: 0 | J389: 0 | K389: 2 | L389: 91.2 | M389: 60.67 | N389: 30.53 | O389: =N389/L389 -> 0.33475877 | P389: 11.69 | Q389: 18.84 | R389: =Q389/L389 -> 0.20657895 | S389: New | T389: UPI | U389: Gurugram
A390: MM-0389 | B390: 45750 | C390: LED Bulb 9W | D390: Electronics | E390: 1 | F390: 120 | G390: 0.05 | H390: 114 | I390: 0 | J390: 0 | K390: 1 | L390: 114 | M390: 95.7 | N390: 18.3 | O390: =N390/L390 -> 0.16052632 | P390: 8.06 | Q390: 10.24 | R390: =Q390/L390 -> 0.089824561 | S390: Member | T390: Cash | U390: Gurugram
A391: MM-0390 | B391: 45825 | C391: Batteries Pack | D391: Electronics | E391: 3 | F391: 85 | G391: 0.02 | H391: 249.9 | I391: 0 | J391: 0 | K391: 3 | L391: 249.9 | M391: 193.18 | N391: 56.72 | O391: =N391/L391 -> 0.22697079 | P391: 26.77 | Q391: 29.95 | R391: =Q391/L391 -> 0.11984794 | S391: Member | T391: Cash | U391: Delhi
A392: MM-0391 | B392: 45947 | C392: Laundry Detergent 2kg | D392: Household | E392: 4 | F392: 280 | G392: 0 | H392: 1120 | I392: 0 | J392: 0 | K392: 4 | L392: 1120 | M392: 761.16 | N392: 358.84 | O392: =N392/L392 -> 0.32039286 | P392: 80.26 | Q392: 278.58 | R392: =Q392/L392 -> 0.24873214 | S392: Walk-in | T392: Card | U392: Delhi
A393: MM-0392 | B393: 45795 | C393: LED Bulb 9W | D393: Electronics | E393: 4 | F393: 120 | G393: 0.02 | H393: 470.4 | I393: 0 | J393: 0 | K393: 4 | L393: 470.4 | M393: 367.61 | N393: 102.79 | O393: =N393/L393 -> 0.21851616 | P393: 59.33 | Q393: 43.46 | R393: =Q393/L393 -> 0.092389456 | S393: New | T393: UPI | U393: Gurugram
A394: MM-0393 | B394: 45748 | C394: Batteries Pack | D394: Electronics | E394: 3 | F394: 85 | G394: 0 | H394: 255 | I394: 0 | J394: 0 | K394: 3 | L394: 255 | M394: 206.25 | N394: 48.75 | O394: =N394/L394 -> 0.19117647 | P394: 23.23 | Q394: 25.52 | R394: =Q394/L394 -> 0.10007843 | S394: New | T394: Wallet | U394: Gurugram
A395: MM-0394 | B395: 45941 | C395: Toothpaste 150g | D395: Personal Care | E395: 2 | F395: 110 | G395: 0.1 | H395: 198 | I395: 0 | J395: 0 | K395: 2 | L395: 198 | M395: 150.53 | N395: 47.47 | O395: =N395/L395 -> 0.23974747 | P395: 14.16 | Q395: 33.31 | R395: =Q395/L395 -> 0.16823232 | S395: Regular | T395: UPI | U395: Delhi
A396: MM-0395 | B396: 45887 | C396: Chocolate Bar | D396: Snacks | E396: 1 | F396: 55 | G396: 0.05 | H396: 52.25 | I396: 0 | J396: 0 | K396: 1 | L396: 52.25 | M396: 37.55 | N396: 14.7 | O396: =N396/L396 -> 0.28133971 | P396: 5.28 | Q396: 9.42 | R396: =Q396/L396 -> 0.18028708 | S396: New | T396: Wallet | U396: Ghaziabad
A397: MM-0396 | B397: 45796 | C397: LED Bulb 9W | D397: Electronics | E397: 4 | F397: 120 | G397: 0.1 | H397: 432 | I397: 0 | J397: 0 | K397: 4 | L397: 432 | M397: 274.48 | N397: 157.52 | O397: =N397/L397 -> 0.36462963 | P397: 31.7 | Q397: 125.82 | R397: =Q397/L397 -> 0.29125 | S397: New | T397: Cash | U397: Delhi
A398: MM-0397 | B398: 45786 | C398: Cooking Oil 1L | D398: Groceries | E398: 3 | F398: 145 | G398: 0 | H398: 435 | I398: 0 | J398: 0 | K398: 3 | L398: 435 | M398: 318.72 | N398: 116.28 | O398: =N398/L398 -> 0.26731034 | P398: 29.06 | Q398: 87.22 | R398: =Q398/L398 -> 0.20050575 | S398: Member | T398: Card | U398: Noida
A399: MM-0398 | B399: 45859 | C399: Coffee 200g | D399: Beverages | E399: 4 | F399: 180 | G399: 0 | H399: 720 | I399: 0 | J399: 0 | K399: 4 | L399: 720 | M399: 473.96 | N399: 246.04 | O399: =N399/L399 -> 0.34172222 | P399: 40.06 | Q399: 205.98 | R399: =Q399/L399 -> 0.28608333 | S399: Walk-in | T399: Cash | U399: Noida
A400: MM-0399 | B400: 45797 | C400: Biscuits Pack | D400: Snacks | E400: 4 | F400: 40 | G400: 0.05 | H400: 152 | I400: 0 | J400: 0 | K400: 4 | L400: 152 | M400: 110.52 | N400: 41.48 | O400: =N400/L400 -> 0.27289474 | P400: 7.7 | Q400: 33.78 | R400: =Q400/L400 -> 0.22223684 | S400: Walk-in | T400: Card | U400: Ghaziabad
... A435: MM-0434 | B435: 45761 | C435: Chocolate Bar | D435: Snacks | E435: 1 | F435: 55 | G435: 0.02 | H435: 53.9 | I435: 0 | J435: 0 | K435: 1 | L435: 53.9 | M435: 43.09 | N435: 10.81 | O435: =N435/L435 -> 0.20055659 | P435: 4.48 | Q435: 6.33 | R435: =Q435/L435 -> 0.1174397 | S435: Walk-in | T435: UPI | U435: Noida
A436: MM-0435 | B436: 45716 | C436: LED Bulb 9W | D436: Electronics | E436: 4 | F436: 120 | G436: 0.05 | H436: 456 | I436: 4 | J436: 456 | K436: 0 | L436: 0 | M436: 0 | N436: 0 | O436: 0 | P436: 0 | Q436: 0 | R436: 0 | S436: Member | T436: Card | U436: Ghaziabad
A437: MM-0436 | B437: 45979 | C437: Potato Chips | D437: Snacks | E437: 5 | F437: 30 | G437: 0.15 | H437: 127.5 | I437: 0 | J437: 0 | K437: 5 | L437: 127.5 | M437: 95.45 | N437: 32.05 | O437: =N437/L437 -> 0.25137255 | P437: 10.47 | Q437: 21.58 | R437: =Q437/L437 -> 0.1692549 | S437: Regular | T437: Cash | U437: Noida
A438: MM-0437 | B438: 45665 | C438: Wheat Flour 5kg | D438: Groceries | E438: 8 | F438: 310 | G438: 0.02 | H438: 2430.4 | I438: 0 | J438: 0 | K438: 8 | L438: 2430.4 | M438: 1852.65 | N438: 577.75 | O438: =N438/L438 -> 0.23771807 | P438: 131.63 | Q438: 446.12 | R438: =Q438/L438 -> 0.18355826 | S438: Regular | T438: Wallet | U438: Noida
A439: MM-0438 | B439: 45702 | C439: Floor Cleaner 1L | D439: Household | E439: 3 | F439: 125 | G439: 0.1 | H439: 337.5 | I439: 0 | J439: 0 | K439: 3 | L439: 337.5 | M439: 280.77 | N439: 56.73 | O439: =N439/L439 -> 0.16808889 | P439: 22.58 | Q439: 34.15 | R439: =Q439/L439 -> 0.10118519 | S439: Member | T439: Card | U439: Ghaziabad
A440: MM-0439 | B440: 45950 | C440: Dishwash Liquid 500ml | D440: Household | E440: 2 | F440: 95 | G440: 0.05 | H440: 180.5 | I440: 0 | J440: 0 | K440: 2 | L440: 180.5 | M440: 150.23 | N440: 30.27 | O440: =N440/L440 -> 0.16770083 | P440: 11.92 | Q440: 18.35 | R440: =Q440/L440 -> 0.10166205 | S440: New | T440: Cash | U440: Gurugram
A441: MM-0440 | B441: 45925 | C441: Potato Chips | D441: Snacks | E441: 8 | F441: 30 | G441: 0.05 | H441: 228 | I441: 0 | J441: 0 | K441: 8 | L441: 228 | M441: 148.36 | N441: 79.64 | O441: =N441/L441 -> 0.34929825 | P441: 19.34 | Q441: 60.3 | R441: =Q441/L441 -> 0.26447368 | S441: Regular | T441: Cash | U441: Ghaziabad
A442: MM-0441 | B442: 45947 | C442: Soft Drink 750ml | D442: Beverages | E442: 8 | F442: 48 | G442: 0 | H442: 384 | I442: 0 | J442: 0 | K442: 8 | L442: 384 | M442: 273.62 | N442: 110.38 | O442: =N442/L442 -> 0.28744792 | P442: 25.68 | Q442: 84.7 | R442: =Q442/L442 -> 0.22057292 | S442: Member | T442: Wallet | U442: Noida
A443: MM-0442 | B443: 45953 | C443: Coffee 200g | D443: Beverages | E443: 8 | F443: 180 | G443: 0 | H443: 1440 | I443: 0 | J443: 0 | K443: 8 | L443: 1440 | M443: 1044.33 | N443: 395.67 | O443: =N443/L443 -> 0.27477083 | P443: 185.51 | Q443: 210.16 | R443: =Q443/L443 -> 0.14594444 | S443: Walk-in | T443: Wallet | U443: Ghaziabad
A444: MM-0443 | B444: 45706 | C444: Potato Chips | D444: Snacks | E444: 1 | F444: 30 | G444: 0.02 | H444: 29.4 | I444: 1 | J444: 29.4 | K444: 0 | L444: 0 | M444: 0 | N444: 0 | O444: 0 | P444: 0 | Q444: 0 | R444: 0 | S444: Walk-in | T444: Cash | U444: Delhi
A445: MM-0444 | B445: 45935 | C445: Cooking Oil 1L | D445: Groceries | E445: 1 | F445: 145 | G445: 0.05 | H445: 137.75 | I445: 0 | J445: 0 | K445: 1 | L445: 137.75 | M445: 90.26 | N445: 47.49 | O445: =N445/L445 -> 0.34475499 | P445: 16.42 | Q445: 31.07 | R445: =Q445/L445 -> 0.22555354 | S445: New | T445: Card | U445: Gurugram
A446: MM-0445 | B446: 45895 | C446: Mineral Water 1L | D446: Beverages | E446: 3 | F446: 20 | G446: 0.05 | H446: 57 | I446: 0 | J446: 0 | K446: 3 | L446: 57 | M446: 37.22 | N446: 19.78 | O446: =N446/L446 -> 0.34701754 | P446: 5.16 | Q446: 14.62 | R446: =Q446/L446 -> 0.25649123 | S446: Walk-in | T446: Card | U446: Ghaziabad
A447: MM-0446 | B447: 45763 | C447: Dishwash Liquid 500ml | D447: Household | E447: 1 | F447: 95 | G447: 0.1 | H447: 85.5 | I447: 0 | J447: 0 | K447: 1 | L447: 85.5 | M447: 62.07 | N447: 23.43 | O447: =N447/L447 -> 0.27403509 | P447: 6.98 | Q447: 16.45 | R447: =Q447/L447 -> 0.19239766 | S447: Regular | T447: Wallet | U447: Noida
A448: MM-0447 | B448: 45763 | C448: Chocolate Bar | D448: Snacks | E448: 1 | F448: 55 | G448: 0 | H448: 55 | I448: 0 | J448: 0 | K448: 1 | L448: 55 | M448: 41.32 | N448: 13.68 | O448: =N448/L448 -> 0.24872727 | P448: 5.67 | Q448: 8.01 | R448: =Q448/L448 -> 0.14563636 | S448: Member | T448: Card | U448: Gurugram
A449: MM-0448 | B449: 45865 | C449: Biscuits Pack | D449: Snacks | E449: 3 | F449: 40 | G449: 0.05 | H449: 114 | I449: 1 | J449: 38 | K449: 2 | L449: 76 | M449: 64.27 | N449: 11.73 | O449: =N449/L449 -> 0.15434211 | P449: 6.78 | Q449: 4.95 | R449: =Q449/L449 -> 0.065131579 | S449: Regular | T449: Card | U449: Ghaziabad
A450: MM-0449 | B450: 45952 | C450: Shampoo 340ml | D450: Personal Care | E450: 4 | F450: 210 | G450: 0.02 | H450: 823.2 | I450: 0 | J450: 0 | K450: 4 | L450: 823.2 | M450: 533.5 | N450: 289.7 | O450: =N450/L450 -> 0.35191934 | P450: 49.28 | Q450: 240.42 | R450: =Q450/L450 -> 0.29205539 | S450: Walk-in | T450: Card | U450: Delhi
A451: MM-0450 | B451: 46003 | C451: Potato Chips | D451: Snacks | E451: 1 | F451: 30 | G451: 0.15 | H451: 25.5 | I451: 0 | J451: 0 | K451: 1 | L451: 25.5 | M451: 16.88 | N451: 8.62 | O451: =N451/L451 -> 0.33803922 | P451: 2.46 | Q451: 6.16 | R451: =Q451/L451 -> 0.24156863 | S451: New | T451: Card | U451: Noida
...

Sheet Dashboard
B1: MEGA MARKET — SALES & PROFIT EXECUTIVE DASHBOARD
B3: Delhi-NCR multi-category retail · FY2025 (Jan–Dec) · All figures are live formulas from the "Cleaned Data" table (Calc sheet) — nothing is hardcoded
B4: FILTERS (choose from each dropdown — every KPI, chart and insight below updates instantly; pick "All" / "Jan"–"Dec" to reset)
B5: Category | F5: City | J5: Customer Type | N5: Payment Method | R5: From month | V5: To month
B6: All | F6: All | J6: All | N6: All | R6: May | V6: Dec
B7: =Calc!$B$153 -> ✔ All reconciliation checks pass — dashboard ties to Cleaned Data
B9: Total Sales (₹) | F9: Net Sales (₹) | J9: Gross Profit (₹) | N9: Net Profit (₹) | R9: Return Rate (units)
B10: =Calc!$B$19 -> 534759.67 | F10: =Calc!$B$21 -> 525460.17 | J10: =Calc!$B$22 -> 136936.28 | N10: =Calc!$B$23 -> 89567.45 | R10: =Calc!$B$31 -> 0.018113385
B13: Gross Profit Margin | F13: Net Profit Margin | J13: Net Qty Sold (units) | N13: Average Order Value (₹) | R13: Sales Return (₹)
B14: =Calc!$B$29 -> 0.26060259 | F14: =Calc!$B$30 -> 0.17045526 | J14: =Calc!$B$26 -> 4174 | N14: =Calc!$B$28 -> 398.07589 | R14: =Calc!$B$20 -> 9299.5
B17: =" "&"Trend ("&INDEX(Calc!$B$37:$B$48,Calc!$C$10)&" vs prior month): Net Sales "&Calc!$F$21&" | Gross Profit "&Calc!$F$22&" | Net Profit "&Calc!$F$23 -> Trend (Dec vs prior month): Net Sales ▲ 17.1% · Dec vs Nov | Gross Profit ▲ 19.0% · Dec vs Nov | Net Profit ▲ 21.8% · Dec vs Nov
B19: MONTHLY TREND & CATEGORY PERFORMANCE
B38: TOP/BOTTOM PRODUCTS & CITY / CUSTOMER / PAYMENT MIX
B57: CITY CONTRIBUTION & CUSTOMER / PAYMENT MIX
B76: RETURNS ANALYSIS

Sheet Insights & Recommendations
B1: MEGA MARKET — KEY INSIGHTS & RECOMMENDATIONS (FY2025)
B2: Figures below are computed live from the "Calc" sheet, which sums the "Cleaned Data" table — nothing here is typed in by hand. Numbers reflect the full-year, all-filters dataset (₹779,939.05 Net Sales) as documented in the Requirements sheet.
B4: 1. SALES & PROFIT DRIVERS
B5: ="Groceries and Household are the clear revenue engines, together contributing "&TEXT((Calc!B54+Calc!B55)/Calc!B61,"0.0%")&" of Net Sales ("&TEXT(Calc!B54,"₹#,##0")&" and "&TEXT(Calc!B55,"₹#,##0")&" respectively). The five hero SKUs — "&Calc!B91&", "&Calc!B92&", "&Calc!B93&", "&Calc!B94&" and "&Calc!B95&" — sit almost entirely inside those two categories, so revenue concentration and category concentration are the same story. Profit follows the same pattern: Groceries also leads on Gross Profit ("&TEXT(Calc!C54,"₹#,##0")&") and Net Profit ("&TEXT(Calc!D54,"₹#,##0")&"), so — unlike a typical retail mix — the top revenue category here is not lagging on margin: its Gross Profit Margin ("&TEXT(Calc!I54,"0.0%")&") is in line with the store-wide average ("&TEXT(Calc!I61,"0.0%")&")." -> Groceries and Household are the clear revenue engines, together contributing 57.7% of Net Sales (₹2,01,364 and ₹1,01,609 respectively). The five hero SKUs — Rice 5kg, Wheat Flour 5kg, Laundry Detergent 2kg, Coffee 200g and Shampoo 340ml — sit almost entirely inside those two categories, so revenue concentration and category concentration are the same story. Profit follows the same pattern: Groceries also leads on Gross Profit (₹53,116) and Net Profit (₹34,797), so — unlike a typical retail mix — the top revenue category here is not lagging on margin: its Gross Profit Margin (26.4%) is in line with the store-wide average (26.1%).
B6: ="Ghaziabad and Delhi are the top two cities by Net Sales ("&TEXT(Calc!B100,"₹#,##0")&" and "&TEXT(Calc!B101,"₹#,##0")&"), but all four named cities are within "&TEXT((Calc!B100-Calc!B103)/Calc!B100,"0.0%")&" of each other — city is not a strong differentiator this year, unlike category or product. Customer Type and Payment Method are similarly balanced, each real segment holding roughly "&TEXT(Calc!B110/Calc!B115,"0%")&"–"&TEXT(Calc!B112/Calc!B115,"0%")&" of Net Sales — no single acquisition channel or payment rail is over- or under-performing enough to flag." -> Ghaziabad and Delhi are the top two cities by Net Sales (₹1,36,753 and ₹1,34,972), but all four named cities are within 10.0% of each other — city is not a strong differentiator this year, unlike category or product. Customer Type and Payment Method are similarly balanced, each real segment holding roughly 24%–25% of Net Sales — no single acquisition channel or payment rail is over- or under-performing enough to flag.
B7: 2. WEAK PERFORMERS
B8: ="The lowest-revenue products are "&Calc!D91&" ("&TEXT(Calc!E91,"₹#,##0")&"), "&Calc!D92&" ("&TEXT(Calc!E92,"₹#,##0")&") and "&Calc!D93&" ("&TEXT(Calc!E93,"₹#,##0")&") — all everyday, low-unit-price items where volume has not compensated for low price. By category, Stationery is the clear laggard: only "&TEXT(Calc!B60/Calc!B61,"0.0%")&" of Net Sales and the lowest absolute Gross Profit ("&TEXT(Calc!C60,"₹#,##0")&") of any category, alongside Snacks (also under 5% of sales). Margins across categories are otherwise tight, within a "&TEXT(MIN(Calc!I54:I60),"0.0%")&"–"&TEXT(MAX(Calc!I54:I60),"0.0%")&" Gross Profit Margin band, so no category is a structural margin problem — the issue for the weak categories is sales volume, not pricing." -> The lowest-revenue products are Mineral Water 1L (₹3,398), Potato Chips (₹6,233) and Biscuits Pack (₹7,640) — all everyday, low-unit-price items where volume has not compensated for low price. By category, Stationery is the clear laggard: only 1.8% of Net Sales and the lowest absolute Gross Profit (₹2,436) of any category, alongside Snacks (also under 5% of sales). Margins across categories are otherwise tight, within a 24.8%–27.0% Gross Profit Margin band, so no category is a structural margin problem — the issue for the weak categories is sales volume, not pricing.
B9: A genuine data-quality gap sits in three fields: 20 rows (Customer Type), 15 rows (Payment Method) and 12 rows (City) are recorded as 'Unknown' — small in absolute terms (well under 1% of the 2,000 invoices each) but concentrated at checkout, meaning the gap is operational (a step being skipped) rather than random. These rows are retained as 'Unknown' rather than guessed, per the cleaning log on the Quality Checks sheet, so they remain visible here rather than silently disappearing from the analysis.
B10: 3. TREND TAKEAWAYS
B11: ="Monthly Net Sales ranges from "&TEXT(MIN(Calc!G37:G48),"₹#,##0")&" to "&TEXT(MAX(Calc!G37:G48),"₹#,##0")&". "&INDEX(Calc!B37:B48,MATCH(MAX(Calc!G37:G48),Calc!G37:G48,0))&" is the peak month and "&INDEX(Calc!B37:B48,MATCH(MIN(Calc!G37:G48),Calc!G37:G48,0))&" the weakest, with no single run of consecutive slow months — the year reads as noisy month-to-month rather than a seasonal decline. Net Profit Margin is essentially flat across the year: H1 (Jan–Jun) averages "&TEXT(SUMIFS(d_NP,d_Date,">="&DATE(Calc!$C$11,1,1),d_Date,"<="&DATE(Calc!$C$11,6,30))/SUMIFS(d_NetSales,d_Date,">="&DATE(Calc!$C$11,1,1),d_Date,"<="&DATE(Calc!$C$11,6,30)),"0.0%")&" against H2's (Jul–Dec) "&TEXT(SUMIFS(d_NP,d_Date,">="&DATE(Calc!$C$11,7,1),d_Date,"<="&DATE(Calc!$C$11,12,31))/SUMIFS(d_NetSales,d_Date,">="&DATE(Calc!$C$11,7,1),d_Date,"<="&DATE(Calc!$C$11,12,31)),"0.0%")&", a gap of well under one percentage point — a trend to keep monitoring, not one requiring immediate action." -> Monthly Net Sales ranges from ₹53,367 to ₹79,101. Aug is the peak month and Feb the weakest, with no single run of consecutive slow months — the year reads as noisy month-to-month rather than a seasonal decline. Net Profit Margin is essentially flat across the year: H1 (Jan–Jun) averages 16.8% against H2's (Jul–Dec) 17.1%, a gap of well under one percentage point — a trend to keep monitoring, not one requiring immediate action.
B12: 4. RETURNS
B13: ="Overall Return Rate is "&TEXT(Calc!B31,"0.0%")&" of units ("&Calc!B25&" of "&TEXT(Calc!B24,"#,##0")&"), worth "&TEXT(Calc!B20,"₹#,##0")&" in returned sales value — a healthy level for retail. Snacks and Groceries carry the highest absolute Return Qty, but scaled to their own sales volume the picture flips: Stationery has the highest true Return Rate at "&TEXT(MAX(Calc!K54:K60),"0.0%")&" of its units, more than double the store-wide rate, while Groceries' rate ("&TEXT(Calc!K54,"0.0%")&") is close to average — so its high return count is simply proportional to being the best-selling category, not a genuine quality issue. Stationery is the one category where returns deserve a root-cause look." -> Overall Return Rate is 1.8% of units (77 of 4,251), worth ₹9,300 in returned sales value — a healthy level for retail. Snacks and Groceries carry the highest absolute Return Qty, but scaled to their own sales volume the picture flips: Stationery has the highest true Return Rate at 3.0% of its units, more than double the store-wide rate, while Groceries' rate (2.1%) is close to average — so its high return count is simply proportional to being the best-selling category, not a genuine quality issue. Stationery is the one category where returns deserve a root-cause look.
B14: 5. RECOMMENDATIONS
B15: • Protect and extend the Groceries/Household hero SKUs (Rice 5kg, Wheat Flour 5kg, Laundry Detergent 2kg, Coffee 200g, Shampoo 340ml): prioritise these for stock cover and end-of-aisle promotion, since they already anchor both revenue and profit.
B16: • Give Stationery and Snacks a defined promotional and merchandising push (bundle offers, cross-placement near Groceries) — their margins are normal, so the fix is demand, not price.
B17: • Investigate Stationery returns specifically: its Return Rate is the highest of any category despite modest sales, which points to a quality, sizing, or expectation-mismatch issue worth a root-cause review rather than a blanket discount cut.
B18: • Tighten checkout data capture for Customer Type, Payment Method and City — even a short mandatory prompt at the till would close the "Unknown" gap and materially improve segment-level targeting.
B19: • Keep discounting concentrated where it already performs (0% and 10-15% bands show the healthiest margins in the Cleaned Data); review the 2-6% discount band, whose margin sits slightly below the other bands for no clear return in volume.
B20: • Watch Net Profit Margin monthly rather than only annually — it is flat year-over-year in aggregate, but the Dashboard's month filter should be used at each business review to catch any emerging dip early.
B22: ASSUMPTIONS & DATA NOTES (also see "Quality Checks" sheet)
B23: • Blank Customer Type, Payment Method and City values were retained as "Unknown" rather than guessed, per the original cleaning log — they remain visible in every chart and KPI (never filtered out silently).
B24: • Net Sales (₹) — after returns — is used as the primary revenue metric throughout this dashboard, per the brief; "Total Sales" is shown separately as the pre-return gross figure.
B25: • Every figure on the Dashboard and in this sheet is a live formula referencing the "Cleaned Data" table via the "Calc" sheet — see the reconciliation checks at the bottom of "Calc" (section 11), which confirm every total ties back to "Cleaned Data" to the rupee.

Sheet Quality Checks
A1: Mega Market — Data Quality & Cleaning Summary
A2: Check | B2: Result
A3: Original transaction rows | B3: 2002
A4: Exact duplicate rows removed | B4: 2
A5: Cleaned transaction rows | B5: 2000
A6: Missing Customer Type handled | B6: 0
A7: Missing Payment Method handled | B7: 0
A8: Missing City handled | B8: 0
A9: Financial calculation mismatches | B9: 0
A10: Quantity/return validation issues | B10: 0
A11: Date format | B11: dd-mmm-yyyy
A12: Currency format | B12: ₹#,##0 (no decimals)
A13: Discount format | B13: 0% (converted from whole percentage points)
A15: Missing-value treatment
A16: Blank Customer Type, Payment Method, and City values were retained as 'Unknown' rather than guessed.

Sheet Calc
A1: Calc — formula layer feeding the Dashboard (replaces PivotTables; every value is a live formula on "Cleaned Data")
A2: All blocks respond to the Dashboard dropdowns. Named ranges d_* point at the "Cleaned Data" table columns; fCat/fCity/fCust/fPay/fStart/fEnd are the active filter criteria ("*" = all).
A4: 1. FILTER CRITERIA (linked to Dashboard dropdowns) | F4: Dropdown lists → Category | City | Customer | Payment | Month
A5: Category | B5: =Dashboard!$B$6 -> All | C5: =IF(B5="All","*",B5) -> * | F5: All | G5: All | H5: All | I5: All | J5: Jan
A6: City | B6: =Dashboard!$F$6 -> All | C6: =IF(B6="All","*",B6) -> * | F6: Groceries | G6: Ghaziabad | H6: Member | I6: Card | J6: Feb
A7: Customer Type | B7: =Dashboard!$J$6 -> All | C7: =IF(B7="All","*",B7) -> * | F7: Household | G7: Delhi | H7: Regular | I7: Cash | J7: Mar
A8: Payment Method | B8: =Dashboard!$N$6 -> All | C8: =IF(B8="All","*",B8) -> * | F8: Beverages | G8: Noida | H8: New | I8: UPI | J8: Apr
A9: From month | B9: =Dashboard!$R$6 -> May | C9: =IFERROR(MATCH(B9,$J$5:$J$16,0),1) -> 5 | F9: Personal Care | G9: Gurugram | H9: Walk-in | I9: Wallet | J9: May
A10: To month | B10: =Dashboard!$V$6 -> Dec | C10: =IFERROR(MATCH(B10,$J$5:$J$16,0),12) -> 12 | F10: Electronics | G10: Unknown | H10: Unknown | I10: Unknown | J10: Jun
A11: Data year | C11: =YEAR(MIN(d_Date)) -> 2025 | F11: Snacks | J11: Jul
A12: Period start date | C12: =DATE(C11,C9,1) -> 45778 | F12: Stationery | J12: Aug
A13: Period end date | C13: =EOMONTH(DATE(C11,C10,1),0) -> 46022 | J13: Sep
A14: Filters at default (All / Jan–Dec)? | C14: =IF(AND(B5="All",B6="All",B7="All",B8="All",C9=1,C10=12),1,0) -> 0 | J14: Oct
J15: Nov
J16: Dec
A17: 2. KPI SUMMARY (all filters applied, incl. period) + month-over-month (To-month vs prior month)
A18: Metric | B18: Value | C18: To-month value | D18: Prior-month value | E18: Change | F18: Indicator text
A19: Total Sales (₹) — gross | B19: =SUMIFS(d_Sales,d_Category,fCat,d_City,fCity,d_Cust,fCust,d_Pay,fPay,d_Date,">="&fStart,d_Date,"<="&fEnd) -> 534759.67 | C19: =INDEX($E$37:$E$48,$C$10) -> 64278.95 | D19: =IF($C$10>1,INDEX($E$37:$E$48,$C$10-1),"") -> 54697.53 | E19: =IF(AND(ISNUMBER(D19),D19<>0),(C19-D19)/D19,"") -> 0.17517098 | F19: =IF(E19="","— no prior month",IF(E19>=0,"▲ ","▼ ")&TEXT(ABS(E19),"0.0%")&" · "&INDEX($B$37:$B$48,$C$10)&" vs "&INDEX($B$37:$B$48,$C$10-1)) -> ▲ 17.5% · Dec vs Nov
A20: Sales Return (₹) | B20: =SUMIFS(d_SalesRet,d_Category,fCat,d_City,fCity,d_Cust,fCust,d_Pay,fPay,d_Date,">="&fStart,d_Date,"<="&fEnd) -> 9299.5 | C20: =INDEX($F$37:$F$48,$C$10) -> 1660 | D20: =IF($C$10>1,INDEX($F$37:$F$48,$C$10-1),"") -> 1201.9 | E20: =IF(AND(ISNUMBER(D20),D20<>0),(C20-D20)/D20,"") -> 0.38114652 | F20: =IF(E20="","— no prior month",IF(E20>=0,"▲ ","▼ ")&TEXT(ABS(E20),"0.0%")&" · "&INDEX($B$37:$B$48,$C$10)&" vs "&INDEX($B$37:$B$48,$C$10-1)) -> ▲ 38.1% · Dec vs Nov
A21: Net Sales (₹) | B21: =SUMIFS(d_NetSales,d_Category,fCat,d_City,fCity,d_Cust,fCust,d_Pay,fPay,d_Date,">="&fStart,d_Date,"<="&fEnd) -> 525460.17 | C21: =INDEX($G$37:$G$48,$C$10) -> 62618.95 | D21: =IF($C$10>1,INDEX($G$37:$G$48,$C$10-1),"") -> 53495.63 | E21: =IF(AND(ISNUMBER(D21),D21<>0),(C21-D21)/D21,"") -> 0.17054328 | F21: =IF(E21="","— no prior month",IF(E21>=0,"▲ ","▼ ")&TEXT(ABS(E21),"0.0%")&" · "&INDEX($B$37:$B$48,$C$10)&" vs "&INDEX($B$37:$B$48,$C$10-1)) -> ▲ 17.1% · Dec vs Nov
A22: Gross Profit (₹) | B22: =SUMIFS(d_GP,d_Category,fCat,d_City,fCity,d_Cust,fCust,d_Pay,fPay,d_Date,">="&fStart,d_Date,"<="&fEnd) -> 136936.28 | C22: =INDEX($H$37:$H$48,$C$10) -> 16403.21 | D22: =IF($C$10>1,INDEX($H$37:$H$48,$C$10-1),"") -> 13783.7 | E22: =IF(AND(ISNUMBER(D22),D22<>0),(C22-D22)/D22,"") -> 0.19004404 | F22: =IF(E22="","— no prior month",IF(E22>=0,"▲ ","▼ ")&TEXT(ABS(E22),"0.0%")&" · "&INDEX($B$37:$B$48,$C$10)&" vs "&INDEX($B$37:$B$48,$C$10-1)) -> ▲ 19.0% · Dec vs Nov
A23: Net Profit (₹) | B23: =SUMIFS(d_NP,d_Category,fCat,d_City,fCity,d_Cust,fCust,d_Pay,fPay,d_Date,">="&fStart,d_Date,"<="&fEnd) -> 89567.45 | C23: =INDEX($I$37:$I$48,$C$10) -> 10760.4 | D23: =IF($C$10>1,INDEX($I$37:$I$48,$C$10-1),"") -> 8836.61 | E23: =IF(AND(ISNUMBER(D23),D23<>0),(C23-D23)/D23,"") -> 0.21770679 | F23: =IF(E23="","— no prior month",IF(E23>=0,"▲ ","▼ ")&TEXT(ABS(E23),"0.0%")&" · "&INDEX($B$37:$B$48,$C$10)&" vs "&INDEX($B$37:$B$48,$C$10-1)) -> ▲ 21.8% · Dec vs Nov
A24: Total Quantity Sold (gross units) | B24: =SUMIFS(d_Qty,d_Category,fCat,d_City,fCity,d_Cust,fCust,d_Pay,fPay,d_Date,">="&fStart,d_Date,"<="&fEnd) -> 4251 | C24: =INDEX($J$37:$J$48,$C$10) -> 564 | D24: =IF($C$10>1,INDEX($J$37:$J$48,$C$10-1),"") -> 495 | E24: =IF(AND(ISNUMBER(D24),D24<>0),(C24-D24)/D24,"") -> 0.13939394 | F24: =IF(E24="","— no prior month",IF(E24>=0,"▲ ","▼ ")&TEXT(ABS(E24),"0.0%")&" · "&INDEX($B$37:$B$48,$C$10)&" vs "&INDEX($B$37:$B$48,$C$10-1)) -> ▲ 13.9% · Dec vs Nov
A25: Return Qty (units) | B25: =SUMIFS(d_RetQty,d_Category,fCat,d_City,fCity,d_Cust,fCust,d_Pay,fPay,d_Date,">="&fStart,d_Date,"<="&fEnd) -> 77 | C25: =INDEX($K$37:$K$48,$C$10) -> 11 | D25: =IF($C$10>1,INDEX($K$37:$K$48,$C$10-1),"") -> 7 | E25: =IF(AND(ISNUMBER(D25),D25<>0),(C25-D25)/D25,"") -> 0.57142857 | F25: =IF(E25="","— no prior month",IF(E25>=0,"▲ ","▼ ")&TEXT(ABS(E25),"0.0%")&" · "&INDEX($B$37:$B$48,$C$10)&" vs "&INDEX($B$37:$B$48,$C$10-1)) -> ▲ 57.1% · Dec vs Nov
A26: Net Quantity Sold (units) | B26: =SUMIFS(d_NetQty,d_Category,fCat,d_City,fCity,d_Cust,fCust,d_Pay,fPay,d_Date,">="&fStart,d_Date,"<="&fEnd) -> 4174 | C26: =INDEX($L$37:$L$48,$C$10) -> 553 | D26: =IF($C$10>1,INDEX($L$37:$L$48,$C$10-1),"") -> 488 | E26: =IF(AND(ISNUMBER(D26),D26<>0),(C26-D26)/D26,"") -> 0.13319672 | F26: =IF(E26="","— no prior month",IF(E26>=0,"▲ ","▼ ")&TEXT(ABS(E26),"0.0%")&" · "&INDEX($B$37:$B$48,$C$10)&" vs "&INDEX($B$37:$B$48,$C$10-1)) -> ▲ 13.3% · Dec vs Nov
A27: Invoices (distinct Invoice IDs) | B27: =COUNTIFS(d_Category,fCat,d_City,fCity,d_Cust,fCust,d_Pay,fPay,d_Date,">="&fStart,d_Date,"<="&fEnd) -> 1320 | C27: =INDEX($M$37:$M$48,$C$10) -> 167 | D27: =IF($C$10>1,INDEX($M$37:$M$48,$C$10-1),"") -> 160 | E27: =IF(AND(ISNUMBER(D27),D27<>0),(C27-D27)/D27,"") -> 0.04375 | F27: =IF(E27="","— no prior month",IF(E27>=0,"▲ ","▼ ")&TEXT(ABS(E27),"0.0%")&" · "&INDEX($B$37:$B$48,$C$10)&" vs "&INDEX($B$37:$B$48,$C$10-1)) -> ▲ 4.4% · Dec vs Nov
A28: Average Order Value (₹) | B28: =IF(B27=0,0,B21/B27) -> 398.07589 | C28: =INDEX($Q$37:$Q$48,$C$10) -> 374.96377 | D28: =IF($C$10>1,INDEX($Q$37:$Q$48,$C$10-1),"") -> 334.34769 | E28: =IF(AND(ISNUMBER(D28),D28<>0),(C28-D28)/D28,"") -> 0.12147859 | F28: =IF(E28="","— no prior month",IF(E28>=0,"▲ ","▼ ")&TEXT(ABS(E28),"0.0%")&" · "&INDEX($B$37:$B$48,$C$10)&" vs "&INDEX($B$37:$B$48,$C$10-1)) -> ▲ 12.1% · Dec vs Nov
A29: Gross Profit Margin | B29: =IF(B21=0,0,B22/B21) -> 0.26060259 | C29: =INDEX($N$37:$N$48,$C$10) -> 0.26195281 | D29: =IF($C$10>1,INDEX($N$37:$N$48,$C$10-1),"") -> 0.2576603 | E29: =IF(ISNUMBER(D29),C29-D29,"") -> 0.0042925128 | F29: =IF(E29="","— no prior month",IF(E29>=0,"▲ ","▼ ")&TEXT(ABS(E29)*100,"0.0")&" pp · "&INDEX($B$37:$B$48,$C$10)&" vs "&INDEX($B$37:$B$48,$C$10-1)) -> ▲ 0.4 pp · Dec vs Nov
A30: Net Profit Margin | B30: =IF(B21=0,0,B23/B21) -> 0.17045526 | C30: =INDEX($O$37:$O$48,$C$10) -> 0.17183936 | D30: =IF($C$10>1,INDEX($O$37:$O$48,$C$10-1),"") -> 0.16518377 | E30: =IF(ISNUMBER(D30),C30-D30,"") -> 0.0066555824 | F30: =IF(E30="","— no prior month",IF(E30>=0,"▲ ","▼ ")&TEXT(ABS(E30)*100,"0.0")&" pp · "&INDEX($B$37:$B$48,$C$10)&" vs "&INDEX($B$37:$B$48,$C$10-1)) -> ▲ 0.7 pp · Dec vs Nov
A31: Return Rate (Return Qty ÷ Qty) | B31: =IF(B24=0,0,B25/B24) -> 0.018113385 | C31: =INDEX($P$37:$P$48,$C$10) -> 0.019503546 | D31: =IF($C$10>1,INDEX($P$37:$P$48,$C$10-1),"") -> 0.014141414 | E31: =IF(ISNUMBER(D31),C31-D31,"") -> 0.005362132 | F31: =IF(E31="","— no prior month",IF(E31>=0,"▲ ","▼ ")&TEXT(ABS(E31)*100,"0.0")&" pp · "&INDEX($B$37:$B$48,$C$10)&" vs "&INDEX($B$37:$B$48,$C$10-1)) -> ▲ 0.5 pp · Dec vs Nov
A35: 3. MONTHLY (all filters EXCEPT the period — always Jan–Dec so the trend context is visible)
A36: Month # | B36: Month | C36: Start | D36: End | E36: Total Sales (₹) | F36: Sales Return (₹) | G36: Net Sales (₹) | H36: Gross Profit (₹) | I36: Net Profit (₹) | J36: Qty | K36: Return Qty | L36: Net Qty | M36: Invoices | N36: GP Margin | O36: NP Margin | P36: Return Rate (Qty) | Q36: Avg Order Value (₹) | R36: Key: weakest month
A37: 1 | B37: Jan | C37: =DATE($C$11,A37,1) -> 45658 | D37: =EOMONTH(C37,0) -> 45688 | E37: =SUMIFS(d_Sales,d_Category,fCat,d_City,fCity,d_Cust,fCust,d_Pay,fPay,d_Date,">="&$C37,d_Date,"<="&$D37) -> 71958.47 | F37: =SUMIFS(d_SalesRet,d_Category,fCat,d_City,fCity,d_Cust,fCust,d_Pay,fPay,d_Date,">="&$C37,d_Date,"<="&$D37) -> 1375 | G37: =SUMIFS(d_NetSales,d_Category,fCat,d_City,fCity,d_Cust,fCust,d_Pay,fPay,d_Date,">="&$C37,d_Date,"<="&$D37) -> 70583.47 | H37: =SUMIFS(d_GP,d_Category,fCat,d_City,fCity,d_Cust,fCust,d_Pay,fPay,d_Date,">="&$C37,d_Date,"<="&$D37) -> 18094.27 | I37: =SUMIFS(d_NP,d_Category,fCat,d_City,fCity,d_Cust,fCust,d_Pay,fPay,d_Date,">="&$C37,d_Date,"<="&$D37) -> 11832.23 | J37: =SUMIFS(d_Qty,d_Category,fCat,d_City,fCity,d_Cust,fCust,d_Pay,fPay,d_Date,">="&$C37,d_Date,"<="&$D37) -> 556 | K37: =SUMIFS(d_RetQty,d_Category,fCat,d_City,fCity,d_Cust,fCust,d_Pay,fPay,d_Date,">="&$C37,d_Date,"<="&$D37) -> 5 | L37: =SUMIFS(d_NetQty,d_Category,fCat,d_City,fCity,d_Cust,fCust,d_Pay,fPay,d_Date,">="&$C37,d_Date,"<="&$D37) -> 551 | M37: =COUNTIFS(d_Category,fCat,d_City,fCity,d_Cust,fCust,d_Pay,fPay,d_Date,">="&$C37,d_Date,"<="&$D37) -> 166 | N37: =IF(G37=0,0,H37/G37) -> 0.2563528 | O37: =IF(G37=0,0,I37/G37) -> 0.16763458 | P37: =IF(J37=0,0,K37/J37) -> 0.0089928058 | Q37: =IF(M37=0,0,G37/M37) -> 425.20163 | R37: =IF(G37>0,G37,1E+99) -> 70583.47
A38: 2 | B38: Feb | C38: =DATE($C$11,A38,1) -> 45689 | D38: =EOMONTH(C38,0) -> 45716 | E38: =SUMIFS(d_Sales,d_Category,fCat,d_City,fCity,d_Cust,fCust,d_Pay,fPay,d_Date,">="&$C38,d_Date,"<="&$D38) -> 53988.62 | F38: =SUMIFS(d_SalesRet,d_Category,fCat,d_City,fCity,d_Cust,fCust,d_Pay,fPay,d_Date,">="&$C38,d_Date,"<="&$D38) -> 621.64 | G38: =SUMIFS(d_NetSales,d_Category,fCat,d_City,fCity,d_Cust,fCust,d_Pay,fPay,d_Date,">="&$C38,d_Date,"<="&$D38) -> 53366.98 | H38: =SUMIFS(d_GP,d_Category,fCat,d_City,fCity,d_Cust,fCust,d_Pay,fPay,d_Date,">="&$C38,d_Date,"<="&$D38) -> 13968.5 | I38: =SUMIFS(d_NP,d_Category,fCat,d_City,fCity,d_Cust,fCust,d_Pay,fPay,d_Date,">="&$C38,d_Date,"<="&$D38) -> 9247.88 | J38: =SUMIFS(d_Qty,d_Category,fCat,d_City,fCity,d_Cust,fCust,d_Pay,fPay,d_Date,">="&$C38,d_Date,"<="&$D38) -> 514 | K38: =SUMIFS(d_RetQty,d_Category,fCat,d_City,fCity,d_Cust,fCust,d_Pay,fPay,d_Date,">="&$C38,d_Date,"<="&$D38) -> 8 | L38: =SUMIFS(d_NetQty,d_Category,fCat,d_City,fCity,d_Cust,fCust,d_Pay,fPay,d_Date,">="&$C38,d_Date,"<="&$D38) -> 506 | M38: =COUNTIFS(d_Category,fCat,d_City,fCity,d_Cust,fCust,d_Pay,fPay,d_Date,">="&$C38,d_Date,"<="&$D38) -> 160 | N38: =IF(G38=0,0,H38/G38) -> 0.26174425 | O38: =IF(G38=0,0,I38/G38) -> 0.17328843 | P38: =IF(J38=0,0,K38/J38) -> 0.015564202 | Q38: =IF(M38=0,0,G38/M38) -> 333.54362 | R38: =IF(G38>0,G38,1E+99) -> 53366.98
A39: 3 | B39: Mar | C39: =DATE($C$11,A39,1) -> 45717 | D39: =EOMONTH(C39,0) -> 45747 | E39: =SUMIFS(d_Sales,d_Category,fCat,d_City,fCity,d_Cust,fCust,d_Pay,fPay,d_Date,">="&$C39,d_Date,"<="&$D39) -> 70833.49 | F39: =SUMIFS(d_SalesRet,d_Category,fCat,d_City,fCity,d_Cust,fCust,d_Pay,fPay,d_Date,">="&$C39,d_Date,"<="&$D39) -> 674 | G39: =SUMIFS(d_NetSales,d_Category,fCat,d_City,fCity,d_Cust,fCust,d_Pay,fPay,d_Date,">="&$C39,d_Date,"<="&$D39) -> 70159.49 | H39: =SUMIFS(d_GP,d_Category,fCat,d_City,fCity,d_Cust,fCust,d_Pay,fPay,d_Date,">="&$C39,d_Date,"<="&$D39) -> 17819.07 | I39: =SUMIFS(d_NP,d_Category,fCat,d_City,fCity,d_Cust,fCust,d_Pay,fPay,d_Date,">="&$C39,d_Date,"<="&$D39) -> 11568.42 | J39: =SUMIFS(d_Qty,d_Category,fCat,d_City,fCity,d_Cust,fCust,d_Pay,fPay,d_Date,">="&$C39,d_Date,"<="&$D39) -> 594 | K39: =SUMIFS(d_RetQty,d_Category,fCat,d_City,fCity,d_Cust,fCust,d_Pay,fPay,d_Date,">="&$C39,d_Date,"<="&$D39) -> 6 | L39: =SUMIFS(d_NetQty,d_Category,fCat,d_City,fCity,d_Cust,fCust,d_Pay,fPay,d_Date,">="&$C39,d_Date,"<="&$D39) -> 588 | M39: =COUNTIFS(d_Category,fCat,d_City,fCity,d_Cust,fCust,d_Pay,fPay,d_Date,">="&$C39,d_Date,"<="&$D39) -> 183 | N39: =IF(G39=0,0,H39/G39) -> 0.25397947 | O39: =IF(G39=0,0,I39/G39) -> 0.16488746 | P39: =IF(J39=0,0,K39/J39) -> 0.01010101 | Q39: =IF(M39=0,0,G39/M39) -> 383.38519 | R39: =IF(G39>0,G39,1E+99) -> 70159.49
A40: 4 | B40: Apr | C40: =DATE($C$11,A40,1) -> 45748 | D40: =EOMONTH(C40,0) -> 45777 | E40: =SUMIFS(d_Sales,d_Category,fCat,d_City,fCity,d_Cust,fCust,d_Pay,fPay,d_Date,">="&$C40,d_Date,"<="&$D40) -> 62206.54 | F40: =SUMIFS(d_SalesRet,d_Category,fCat,d_City,fCity,d_Cust,fCust,d_Pay,fPay,d_Date,">="&$C40,d_Date,"<="&$D40) -> 1837.6 | G40: =SUMIFS(d_NetSales,d_Category,fCat,d_City,fCity,d_Cust,fCust,d_Pay,fPay,d_Date,">="&$C40,d_Date,"<="&$D40) -> 60368.94 | H40: =SUMIFS(d_GP,d_Category,fCat,d_City,fCity,d_Cust,fCust,d_Pay,fPay,d_Date,">="&$C40,d_Date,"<="&$D40) -> 15471.46 | I40: =SUMIFS(d_NP,d_Category,fCat,d_City,fCity,d_Cust,fCust,d_Pay,fPay,d_Date,">="&$C40,d_Date,"<="&$D40) -> 10106.41 | J40: =SUMIFS(d_Qty,d_Category,fCat,d_City,fCity,d_Cust,fCust,d_Pay,fPay,d_Date,">="&$C40,d_Date,"<="&$D40) -> 555 | K40: =SUMIFS(d_RetQty,d_Category,fCat,d_City,fCity,d_Cust,fCust,d_Pay,fPay,d_Date,">="&$C40,d_Date,"<="&$D40) -> 18 | L40: =SUMIFS(d_NetQty,d_Category,fCat,d_City,fCity,d_Cust,fCust,d_Pay,fPay,d_Date,">="&$C40,d_Date,"<="&$D40) -> 537 | M40: =COUNTIFS(d_Category,fCat,d_City,fCity,d_Cust,fCust,d_Pay,fPay,d_Date,">="&$C40,d_Date,"<="&$D40) -> 171 | N40: =IF(G40=0,0,H40/G40) -> 0.25628179 | O40: =IF(G40=0,0,I40/G40) -> 0.16741076 | P40: =IF(J40=0,0,K40/J40) -> 0.032432432 | Q40: =IF(M40=0,0,G40/M40) -> 353.03474 | R40: =IF(G40>0,G40,1E+99) -> 60368.94
A41: 5 | B41: May | C41: =DATE($C$11,A41,1) -> 45778 | D41: =EOMONTH(C41,0) -> 45808 | E41: =SUMIFS(d_Sales,d_Category,fCat,d_City,fCity,d_Cust,fCust,d_Pay,fPay,d_Date,">="&$C41,d_Date,"<="&$D41) -> 76020.12 | F41: =SUMIFS(d_SalesRet,d_Category,fCat,d_City,fCity,d_Cust,fCust,d_Pay,fPay,d_Date,">="&$C41,d_Date,"<="&$D41) -> 2444.9 | G41: =SUMIFS(d_NetSales,d_Category,fCat,d_City,fCity,d_Cust,fCust,d_Pay,fPay,d_Date,">="&$C41,d_Date,"<="&$D41) -> 73575.22 | H41: =SUMIFS(d_GP,d_Category,fCat,d_City,fCity,d_Cust,fCust,d_Pay,fPay,d_Date,">="&$C41,d_Date,"<="&$D41) -> 19322.34 | I41: =SUMIFS(d_NP,d_Category,fCat,d_City,fCity,d_Cust,fCust,d_Pay,fPay,d_Date,">="&$C41,d_Date,"<="&$D41) -> 12855.67 | J41: =SUMIFS(d_Qty,d_Category,fCat,d_City,fCity,d_Cust,fCust,d_Pay,fPay,d_Date,">="&$C41,d_Date,"<="&$D41) -> 535 | K41: =SUMIFS(d_RetQty,d_Category,fCat,d_City,fCity,d_Cust,fCust,d_Pay,fPay,d_Date,">="&$C41,d_Date,"<="&$D41) -> 16 | L41: =SUMIFS(d_NetQty,d_Category,fCat,d_City,fCity,d_Cust,fCust,d_Pay,fPay,d_Date,">="&$C41,d_Date,"<="&$D41) -> 519 | M41: =COUNTIFS(d_Category,fCat,d_City,fCity,d_Cust,fCust,d_Pay,fPay,d_Date,">="&$C41,d_Date,"<="&$D41) -> 168 | N41: =IF(G41=0,0,H41/G41) -> 0.26262021 | O41: =IF(G41=0,0,I41/G41) -> 0.17472826 | P41: =IF(J41=0,0,K41/J41) -> 0.029906542 | Q41: =IF(M41=0,0,G41/M41) -> 437.94774 | R41: =IF(G41>0,G41,1E+99) -> 73575.22
A42: 6 | B42: Jun | C42: =DATE($C$11,A42,1) -> 45809 | D42: =EOMONTH(C42,0) -> 45838 | E42: =SUMIFS(d_Sales,d_Category,fCat,d_City,fCity,d_Cust,fCust,d_Pay,fPay,d_Date,">="&$C42,d_Date,"<="&$D42) -> 56504.39 | F42: =SUMIFS(d_SalesRet,d_Category,fCat,d_City,fCity,d_Cust,fCust,d_Pay,fPay,d_Date,">="&$C42,d_Date,"<="&$D42) -> 112.5 | G42: =SUMIFS(d_NetSales,d_Category,fCat,d_City,fCity,d_Cust,fCust,d_Pay,fPay,d_Date,">="&$C42,d_Date,"<="&$D42) -> 56391.89 | H42: =SUMIFS(d_GP,d_Category,fCat,d_City,fCity,d_Cust,fCust,d_Pay,fPay,d_Date,">="&$C42,d_Date,"<="&$D42) -> 14085.3 | I42: =SUMIFS(d_NP,d_Category,fCat,d_City,fCity,d_Cust,fCust,d_Pay,fPay,d_Date,">="&$C42,d_Date,"<="&$D42) -> 8930.58 | J42: =SUMIFS(d_Qty,d_Category,fCat,d_City,fCity,d_Cust,fCust,d_Pay,fPay,d_Date,">="&$C42,d_Date,"<="&$D42) -> 493 | K42: =SUMIFS(d_RetQty,d_Category,fCat,d_City,fCity,d_Cust,fCust,d_Pay,fPay,d_Date,">="&$C42,d_Date,"<="&$D42) -> 1 | L42: =SUMIFS(d_NetQty,d_Category,fCat,d_City,fCity,d_Cust,fCust,d_Pay,fPay,d_Date,">="&$C42,d_Date,"<="&$D42) -> 492 | M42: =COUNTIFS(d_Category,fCat,d_City,fCity,d_Cust,fCust,d_Pay,fPay,d_Date,">="&$C42,d_Date,"<="&$D42) -> 150 | N42: =IF(G42=0,0,H42/G42) -> 0.24977528 | O42: =IF(G42=0,0,I42/G42) -> 0.15836639 | P42: =IF(J42=0,0,K42/J42) -> 0.0020283976 | Q42: =IF(M42=0,0,G42/M42) -> 375.94593 | R42: =IF(G42>0,G42,1E+99) -> 56391.89
A43: 7 | B43: Jul | C43: =DATE($C$11,A43,1) -> 45839 | D43: =EOMONTH(C43,0) -> 45869 | E43: =SUMIFS(d_Sales,d_Category,fCat,d_City,fCity,d_Cust,fCust,d_Pay,fPay,d_Date,">="&$C43,d_Date,"<="&$D43) -> 65915.22 | F43: =SUMIFS(d_SalesRet,d_Category,fCat,d_City,fCity,d_Cust,fCust,d_Pay,fPay,d_Date,">="&$C43,d_Date,"<="&$D43) -> 1177.25 | G43: =SUMIFS(d_NetSales,d_Category,fCat,d_City,fCity,d_Cust,fCust,d_Pay,fPay,d_Date,">="&$C43,d_Date,"<="&$D43) -> 64737.97 | H43: =SUMIFS(d_GP,d_Category,fCat,d_City,fCity,d_Cust,fCust,d_Pay,fPay,d_Date,">="&$C43,d_Date,"<="&$D43) -> 17542.9 | I43: =SUMIFS(d_NP,d_Category,fCat,d_City,fCity,d_Cust,fCust,d_Pay,fPay,d_Date,">="&$C43,d_Date,"<="&$D43) -> 11793.7 | J43: =SUMIFS(d_Qty,d_Category,fCat,d_City,fCity,d_Cust,fCust,d_Pay,fPay,d_Date,">="&$C43,d_Date,"<="&$D43) -> 495 | K43: =SUMIFS(d_RetQty,d_Category,fCat,d_City,fCity,d_Cust,fCust,d_Pay,fPay,d_Date,">="&$C43,d_Date,"<="&$D43) -> 9 | L43: =SUMIFS(d_NetQty,d_Category,fCat,d_City,fCity,d_Cust,fCust,d_Pay,fPay,d_Date,">="&$C43,d_Date,"<="&$D43) -> 486 | M43: =COUNTIFS(d_Category,fCat,d_City,fCity,d_Cust,fCust,d_Pay,fPay,d_Date,">="&$C43,d_Date,"<="&$D43) -> 161 | N43: =IF(G43=0,0,H43/G43) -> 0.27098316 | O43: =IF(G43=0,0,I43/G43) -> 0.18217593 | P43: =IF(J43=0,0,K43/J43) -> 0.018181818 | Q43: =IF(M43=0,0,G43/M43) -> 402.09919 | R43: =IF(G43>0,G43,1E+99) -> 64737.97
A44: 8 | B44: Aug | C44: =DATE($C$11,A44,1) -> 45870 | D44: =EOMONTH(C44,0) -> 45900 | E44: =SUMIFS(d_Sales,d_Category,fCat,d_City,fCity,d_Cust,fCust,d_Pay,fPay,d_Date,">="&$C44,d_Date,"<="&$D44) -> 80130.46 | F44: =SUMIFS(d_SalesRet,d_Category,fCat,d_City,fCity,d_Cust,fCust,d_Pay,fPay,d_Date,">="&$C44,d_Date,"<="&$D44) -> 1029 | G44: =SUMIFS(d_NetSales,d_Category,fCat,d_City,fCity,d_Cust,fCust,d_Pay,fPay,d_Date,">="&$C44,d_Date,"<="&$D44) -> 79101.46 | H44: =SUMIFS(d_GP,d_Category,fCat,d_City,fCity,d_Cust,fCust,d_Pay,fPay,d_Date,">="&$C44,d_Date,"<="&$D44) -> 19450.45 | I44: =SUMIFS(d_NP,d_Category,fCat,d_City,fCity,d_Cust,fCust,d_Pay,fPay,d_Date,">="&$C44,d_Date,"<="&$D44) -> 12142.13 | J44: =SUMIFS(d_Qty,d_Category,fCat,d_City,fCity,d_Cust,fCust,d_Pay,fPay,d_Date,">="&$C44,d_Date,"<="&$D44) -> 622 | K44: =SUMIFS(d_RetQty,d_Category,fCat,d_City,fCity,d_Cust,fCust,d_Pay,fPay,d_Date,">="&$C44,d_Date,"<="&$D44) -> 15 | L44: =SUMIFS(d_NetQty,d_Category,fCat,d_City,fCity,d_Cust,fCust,d_Pay,fPay,d_Date,">="&$C44,d_Date,"<="&$D44) -> 607 | M44: =COUNTIFS(d_Category,fCat,d_City,fCity,d_Cust,fCust,d_Pay,fPay,d_Date,">="&$C44,d_Date,"<="&$D44) -> 185 | N44: =IF(G44=0,0,H44/G44) -> 0.24589243 | O44: =IF(G44=0,0,I44/G44) -> 0.15350071 | P44: =IF(J44=0,0,K44/J44) -> 0.024115756 | Q44: =IF(M44=0,0,G44/M44) -> 427.57546 | R44: =IF(G44>0,G44,1E+99) -> 79101.46
A45: 9 | B45: Sep | C45: =DATE($C$11,A45,1) -> 45901 | D45: =EOMONTH(C45,0) -> 45930 | E45: =SUMIFS(d_Sales,d_Category,fCat,d_City,fCity,d_Cust,fCust,d_Pay,fPay,d_Date,">="&$C45,d_Date,"<="&$D45) -> 64346.25 | F45: =SUMIFS(d_SalesRet,d_Category,fCat,d_City,fCity,d_Cust,fCust,d_Pay,fPay,d_Date,">="&$C45,d_Date,"<="&$D45) -> 1079.7 | G45: =SUMIFS(d_NetSales,d_Category,fCat,d_City,fCity,d_Cust,fCust,d_Pay,fPay,d_Date,">="&$C45,d_Date,"<="&$D45) -> 63266.55 | H45: =SUMIFS(d_GP,d_Category,fCat,d_City,fCity,d_Cust,fCust,d_Pay,fPay,d_Date,">="&$C45,d_Date,"<="&$D45) -> 17065.84 | I45: =SUMIFS(d_NP,d_Category,fCat,d_City,fCity,d_Cust,fCust,d_Pay,fPay,d_Date,">="&$C45,d_Date,"<="&$D45) -> 11353.66 | J45: =SUMIFS(d_Qty,d_Category,fCat,d_City,fCity,d_Cust,fCust,d_Pay,fPay,d_Date,">="&$C45,d_Date,"<="&$D45) -> 494 | K45: =SUMIFS(d_RetQty,d_Category,fCat,d_City,fCity,d_Cust,fCust,d_Pay,fPay,d_Date,">="&$C45,d_Date,"<="&$D45) -> 11 | L45: =SUMIFS(d_NetQty,d_Category,fCat,d_City,fCity,d_Cust,fCust,d_Pay,fPay,d_Date,">="&$C45,d_Date,"<="&$D45) -> 483 | M45: =COUNTIFS(d_Category,fCat,d_City,fCity,d_Cust,fCust,d_Pay,fPay,d_Date,">="&$C45,d_Date,"<="&$D45) -> 152 | N45: =IF(G45=0,0,H45/G45) -> 0.26974507 | O45: =IF(G45=0,0,I45/G45) -> 0.17945755 | P45: =IF(J45=0,0,K45/J45) -> 0.022267206 | Q45: =IF(M45=0,0,G45/M45) -> 416.2273 | R45: =IF(G45>0,G45,1E+99) -> 63266.55
A46: 10 | B46: Oct | C46: =DATE($C$11,A46,1) -> 45931 | D46: =EOMONTH(C46,0) -> 45961 | E46: =SUMIFS(d_Sales,d_Category,fCat,d_City,fCity,d_Cust,fCust,d_Pay,fPay,d_Date,">="&$C46,d_Date,"<="&$D46) -> 72866.75 | F46: =SUMIFS(d_SalesRet,d_Category,fCat,d_City,fCity,d_Cust,fCust,d_Pay,fPay,d_Date,">="&$C46,d_Date,"<="&$D46) -> 594.25 | G46: =SUMIFS(d_NetSales,d_Category,fCat,d_City,fCity,d_Cust,fCust,d_Pay,fPay,d_Date,">="&$C46,d_Date,"<="&$D46) -> 72272.5 | H46: =SUMIFS(d_GP,d_Category,fCat,d_City,fCity,d_Cust,fCust,d_Pay,fPay,d_Date,">="&$C46,d_Date,"<="&$D46) -> 19282.54 | I46: =SUMIFS(d_NP,d_Category,fCat,d_City,fCity,d_Cust,fCust,d_Pay,fPay,d_Date,">="&$C46,d_Date,"<="&$D46) -> 12894.7 | J46: =SUMIFS(d_Qty,d_Category,fCat,d_City,fCity,d_Cust,fCust,d_Pay,fPay,d_Date,">="&$C46,d_Date,"<="&$D46) -> 553 | K46: =SUMIFS(d_RetQty,d_Category,fCat,d_City,fCity,d_Cust,fCust,d_Pay,fPay,d_Date,">="&$C46,d_Date,"<="&$D46) -> 7 | L46: =SUMIFS(d_NetQty,d_Category,fCat,d_City,fCity,d_Cust,fCust,d_Pay,fPay,d_Date,">="&$C46,d_Date,"<="&$D46) -> 546 | M46: =COUNTIFS(d_Category,fCat,d_City,fCity,d_Cust,fCust,d_Pay,fPay,d_Date,">="&$C46,d_Date,"<="&$D46) -> 177 | N46: =IF(G46=0,0,H46/G46) -> 0.26680328 | O46: =IF(G46=0,0,I46/G46) -> 0.17841779 | P46: =IF(J46=0,0,K46/J46) -> 0.012658228 | Q46: =IF(M46=0,0,G46/M46) -> 408.31921 | R46: =IF(G46>0,G46,1E+99) -> 72272.5
A47: 11 | B47: Nov | C47: =DATE($C$11,A47,1) -> 45962 | D47: =EOMONTH(C47,0) -> 45991 | E47: =SUMIFS(d_Sales,d_Category,fCat,d_City,fCity,d_Cust,fCust,d_Pay,fPay,d_Date,">="&$C47,d_Date,"<="&$D47) -> 54697.53 | F47: =SUMIFS(d_SalesRet,d_Category,fCat,d_City,fCity,d_Cust,fCust,d_Pay,fPay,d_Date,">="&$C47,d_Date,"<="&$D47) -> 1201.9 | G47: =SUMIFS(d_NetSales,d_Category,fCat,d_City,fCity,d_Cust,fCust,d_Pay,fPay,d_Date,">="&$C47,d_Date,"<="&$D47) -> 53495.63 | H47: =SUMIFS(d_GP,d_Category,fCat,d_City,fCity,d_Cust,fCust,d_Pay,fPay,d_Date,">="&$C47,d_Date,"<="&$D47) -> 13783.7 | I47: =SUMIFS(d_NP,d_Category,fCat,d_City,fCity,d_Cust,fCust,d_Pay,fPay,d_Date,">="&$C47,d_Date,"<="&$D47) -> 8836.61 | J47: =SUMIFS(d_Qty,d_Category,fCat,d_City,fCity,d_Cust,fCust,d_Pay,fPay,d_Date,">="&$C47,d_Date,"<="&$D47) -> 495 | K47: =SUMIFS(d_RetQty,d_Category,fCat,d_City,fCity,d_Cust,fCust,d_Pay,fPay,d_Date,">="&$C47,d_Date,"<="&$D47) -> 7 | L47: =SUMIFS(d_NetQty,d_Category,fCat,d_City,fCity,d_Cust,fCust,d_Pay,fPay,d_Date,">="&$C47,d_Date,"<="&$D47) -> 488 | M47: =COUNTIFS(d_Category,fCat,d_City,fCity,d_Cust,fCust,d_Pay,fPay,d_Date,">="&$C47,d_Date,"<="&$D47) -> 160 | N47: =IF(G47=0,0,H47/G47) -> 0.2576603 | O47: =IF(G47=0,0,I47/G47) -> 0.16518377 | P47: =IF(J47=0,0,K47/J47) -> 0.014141414 | Q47: =IF(M47=0,0,G47/M47) -> 334.34769 | R47: =IF(G47>0,G47,1E+99) -> 53495.63
A48: 12 | B48: Dec | C48: =DATE($C$11,A48,1) -> 45992 | D48: =EOMONTH(C48,0) -> 46022 | E48: =SUMIFS(d_Sales,d_Category,fCat,d_City,fCity,d_Cust,fCust,d_Pay,fPay,d_Date,">="&$C48,d_Date,"<="&$D48) -> 64278.95 | F48: =SUMIFS(d_SalesRet,d_Category,fCat,d_City,fCity,d_Cust,fCust,d_Pay,fPay,d_Date,">="&$C48,d_Date,"<="&$D48) -> 1660 | G48: =SUMIFS(d_NetSales,d_Category,fCat,d_City,fCity,d_Cust,fCust,d_Pay,fPay,d_Date,">="&$C48,d_Date,"<="&$D48) -> 62618.95 | H48: =SUMIFS(d_GP,d_Category,fCat,d_City,fCity,d_Cust,fCust,d_Pay,fPay,d_Date,">="&$C48,d_Date,"<="&$D48) -> 16403.21 | I48: =SUMIFS(d_NP,d_Category,fCat,d_City,fCity,d_Cust,fCust,d_Pay,fPay,d_Date,">="&$C48,d_Date,"<="&$D48) -> 10760.4 | J48: =SUMIFS(d_Qty,d_Category,fCat,d_City,fCity,d_Cust,fCust,d_Pay,fPay,d_Date,">="&$C48,d_Date,"<="&$D48) -> 564 | K48: =SUMIFS(d_RetQty,d_Category,fCat,d_City,fCity,d_Cust,fCust,d_Pay,fPay,d_Date,">="&$C48,d_Date,"<="&$D48) -> 11 | L48: =SUMIFS(d_NetQty,d_Category,fCat,d_City,fCity,d_Cust,fCust,d_Pay,fPay,d_Date,">="&$C48,d_Date,"<="&$D48) -> 553 | M48: =COUNTIFS(d_Category,fCat,d_City,fCity,d_Cust,fCust,d_Pay,fPay,d_Date,">="&$C48,d_Date,"<="&$D48) -> 167 | N48: =IF(G48=0,0,H48/G48) -> 0.26195281 | O48: =IF(G48=0,0,I48/G48) -> 0.17183936 | P48: =IF(J48=0,0,K48/J48) -> 0.019503546 | Q48: =IF(M48=0,0,G48/M48) -> 374.96377 | R48: =IF(G48>0,G48,1E+99) -> 62618.95
A49: Total (full year, filtered) | E49: =SUM(E37:E48) -> 793746.79 | F49: =SUM(F37:F48) -> 13807.74 | G49: =SUM(G37:G48) -> 779939.05 | H49: =SUM(H37:H48) -> 202289.58 | I49: =SUM(I37:I48) -> 132322.39 | J49: =SUM(J37:J48) -> 6470 | K49: =SUM(K37:K48) -> 114 | L49: =SUM(L37:L48) -> 6356 | M49: =SUM(M37:M48) -> 2000 | N49: =IF(G49=0,0,H49/G49) -> 0.25936588 | O49: =IF(G49=0,0,I49/G49) -> 0.16965735 | P49: =IF(J49=0,0,K49/J49) -> 0.017619784 | Q49: =IF(M49=0,0,G49/M49) -> 389.96952
A52: 4. CATEGORY (all filters applied)
A53: Category | B53: Net Sales (₹) | C53: Gross Profit (₹) | D53: Net Profit (₹) | E53: Qty | F53: Return Qty | G53: Net Qty | H53: Sales Return (₹) | I53: GP Margin | J53: NP Margin | K53: Return Rate (Qty) | L53: Share of Net Sales | M53: Key: weakest | N53: Key: return rate
A54: Groceries | B54: =SUMIFS(d_NetSales,d_Category,fCat,d_City,fCity,d_Cust,fCust,d_Pay,fPay,d_Category,$A54,d_Date,">="&fStart,d_Date,"<="&fEnd) -> 201363.76 | C54: =SUMIFS(d_GP,d_Category,fCat,d_City,fCity,d_Cust,fCust,d_Pay,fPay,d_Category,$A54,d_Date,">="&fStart,d_Date,"<="&fEnd) -> 53116 | D54: =SUMIFS(d_NP,d_Category,fCat,d_City,fCity,d_Cust,fCust,d_Pay,fPay,d_Category,$A54,d_Date,">="&fStart,d_Date,"<="&fEnd) -> 34797.47 | E54: =SUMIFS(d_Qty,d_Category,fCat,d_City,fCity,d_Cust,fCust,d_Pay,fPay,d_Category,$A54,d_Date,">="&fStart,d_Date,"<="&fEnd) -> 950 | F54: =SUMIFS(d_RetQty,d_Category,fCat,d_City,fCity,d_Cust,fCust,d_Pay,fPay,d_Category,$A54,d_Date,">="&fStart,d_Date,"<="&fEnd) -> 20 | G54: =SUMIFS(d_NetQty,d_Category,fCat,d_City,fCity,d_Cust,fCust,d_Pay,fPay,d_Category,$A54,d_Date,">="&fStart,d_Date,"<="&fEnd) -> 930 | H54: =SUMIFS(d_SalesRet,d_Category,fCat,d_City,fCity,d_Cust,fCust,d_Pay,fPay,d_Category,$A54,d_Date,">="&fStart,d_Date,"<="&fEnd) -> 4526.2 | I54: =IF(B54=0,0,C54/B54) -> 0.26378133 | J54: =IF(B54=0,0,D54/B54) -> 0.172809 | K54: =IF(E54=0,0,F54/E54) -> 0.021052632 | L54: =IF($B$61=0,0,B54/$B$61) -> 0.38321413 | M54: =IF(B54>0,B54,1E+99) -> 201363.76 | N54: =IF(E54>0,K54,-1) -> 0.021052632
A55: Household | B55: =SUMIFS(d_NetSales,d_Category,fCat,d_City,fCity,d_Cust,fCust,d_Pay,fPay,d_Category,$A55,d_Date,">="&fStart,d_Date,"<="&fEnd) -> 101609.35 | C55: =SUMIFS(d_GP,d_Category,fCat,d_City,fCity,d_Cust,fCust,d_Pay,fPay,d_Category,$A55,d_Date,">="&fStart,d_Date,"<="&fEnd) -> 25848.17 | D55: =SUMIFS(d_NP,d_Category,fCat,d_City,fCity,d_Cust,fCust,d_Pay,fPay,d_Category,$A55,d_Date,">="&fStart,d_Date,"<="&fEnd) -> 16689.66 | E55: =SUMIFS(d_Qty,d_Category,fCat,d_City,fCity,d_Cust,fCust,d_Pay,fPay,d_Category,$A55,d_Date,">="&fStart,d_Date,"<="&fEnd) -> 647 | F55: =SUMIFS(d_RetQty,d_Category,fCat,d_City,fCity,d_Cust,fCust,d_Pay,fPay,d_Category,$A55,d_Date,">="&fStart,d_Date,"<="&fEnd) -> 10 | G55: =SUMIFS(d_NetQty,d_Category,fCat,d_City,fCity,d_Cust,fCust,d_Pay,fPay,d_Category,$A55,d_Date,">="&fStart,d_Date,"<="&fEnd) -> 637 | H55: =SUMIFS(d_SalesRet,d_Category,fCat,d_City,fCity,d_Cust,fCust,d_Pay,fPay,d_Category,$A55,d_Date,">="&fStart,d_Date,"<="&fEnd) -> 1133.75 | I55: =IF(B55=0,0,C55/B55) -> 0.25438771 | J55: =IF(B55=0,0,D55/B55) -> 0.16425319 | K55: =IF(E55=0,0,F55/E55) -> 0.015455951 | L55: =IF($B$61=0,0,B55/$B$61) -> 0.19337213 | M55: =IF(B55>0,B55,1E+99) -> 101609.35 | N55: =IF(E55>0,K55,-1) -> 0.015455951
A56: Beverages | B56: =SUMIFS(d_NetSales,d_Category,fCat,d_City,fCity,d_Cust,fCust,d_Pay,fPay,d_Category,$A56,d_Date,">="&fStart,d_Date,"<="&fEnd) -> 79609.66 | C56: =SUMIFS(d_GP,d_Category,fCat,d_City,fCity,d_Cust,fCust,d_Pay,fPay,d_Category,$A56,d_Date,">="&fStart,d_Date,"<="&fEnd) -> 21508.81 | D56: =SUMIFS(d_NP,d_Category,fCat,d_City,fCity,d_Cust,fCust,d_Pay,fPay,d_Category,$A56,d_Date,">="&fStart,d_Date,"<="&fEnd) -> 14498.66 | E56: =SUMIFS(d_Qty,d_Category,fCat,d_City,fCity,d_Cust,fCust,d_Pay,fPay,d_Category,$A56,d_Date,">="&fStart,d_Date,"<="&fEnd) -> 827 | F56: =SUMIFS(d_RetQty,d_Category,fCat,d_City,fCity,d_Cust,fCust,d_Pay,fPay,d_Category,$A56,d_Date,">="&fStart,d_Date,"<="&fEnd) -> 13 | G56: =SUMIFS(d_NetQty,d_Category,fCat,d_City,fCity,d_Cust,fCust,d_Pay,fPay,d_Category,$A56,d_Date,">="&fStart,d_Date,"<="&fEnd) -> 814 | H56: =SUMIFS(d_SalesRet,d_Category,fCat,d_City,fCity,d_Cust,fCust,d_Pay,fPay,d_Category,$A56,d_Date,">="&fStart,d_Date,"<="&fEnd) -> 770.8 | I56: =IF(B56=0,0,C56/B56) -> 0.27017839 | J56: =IF(B56=0,0,D56/B56) -> 0.18212187 | K56: =IF(E56=0,0,F56/E56) -> 0.015719468 | L56: =IF($B$61=0,0,B56/$B$61) -> 0.15150465 | M56: =IF(B56>0,B56,1E+99) -> 79609.66 | N56: =IF(E56>0,K56,-1) -> 0.015719468
A57: Personal Care | B57: =SUMIFS(d_NetSales,d_Category,fCat,d_City,fCity,d_Cust,fCust,d_Pay,fPay,d_Category,$A57,d_Date,">="&fStart,d_Date,"<="&fEnd) -> 68748.7 | C57: =SUMIFS(d_GP,d_Category,fCat,d_City,fCity,d_Cust,fCust,d_Pay,fPay,d_Category,$A57,d_Date,">="&fStart,d_Date,"<="&fEnd) -> 17026.09 | D57: =SUMIFS(d_NP,d_Category,fCat,d_City,fCity,d_Cust,fCust,d_Pay,fPay,d_Category,$A57,d_Date,">="&fStart,d_Date,"<="&fEnd) -> 10854.59 | E57: =SUMIFS(d_Qty,d_Category,fCat,d_City,fCity,d_Cust,fCust,d_Pay,fPay,d_Category,$A57,d_Date,">="&fStart,d_Date,"<="&fEnd) -> 645 | F57: =SUMIFS(d_RetQty,d_Category,fCat,d_City,fCity,d_Cust,fCust,d_Pay,fPay,d_Category,$A57,d_Date,">="&fStart,d_Date,"<="&fEnd) -> 10 | G57: =SUMIFS(d_NetQty,d_Category,fCat,d_City,fCity,d_Cust,fCust,d_Pay,fPay,d_Category,$A57,d_Date,">="&fStart,d_Date,"<="&fEnd) -> 635 | H57: =SUMIFS(d_SalesRet,d_Category,fCat,d_City,fCity,d_Cust,fCust,d_Pay,fPay,d_Category,$A57,d_Date,">="&fStart,d_Date,"<="&fEnd) -> 1572.5 | I57: =IF(B57=0,0,C57/B57) -> 0.2476569 | J57: =IF(B57=0,0,D57/B57) -> 0.15788793 | K57: =IF(E57=0,0,F57/E57) -> 0.015503876 | L57: =IF($B$61=0,0,B57/$B$61) -> 0.13083523 | M57: =IF(B57>0,B57,1E+99) -> 68748.7 | N57: =IF(E57>0,K57,-1) -> 0.015503876
A58: Electronics | B58: =SUMIFS(d_NetSales,d_Category,fCat,d_City,fCity,d_Cust,fCust,d_Pay,fPay,d_Category,$A58,d_Date,">="&fStart,d_Date,"<="&fEnd) -> 40416.3 | C58: =SUMIFS(d_GP,d_Category,fCat,d_City,fCity,d_Cust,fCust,d_Pay,fPay,d_Category,$A58,d_Date,">="&fStart,d_Date,"<="&fEnd) -> 10478.62 | D58: =SUMIFS(d_NP,d_Category,fCat,d_City,fCity,d_Cust,fCust,d_Pay,fPay,d_Category,$A58,d_Date,">="&fStart,d_Date,"<="&fEnd) -> 6865.77 | E58: =SUMIFS(d_Qty,d_Category,fCat,d_City,fCity,d_Cust,fCust,d_Pay,fPay,d_Category,$A58,d_Date,">="&fStart,d_Date,"<="&fEnd) -> 405 | F58: =SUMIFS(d_RetQty,d_Category,fCat,d_City,fCity,d_Cust,fCust,d_Pay,fPay,d_Category,$A58,d_Date,">="&fStart,d_Date,"<="&fEnd) -> 4 | G58: =SUMIFS(d_NetQty,d_Category,fCat,d_City,fCity,d_Cust,fCust,d_Pay,fPay,d_Category,$A58,d_Date,">="&fStart,d_Date,"<="&fEnd) -> 401 | H58: =SUMIFS(d_SalesRet,d_Category,fCat,d_City,fCity,d_Cust,fCust,d_Pay,fPay,d_Category,$A58,d_Date,">="&fStart,d_Date,"<="&fEnd) -> 432 | I58: =IF(B58=0,0,C58/B58) -> 0.25926718 | J58: =IF(B58=0,0,D58/B58) -> 0.16987626 | K58: =IF(E58=0,0,F58/E58) -> 0.0098765432 | L58: =IF($B$61=0,0,B58/$B$61) -> 0.076916011 | M58: =IF(B58>0,B58,1E+99) -> 40416.3 | N58: =IF(E58>0,K58,-1) -> 0.0098765432
A59: Snacks | B59: =SUMIFS(d_NetSales,d_Category,fCat,d_City,fCity,d_Cust,fCust,d_Pay,fPay,d_Category,$A59,d_Date,">="&fStart,d_Date,"<="&fEnd) -> 24327.05 | C59: =SUMIFS(d_GP,d_Category,fCat,d_City,fCity,d_Cust,fCust,d_Pay,fPay,d_Category,$A59,d_Date,">="&fStart,d_Date,"<="&fEnd) -> 6522.23 | D59: =SUMIFS(d_NP,d_Category,fCat,d_City,fCity,d_Cust,fCust,d_Pay,fPay,d_Category,$A59,d_Date,">="&fStart,d_Date,"<="&fEnd) -> 4238.5 | E59: =SUMIFS(d_Qty,d_Category,fCat,d_City,fCity,d_Cust,fCust,d_Pay,fPay,d_Category,$A59,d_Date,">="&fStart,d_Date,"<="&fEnd) -> 628 | F59: =SUMIFS(d_RetQty,d_Category,fCat,d_City,fCity,d_Cust,fCust,d_Pay,fPay,d_Category,$A59,d_Date,">="&fStart,d_Date,"<="&fEnd) -> 19 | G59: =SUMIFS(d_NetQty,d_Category,fCat,d_City,fCity,d_Cust,fCust,d_Pay,fPay,d_Category,$A59,d_Date,">="&fStart,d_Date,"<="&fEnd) -> 609 | H59: =SUMIFS(d_SalesRet,d_Category,fCat,d_City,fCity,d_Cust,fCust,d_Pay,fPay,d_Category,$A59,d_Date,">="&fStart,d_Date,"<="&fEnd) -> 799.25 | I59: =IF(B59=0,0,C59/B59) -> 0.26810608 | J59: =IF(B59=0,0,D59/B59) -> 0.17422992 | K59: =IF(E59=0,0,F59/E59) -> 0.030254777 | L59: =IF($B$61=0,0,B59/$B$61) -> 0.046296658 | M59: =IF(B59>0,B59,1E+99) -> 24327.05 | N59: =IF(E59>0,K59,-1) -> 0.030254777
A60: Stationery | B60: =SUMIFS(d_NetSales,d_Category,fCat,d_City,fCity,d_Cust,fCust,d_Pay,fPay,d_Category,$A60,d_Date,">="&fStart,d_Date,"<="&fEnd) -> 9385.35 | C60: =SUMIFS(d_GP,d_Category,fCat,d_City,fCity,d_Cust,fCust,d_Pay,fPay,d_Category,$A60,d_Date,">="&fStart,d_Date,"<="&fEnd) -> 2436.36 | D60: =SUMIFS(d_NP,d_Category,fCat,d_City,fCity,d_Cust,fCust,d_Pay,fPay,d_Category,$A60,d_Date,">="&fStart,d_Date,"<="&fEnd) -> 1622.8 | E60: =SUMIFS(d_Qty,d_Category,fCat,d_City,fCity,d_Cust,fCust,d_Pay,fPay,d_Category,$A60,d_Date,">="&fStart,d_Date,"<="&fEnd) -> 149 | F60: =SUMIFS(d_RetQty,d_Category,fCat,d_City,fCity,d_Cust,fCust,d_Pay,fPay,d_Category,$A60,d_Date,">="&fStart,d_Date,"<="&fEnd) -> 1 | G60: =SUMIFS(d_NetQty,d_Category,fCat,d_City,fCity,d_Cust,fCust,d_Pay,fPay,d_Category,$A60,d_Date,">="&fStart,d_Date,"<="&fEnd) -> 148 | H60: =SUMIFS(d_SalesRet,d_Category,fCat,d_City,fCity,d_Cust,fCust,d_Pay,fPay,d_Category,$A60,d_Date,">="&fStart,d_Date,"<="&fEnd) -> 65 | I60: =IF(B60=0,0,C60/B60) -> 0.25959181 | J60: =IF(B60=0,0,D60/B60) -> 0.17290778 | K60: =IF(E60=0,0,F60/E60) -> 0.0067114094 | L60: =IF($B$61=0,0,B60/$B$61) -> 0.017861202 | M60: =IF(B60>0,B60,1E+99) -> 9385.35 | N60: =IF(E60>0,K60,-1) -> 0.0067114094
A61: Total | B61: =SUM(B54:B60) -> 525460.17 | C61: =SUM(C54:C60) -> 136936.28 | D61: =SUM(D54:D60) -> 89567.45 | E61: =SUM(E54:E60) -> 4251 | F61: =SUM(F54:F60) -> 77 | G61: =SUM(G54:G60) -> 4174 | H61: =SUM(H54:H60) -> 9299.5 | I61: =IF(B61=0,0,C61/B61) -> 0.26060259 | J61: =IF(B61=0,0,D61/B61) -> 0.17045526 | K61: =IF(E61=0,0,F61/E61) -> 0.018113385 | L61: =SUM(L54:L60) -> 1
A64: 5. PRODUCT (all filters applied) — list ordered by full-year Net Sales at build time; rankings below are dynamic
A65: Product | B65: Category | C65: Net Sales (₹) | D65: Net Qty | E65: Gross Profit (₹) | F65: Net Profit (₹) | G65: Qty | H65: Return Qty | I65: Sales Return (₹) | J65: GP Margin | K65: NP Margin | L65: Return Rate (Qty) | M65: Key: top sales | N65: Key: bottom sales | O65: Key: returns ₹
A66: Rice 5kg | B66: =INDEX(d_Category,MATCH(A66,d_Product,0)) -> Groceries | C66: =SUMIFS(d_NetSales,d_Category,fCat,d_City,fCity,d_Cust,fCust,d_Pay,fPay,d_Product,$A66,d_Date,">="&fStart,d_Date,"<="&fEnd) -> 82152 | D66: =SUMIFS(d_NetQty,d_Category,fCat,d_City,fCity,d_Cust,fCust,d_Pay,fPay,d_Product,$A66,d_Date,">="&fStart,d_Date,"<="&fEnd) -> 202 | E66: =SUMIFS(d_GP,d_Category,fCat,d_City,fCity,d_Cust,fCust,d_Pay,fPay,d_Product,$A66,d_Date,">="&fStart,d_Date,"<="&fEnd) -> 21563.21 | F66: =SUMIFS(d_NP,d_Category,fCat,d_City,fCity,d_Cust,fCust,d_Pay,fPay,d_Product,$A66,d_Date,">="&fStart,d_Date,"<="&fEnd) -> 14059.79 | G66: =SUMIFS(d_Qty,d_Category,fCat,d_City,fCity,d_Cust,fCust,d_Pay,fPay,d_Product,$A66,d_Date,">="&fStart,d_Date,"<="&fEnd) -> 208 | H66: =SUMIFS(d_RetQty,d_Category,fCat,d_City,fCity,d_Cust,fCust,d_Pay,fPay,d_Product,$A66,d_Date,">="&fStart,d_Date,"<="&fEnd) -> 6 | I66: =SUMIFS(d_SalesRet,d_Category,fCat,d_City,fCity,d_Cust,fCust,d_Pay,fPay,d_Product,$A66,d_Date,">="&fStart,d_Date,"<="&fEnd) -> 2314.2 | J66: =IF(C66=0,0,E66/C66) -> 0.26247943 | K66: =IF(C66=0,0,F66/C66) -> 0.17114361 | L66: =IF(G66=0,0,H66/G66) -> 0.028846154 | M66: =C66+ROW()*0.000001 -> 82152 | N66: =IF(C66>0,C66+ROW()*0.000001,1000000000000) -> 82152 | O66: =I66+ROW()*0.000001 -> 2314.2001
A67: Wheat Flour 5kg | B67: =INDEX(d_Category,MATCH(A67,d_Product,0)) -> Groceries | C67: =SUMIFS(d_NetSales,d_Category,fCat,d_City,fCity,d_Cust,fCust,d_Pay,fPay,d_Product,$A67,d_Date,">="&fStart,d_Date,"<="&fEnd) -> 77599.2 | D67: =SUMIFS(d_NetQty,d_Category,fCat,d_City,fCity,d_Cust,fCust,d_Pay,fPay,d_Product,$A67,d_Date,">="&fStart,d_Date,"<="&fEnd) -> 256 | E67: =SUMIFS(d_GP,d_Category,fCat,d_City,fCity,d_Cust,fCust,d_Pay,fPay,d_Product,$A67,d_Date,">="&fStart,d_Date,"<="&fEnd) -> 20357.54 | F67: =SUMIFS(d_NP,d_Category,fCat,d_City,fCity,d_Cust,fCust,d_Pay,fPay,d_Product,$A67,d_Date,">="&fStart,d_Date,"<="&fEnd) -> 13245.18 | G67: =SUMIFS(d_Qty,d_Category,fCat,d_City,fCity,d_Cust,fCust,d_Pay,fPay,d_Product,$A67,d_Date,">="&fStart,d_Date,"<="&fEnd) -> 258 | H67: =SUMIFS(d_RetQty,d_Category,fCat,d_City,fCity,d_Cust,fCust,d_Pay,fPay,d_Product,$A67,d_Date,">="&fStart,d_Date,"<="&fEnd) -> 2 | I67: =SUMIFS(d_SalesRet,d_Category,fCat,d_City,fCity,d_Cust,fCust,d_Pay,fPay,d_Product,$A67,d_Date,">="&fStart,d_Date,"<="&fEnd) -> 573.5 | J67: =IF(C67=0,0,E67/C67) -> 0.26234214 | K67: =IF(C67=0,0,F67/C67) -> 0.17068707 | L67: =IF(G67=0,0,H67/G67) -> 0.007751938 | M67: =C67+ROW()*0.000001 -> 77599.2 | N67: =IF(C67>0,C67+ROW()*0.000001,1000000000000) -> 77599.2 | O67: =I67+ROW()*0.000001 -> 573.50007
A68: Laundry Detergent 2kg | B68: =INDEX(d_Category,MATCH(A68,d_Product,0)) -> Household | C68: =SUMIFS(d_NetSales,d_Category,fCat,d_City,fCity,d_Cust,fCust,d_Pay,fPay,d_Product,$A68,d_Date,">="&fStart,d_Date,"<="&fEnd) -> 55955.2 | D68: =SUMIFS(d_NetQty,d_Category,fCat,d_City,fCity,d_Cust,fCust,d_Pay,fPay,d_Product,$A68,d_Date,">="&fStart,d_Date,"<="&fEnd) -> 208 | E68: =SUMIFS(d_GP,d_Category,fCat,d_City,fCity,d_Cust,fCust,d_Pay,fPay,d_Product,$A68,d_Date,">="&fStart,d_Date,"<="&fEnd) -> 14269.83 | F68: =SUMIFS(d_NP,d_Category,fCat,d_City,fCity,d_Cust,fCust,d_Pay,fPay,d_Product,$A68,d_Date,">="&fStart,d_Date,"<="&fEnd) -> 9167.95 | G68: =SUMIFS(d_Qty,d_Category,fCat,d_City,fCity,d_Cust,fCust,d_Pay,fPay,d_Product,$A68,d_Date,">="&fStart,d_Date,"<="&fEnd) -> 209 | H68: =SUMIFS(d_RetQty,d_Category,fCat,d_City,fCity,d_Cust,fCust,d_Pay,fPay,d_Product,$A68,d_Date,">="&fStart,d_Date,"<="&fEnd) -> 1 | I68: =SUMIFS(d_SalesRet,d_Category,fCat,d_City,fCity,d_Cust,fCust,d_Pay,fPay,d_Product,$A68,d_Date,">="&fStart,d_Date,"<="&fEnd) -> 266 | J68: =IF(C68=0,0,E68/C68) -> 0.25502241 | K68: =IF(C68=0,0,F68/C68) -> 0.16384447 | L68: =IF(G68=0,0,H68/G68) -> 0.004784689 | M68: =C68+ROW()*0.000001 -> 55955.2 | N68: =IF(C68>0,C68+ROW()*0.000001,1000000000000) -> 55955.2 | O68: =I68+ROW()*0.000001 -> 266.00007
A69: Coffee 200g | B69: =INDEX(d_Category,MATCH(A69,d_Product,0)) -> Beverages | C69: =SUMIFS(d_NetSales,d_Category,fCat,d_City,fCity,d_Cust,fCust,d_Pay,fPay,d_Product,$A69,d_Date,">="&fStart,d_Date,"<="&fEnd) -> 44530.2 | D69: =SUMIFS(d_NetQty,d_Category,fCat,d_City,fCity,d_Cust,fCust,d_Pay,fPay,d_Product,$A69,d_Date,">="&fStart,d_Date,"<="&fEnd) -> 255 | E69: =SUMIFS(d_GP,d_Category,fCat,d_City,fCity,d_Cust,fCust,d_Pay,fPay,d_Product,$A69,d_Date,">="&fStart,d_Date,"<="&fEnd) -> 12222.53 | F69: =SUMIFS(d_NP,d_Category,fCat,d_City,fCity,d_Cust,fCust,d_Pay,fPay,d_Product,$A69,d_Date,">="&fStart,d_Date,"<="&fEnd) -> 8446.31 | G69: =SUMIFS(d_Qty,d_Category,fCat,d_City,fCity,d_Cust,fCust,d_Pay,fPay,d_Product,$A69,d_Date,">="&fStart,d_Date,"<="&fEnd) -> 255 | H69: =SUMIFS(d_RetQty,d_Category,fCat,d_City,fCity,d_Cust,fCust,d_Pay,fPay,d_Product,$A69,d_Date,">="&fStart,d_Date,"<="&fEnd) -> 0 | I69: =SUMIFS(d_SalesRet,d_Category,fCat,d_City,fCity,d_Cust,fCust,d_Pay,fPay,d_Product,$A69,d_Date,">="&fStart,d_Date,"<="&fEnd) -> 0 | J69: =IF(C69=0,0,E69/C69) -> 0.27447732 | K69: =IF(C69=0,0,F69/C69) -> 0.189676 | L69: =IF(G69=0,0,H69/G69) -> 0 | M69: =C69+ROW()*0.000001 -> 44530.2 | N69: =IF(C69>0,C69+ROW()*0.000001,1000000000000) -> 44530.2 | O69: =I69+ROW()*0.000001 -> 6.9e-05
A70: Shampoo 340ml | B70: =INDEX(d_Category,MATCH(A70,d_Product,0)) -> Personal Care | C70: =SUMIFS(d_NetSales,d_Category,fCat,d_City,fCity,d_Cust,fCust,d_Pay,fPay,d_Product,$A70,d_Date,">="&fStart,d_Date,"<="&fEnd) -> 36071.7 | D70: =SUMIFS(d_NetQty,d_Category,fCat,d_City,fCity,d_Cust,fCust,d_Pay,fPay,d_Product,$A70,d_Date,">="&fStart,d_Date,"<="&fEnd) -> 178 | E70: =SUMIFS(d_GP,d_Category,fCat,d_City,fCity,d_Cust,fCust,d_Pay,fPay,d_Product,$A70,d_Date,">="&fStart,d_Date,"<="&fEnd) -> 8805.42 | F70: =SUMIFS(d_NP,d_Category,fCat,d_City,fCity,d_Cust,fCust,d_Pay,fPay,d_Product,$A70,d_Date,">="&fStart,d_Date,"<="&fEnd) -> 5662.07 | G70: =SUMIFS(d_Qty,d_Category,fCat,d_City,fCity,d_Cust,fCust,d_Pay,fPay,d_Product,$A70,d_Date,">="&fStart,d_Date,"<="&fEnd) -> 183 | H70: =SUMIFS(d_RetQty,d_Category,fCat,d_City,fCity,d_Cust,fCust,d_Pay,fPay,d_Product,$A70,d_Date,">="&fStart,d_Date,"<="&fEnd) -> 5 | I70: =SUMIFS(d_SalesRet,d_Category,fCat,d_City,fCity,d_Cust,fCust,d_Pay,fPay,d_Product,$A70,d_Date,">="&fStart,d_Date,"<="&fEnd) -> 1050 | J70: =IF(C70=0,0,E70/C70) -> 0.24410882 | K70: =IF(C70=0,0,F70/C70) -> 0.1569671 | L70: =IF(G70=0,0,H70/G70) -> 0.027322404 | M70: =C70+ROW()*0.000001 -> 36071.7 | N70: =IF(C70>0,C70+ROW()*0.000001,1000000000000) -> 36071.7 | O70: =I70+ROW()*0.000001 -> 1050.0001
A71: Cooking Oil 1L | B71: =INDEX(d_Category,MATCH(A71,d_Product,0)) -> Groceries | C71: =SUMIFS(d_NetSales,d_Category,fCat,d_City,fCity,d_Cust,fCust,d_Pay,fPay,d_Product,$A71,d_Date,">="&fStart,d_Date,"<="&fEnd) -> 27979.2 | D71: =SUMIFS(d_NetQty,d_Category,fCat,d_City,fCity,d_Cust,fCust,d_Pay,fPay,d_Product,$A71,d_Date,">="&fStart,d_Date,"<="&fEnd) -> 199 | E71: =SUMIFS(d_GP,d_Category,fCat,d_City,fCity,d_Cust,fCust,d_Pay,fPay,d_Product,$A71,d_Date,">="&fStart,d_Date,"<="&fEnd) -> 7730.88 | F71: =SUMIFS(d_NP,d_Category,fCat,d_City,fCity,d_Cust,fCust,d_Pay,fPay,d_Product,$A71,d_Date,">="&fStart,d_Date,"<="&fEnd) -> 5259.37 | G71: =SUMIFS(d_Qty,d_Category,fCat,d_City,fCity,d_Cust,fCust,d_Pay,fPay,d_Product,$A71,d_Date,">="&fStart,d_Date,"<="&fEnd) -> 211 | H71: =SUMIFS(d_RetQty,d_Category,fCat,d_City,fCity,d_Cust,fCust,d_Pay,fPay,d_Product,$A71,d_Date,">="&fStart,d_Date,"<="&fEnd) -> 12 | I71: =SUMIFS(d_SalesRet,d_Category,fCat,d_City,fCity,d_Cust,fCust,d_Pay,fPay,d_Product,$A71,d_Date,">="&fStart,d_Date,"<="&fEnd) -> 1638.5 | J71: =IF(C71=0,0,E71/C71) -> 0.27630811 | K71: =IF(C71=0,0,F71/C71) -> 0.18797428 | L71: =IF(G71=0,0,H71/G71) -> 0.056872038 | M71: =C71+ROW()*0.000001 -> 27979.2 | N71: =IF(C71>0,C71+ROW()*0.000001,1000000000000) -> 27979.2 | O71: =I71+ROW()*0.000001 -> 1638.5001
A72: Floor Cleaner 1L | B72: =INDEX(d_Category,MATCH(A72,d_Product,0)) -> Household | C72: =SUMIFS(d_NetSales,d_Category,fCat,d_City,fCity,d_Cust,fCust,d_Pay,fPay,d_Product,$A72,d_Date,">="&fStart,d_Date,"<="&fEnd) -> 25745 | D72: =SUMIFS(d_NetQty,d_Category,fCat,d_City,fCity,d_Cust,fCust,d_Pay,fPay,d_Product,$A72,d_Date,">="&fStart,d_Date,"<="&fEnd) -> 212 | E72: =SUMIFS(d_GP,d_Category,fCat,d_City,fCity,d_Cust,fCust,d_Pay,fPay,d_Product,$A72,d_Date,">="&fStart,d_Date,"<="&fEnd) -> 6383.05 | F72: =SUMIFS(d_NP,d_Category,fCat,d_City,fCity,d_Cust,fCust,d_Pay,fPay,d_Product,$A72,d_Date,">="&fStart,d_Date,"<="&fEnd) -> 4096.08 | G72: =SUMIFS(d_Qty,d_Category,fCat,d_City,fCity,d_Cust,fCust,d_Pay,fPay,d_Product,$A72,d_Date,">="&fStart,d_Date,"<="&fEnd) -> 213 | H72: =SUMIFS(d_RetQty,d_Category,fCat,d_City,fCity,d_Cust,fCust,d_Pay,fPay,d_Product,$A72,d_Date,">="&fStart,d_Date,"<="&fEnd) -> 1 | I72: =SUMIFS(d_SalesRet,d_Category,fCat,d_City,fCity,d_Cust,fCust,d_Pay,fPay,d_Product,$A72,d_Date,">="&fStart,d_Date,"<="&fEnd) -> 112.5 | J72: =IF(C72=0,0,E72/C72) -> 0.24793358 | K72: =IF(C72=0,0,F72/C72) -> 0.15910196 | L72: =IF(G72=0,0,H72/G72) -> 0.0046948357 | M72: =C72+ROW()*0.000001 -> 25745 | N72: =IF(C72>0,C72+ROW()*0.000001,1000000000000) -> 25745 | O72: =I72+ROW()*0.000001 -> 112.50007
A73: Tea 250g | B73: =INDEX(d_Category,MATCH(A73,d_Product,0)) -> Beverages | C73: =SUMIFS(d_NetSales,d_Category,fCat,d_City,fCity,d_Cust,fCust,d_Pay,fPay,d_Product,$A73,d_Date,">="&fStart,d_Date,"<="&fEnd) -> 22087.5 | D73: =SUMIFS(d_NetQty,d_Category,fCat,d_City,fCity,d_Cust,fCust,d_Pay,fPay,d_Product,$A73,d_Date,">="&fStart,d_Date,"<="&fEnd) -> 180 | E73: =SUMIFS(d_GP,d_Category,fCat,d_City,fCity,d_Cust,fCust,d_Pay,fPay,d_Product,$A73,d_Date,">="&fStart,d_Date,"<="&fEnd) -> 5938.55 | F73: =SUMIFS(d_NP,d_Category,fCat,d_City,fCity,d_Cust,fCust,d_Pay,fPay,d_Product,$A73,d_Date,">="&fStart,d_Date,"<="&fEnd) -> 3893.15 | G73: =SUMIFS(d_Qty,d_Category,fCat,d_City,fCity,d_Cust,fCust,d_Pay,fPay,d_Product,$A73,d_Date,">="&fStart,d_Date,"<="&fEnd) -> 182 | H73: =SUMIFS(d_RetQty,d_Category,fCat,d_City,fCity,d_Cust,fCust,d_Pay,fPay,d_Product,$A73,d_Date,">="&fStart,d_Date,"<="&fEnd) -> 2 | I73: =SUMIFS(d_SalesRet,d_Category,fCat,d_City,fCity,d_Cust,fCust,d_Pay,fPay,d_Product,$A73,d_Date,">="&fStart,d_Date,"<="&fEnd) -> 250 | J73: =IF(C73=0,0,E73/C73) -> 0.26886474 | K73: =IF(C73=0,0,F73/C73) -> 0.17626033 | L73: =IF(G73=0,0,H73/G73) -> 0.010989011 | M73: =C73+ROW()*0.000001 -> 22087.5 | N73: =IF(C73>0,C73+ROW()*0.000001,1000000000000) -> 22087.5 | O73: =I73+ROW()*0.000001 -> 250.00007
A74: LED Bulb 9W | B74: =INDEX(d_Category,MATCH(A74,d_Product,0)) -> Electronics | C74: =SUMIFS(d_NetSales,d_Category,fCat,d_City,fCity,d_Cust,fCust,d_Pay,fPay,d_Product,$A74,d_Date,">="&fStart,d_Date,"<="&fEnd) -> 25539.6 | D74: =SUMIFS(d_NetQty,d_Category,fCat,d_City,fCity,d_Cust,fCust,d_Pay,fPay,d_Product,$A74,d_Date,">="&fStart,d_Date,"<="&fEnd) -> 219 | E74: =SUMIFS(d_GP,d_Category,fCat,d_City,fCity,d_Cust,fCust,d_Pay,fPay,d_Product,$A74,d_Date,">="&fStart,d_Date,"<="&fEnd) -> 6586.62 | F74: =SUMIFS(d_NP,d_Category,fCat,d_City,fCity,d_Cust,fCust,d_Pay,fPay,d_Product,$A74,d_Date,">="&fStart,d_Date,"<="&fEnd) -> 4292.4 | G74: =SUMIFS(d_Qty,d_Category,fCat,d_City,fCity,d_Cust,fCust,d_Pay,fPay,d_Product,$A74,d_Date,">="&fStart,d_Date,"<="&fEnd) -> 223 | H74: =SUMIFS(d_RetQty,d_Category,fCat,d_City,fCity,d_Cust,fCust,d_Pay,fPay,d_Product,$A74,d_Date,">="&fStart,d_Date,"<="&fEnd) -> 4 | I74: =SUMIFS(d_SalesRet,d_Category,fCat,d_City,fCity,d_Cust,fCust,d_Pay,fPay,d_Product,$A74,d_Date,">="&fStart,d_Date,"<="&fEnd) -> 432 | J74: =IF(C74=0,0,E74/C74) -> 0.25789832 | K74: =IF(C74=0,0,F74/C74) -> 0.16806841 | L74: =IF(G74=0,0,H74/G74) -> 0.01793722 | M74: =C74+ROW()*0.000001 -> 25539.6 | N74: =IF(C74>0,C74+ROW()*0.000001,1000000000000) -> 25539.6 | O74: =I74+ROW()*0.000001 -> 432.00007
A75: Dishwash Liquid 500ml | B75: =INDEX(d_Category,MATCH(A75,d_Product,0)) -> Household | C75: =SUMIFS(d_NetSales,d_Category,fCat,d_City,fCity,d_Cust,fCust,d_Pay,fPay,d_Product,$A75,d_Date,">="&fStart,d_Date,"<="&fEnd) -> 19909.15 | D75: =SUMIFS(d_NetQty,d_Category,fCat,d_City,fCity,d_Cust,fCust,d_Pay,fPay,d_Product,$A75,d_Date,">="&fStart,d_Date,"<="&fEnd) -> 217 | E75: =SUMIFS(d_GP,d_Category,fCat,d_City,fCity,d_Cust,fCust,d_Pay,fPay,d_Product,$A75,d_Date,">="&fStart,d_Date,"<="&fEnd) -> 5195.29 | F75: =SUMIFS(d_NP,d_Category,fCat,d_City,fCity,d_Cust,fCust,d_Pay,fPay,d_Product,$A75,d_Date,">="&fStart,d_Date,"<="&fEnd) -> 3425.63 | G75: =SUMIFS(d_Qty,d_Category,fCat,d_City,fCity,d_Cust,fCust,d_Pay,fPay,d_Product,$A75,d_Date,">="&fStart,d_Date,"<="&fEnd) -> 225 | H75: =SUMIFS(d_RetQty,d_Category,fCat,d_City,fCity,d_Cust,fCust,d_Pay,fPay,d_Product,$A75,d_Date,">="&fStart,d_Date,"<="&fEnd) -> 8 | I75: =SUMIFS(d_SalesRet,d_Category,fCat,d_City,fCity,d_Cust,fCust,d_Pay,fPay,d_Product,$A75,d_Date,">="&fStart,d_Date,"<="&fEnd) -> 755.25 | J75: =IF(C75=0,0,E75/C75) -> 0.26094986 | K75: =IF(C75=0,0,F75/C75) -> 0.1720631 | L75: =IF(G75=0,0,H75/G75) -> 0.035555556 | M75: =C75+ROW()*0.000001 -> 19909.15 | N75: =IF(C75>0,C75+ROW()*0.000001,1000000000000) -> 19909.15 | O75: =I75+ROW()*0.000001 -> 755.25008
A76: Toothpaste 150g | B76: =INDEX(d_Category,MATCH(A76,d_Product,0)) -> Personal Care | C76: =SUMIFS(d_NetSales,d_Category,fCat,d_City,fCity,d_Cust,fCust,d_Pay,fPay,d_Product,$A76,d_Date,">="&fStart,d_Date,"<="&fEnd) -> 24033.9 | D76: =SUMIFS(d_NetQty,d_Category,fCat,d_City,fCity,d_Cust,fCust,d_Pay,fPay,d_Product,$A76,d_Date,">="&fStart,d_Date,"<="&fEnd) -> 224 | E76: =SUMIFS(d_GP,d_Category,fCat,d_City,fCity,d_Cust,fCust,d_Pay,fPay,d_Product,$A76,d_Date,">="&fStart,d_Date,"<="&fEnd) -> 6022.29 | F76: =SUMIFS(d_NP,d_Category,fCat,d_City,fCity,d_Cust,fCust,d_Pay,fPay,d_Product,$A76,d_Date,">="&fStart,d_Date,"<="&fEnd) -> 3742.94 | G76: =SUMIFS(d_Qty,d_Category,fCat,d_City,fCity,d_Cust,fCust,d_Pay,fPay,d_Product,$A76,d_Date,">="&fStart,d_Date,"<="&fEnd) -> 229 | H76: =SUMIFS(d_RetQty,d_Category,fCat,d_City,fCity,d_Cust,fCust,d_Pay,fPay,d_Product,$A76,d_Date,">="&fStart,d_Date,"<="&fEnd) -> 5 | I76: =SUMIFS(d_SalesRet,d_Category,fCat,d_City,fCity,d_Cust,fCust,d_Pay,fPay,d_Product,$A76,d_Date,">="&fStart,d_Date,"<="&fEnd) -> 522.5 | J76: =IF(C76=0,0,E76/C76) -> 0.25057481 | K76: =IF(C76=0,0,F76/C76) -> 0.15573586 | L76: =IF(G76=0,0,H76/G76) -> 0.021834061 | M76: =C76+ROW()*0.000001 -> 24033.9 | N76: =IF(C76>0,C76+ROW()*0.000001,1000000000000) -> 24033.9 | O76: =I76+ROW()*0.000001 -> 522.50008
A77: Batteries Pack | B77: =INDEX(d_Category,MATCH(A77,d_Product,0)) -> Electronics | C77: =SUMIFS(d_NetSales,d_Category,fCat,d_City,fCity,d_Cust,fCust,d_Pay,fPay,d_Product,$A77,d_Date,">="&fStart,d_Date,"<="&fEnd) -> 14876.7 | D77: =SUMIFS(d_NetQty,d_Category,fCat,d_City,fCity,d_Cust,fCust,d_Pay,fPay,d_Product,$A77,d_Date,">="&fStart,d_Date,"<="&fEnd) -> 182 | E77: =SUMIFS(d_GP,d_Category,fCat,d_City,fCity,d_Cust,fCust,d_Pay,fPay,d_Product,$A77,d_Date,">="&fStart,d_Date,"<="&fEnd) -> 3892 | F77: =SUMIFS(d_NP,d_Category,fCat,d_City,fCity,d_Cust,fCust,d_Pay,fPay,d_Product,$A77,d_Date,">="&fStart,d_Date,"<="&fEnd) -> 2573.37 | G77: =SUMIFS(d_Qty,d_Category,fCat,d_City,fCity,d_Cust,fCust,d_Pay,fPay,d_Product,$A77,d_Date,">="&fStart,d_Date,"<="&fEnd) -> 182 | H77: =SUMIFS(d_RetQty,d_Category,fCat,d_City,fCity,d_Cust,fCust,d_Pay,fPay,d_Product,$A77,d_Date,">="&fStart,d_Date,"<="&fEnd) -> 0 | I77: =SUMIFS(d_SalesRet,d_Category,fCat,d_City,fCity,d_Cust,fCust,d_Pay,fPay,d_Product,$A77,d_Date,">="&fStart,d_Date,"<="&fEnd) -> 0 | J77: =IF(C77=0,0,E77/C77) -> 0.26161716 | K77: =IF(C77=0,0,F77/C77) -> 0.17297989 | L77: =IF(G77=0,0,H77/G77) -> 0 | M77: =C77+ROW()*0.000001 -> 14876.7 | N77: =IF(C77>0,C77+ROW()*0.000001,1000000000000) -> 14876.7 | O77: =I77+ROW()*0.000001 -> 7.7e-05
... A85: Mineral Water 1L | B85: =INDEX(d_Category,MATCH(A85,d_Product,0)) -> Beverages | C85: =SUMIFS(d_NetSales,d_Category,fCat,d_City,fCity,d_Cust,fCust,d_Pay,fPay,d_Product,$A85,d_Date,">="&fStart,d_Date,"<="&fEnd) -> 3398.2 | D85: =SUMIFS(d_NetQty,d_Category,fCat,d_City,fCity,d_Cust,fCust,d_Pay,fPay,d_Product,$A85,d_Date,">="&fStart,d_Date,"<="&fEnd) -> 175 | E85: =SUMIFS(d_GP,d_Category,fCat,d_City,fCity,d_Cust,fCust,d_Pay,fPay,d_Product,$A85,d_Date,">="&fStart,d_Date,"<="&fEnd) -> 844.39 | F85: =SUMIFS(d_NP,d_Category,fCat,d_City,fCity,d_Cust,fCust,d_Pay,fPay,d_Product,$A85,d_Date,">="&fStart,d_Date,"<="&fEnd) -> 531.41 | G85: =SUMIFS(d_Qty,d_Category,fCat,d_City,fCity,d_Cust,fCust,d_Pay,fPay,d_Product,$A85,d_Date,">="&fStart,d_Date,"<="&fEnd) -> 175 | H85: =SUMIFS(d_RetQty,d_Category,fCat,d_City,fCity,d_Cust,fCust,d_Pay,fPay,d_Product,$A85,d_Date,">="&fStart,d_Date,"<="&fEnd) -> 0 | I85: =SUMIFS(d_SalesRet,d_Category,fCat,d_City,fCity,d_Cust,fCust,d_Pay,fPay,d_Product,$A85,d_Date,">="&fStart,d_Date,"<="&fEnd) -> 0 | J85: =IF(C85=0,0,E85/C85) -> 0.24848155 | K85: =IF(C85=0,0,F85/C85) -> 0.15637985 | L85: =IF(G85=0,0,H85/G85) -> 0 | M85: =C85+ROW()*0.000001 -> 3398.2001 | N85: =IF(C85>0,C85+ROW()*0.000001,1000000000000) -> 3398.2001 | O85: =I85+ROW()*0.000001 -> 8.5e-05
A86: Total | C86: =SUM(C66:C85) -> 525460.17 | D86: =SUM(D66:D85) -> 4174 | E86: =SUM(E66:E85) -> 136936.28 | F86: =SUM(F66:F85) -> 89567.45 | G86: =SUM(G66:G85) -> 4251 | H86: =SUM(H66:H85) -> 77 | I86: =SUM(I66:I85) -> 9299.5
A89: 6. TOP 5 / BOTTOM 5 PRODUCTS (dynamic ranking; bottom list ignores products with zero sales; "—" = none)
A90: Rank | B90: Top 5 product (Net Sales) | C90: Net Sales (₹) | D90: Bottom 5 product (Net Sales) | E90: Net Sales (₹) | F90: Top 5 product (Sales Return ₹) | G90: Sales Return (₹)
A91: 1 | B91: =IF(LARGE($M$66:$M$85,A91)<=0.5,"—",INDEX($A$66:$A$85,MATCH(LARGE($M$66:$M$85,A91),$M$66:$M$85,0))) -> Rice 5kg | C91: =IF(B91="—",0,INDEX($C$66:$C$85,MATCH(LARGE($M$66:$M$85,A91),$M$66:$M$85,0))) -> 82152 | D91: =IF(SMALL($N$66:$N$85,A91)>=100000000000,"—",INDEX($A$66:$A$85,MATCH(SMALL($N$66:$N$85,A91),$N$66:$N$85,0))) -> Mineral Water 1L | E91: =IF(D91="—",0,INDEX($C$66:$C$85,MATCH(SMALL($N$66:$N$85,A91),$N$66:$N$85,0))) -> 3398.2 | F91: =IF(LARGE($O$66:$O$85,A91)<=0.5,"—",INDEX($A$66:$A$85,MATCH(LARGE($O$66:$O$85,A91),$O$66:$O$85,0))) -> Rice 5kg | G91: =IF(F91="—",0,INDEX($I$66:$I$85,MATCH(LARGE($O$66:$O$85,A91),$O$66:$O$85,0))) -> 2314.2
A92: 2 | B92: =IF(LARGE($M$66:$M$85,A92)<=0.5,"—",INDEX($A$66:$A$85,MATCH(LARGE($M$66:$M$85,A92),$M$66:$M$85,0))) -> Wheat Flour 5kg | C92: =IF(B92="—",0,INDEX($C$66:$C$85,MATCH(LARGE($M$66:$M$85,A92),$M$66:$M$85,0))) -> 77599.2 | D92: =IF(SMALL($N$66:$N$85,A92)>=100000000000,"—",INDEX($A$66:$A$85,MATCH(SMALL($N$66:$N$85,A92),$N$66:$N$85,0))) -> Potato Chips | E92: =IF(D92="—",0,INDEX($C$66:$C$85,MATCH(SMALL($N$66:$N$85,A92),$N$66:$N$85,0))) -> 6232.8 | F92: =IF(LARGE($O$66:$O$85,A92)<=0.5,"—",INDEX($A$66:$A$85,MATCH(LARGE($O$66:$O$85,A92),$O$66:$O$85,0))) -> Cooking Oil 1L | G92: =IF(F92="—",0,INDEX($I$66:$I$85,MATCH(LARGE($O$66:$O$85,A92),$O$66:$O$85,0))) -> 1638.5
A93: 3 | B93: =IF(LARGE($M$66:$M$85,A93)<=0.5,"—",INDEX($A$66:$A$85,MATCH(LARGE($M$66:$M$85,A93),$M$66:$M$85,0))) -> Laundry Detergent 2kg | C93: =IF(B93="—",0,INDEX($C$66:$C$85,MATCH(LARGE($M$66:$M$85,A93),$M$66:$M$85,0))) -> 55955.2 | D93: =IF(SMALL($N$66:$N$85,A93)>=100000000000,"—",INDEX($A$66:$A$85,MATCH(SMALL($N$66:$N$85,A93),$N$66:$N$85,0))) -> Biscuits Pack | E93: =IF(D93="—",0,INDEX($C$66:$C$85,MATCH(SMALL($N$66:$N$85,A93),$N$66:$N$85,0))) -> 7640.4 | F93: =IF(LARGE($O$66:$O$85,A93)<=0.5,"—",INDEX($A$66:$A$85,MATCH(LARGE($O$66:$O$85,A93),$O$66:$O$85,0))) -> Shampoo 340ml | G93: =IF(F93="—",0,INDEX($I$66:$I$85,MATCH(LARGE($O$66:$O$85,A93),$O$66:$O$85,0))) -> 1050
A94: 4 | B94: =IF(LARGE($M$66:$M$85,A94)<=0.5,"—",INDEX($A$66:$A$85,MATCH(LARGE($M$66:$M$85,A94),$M$66:$M$85,0))) -> Coffee 200g | C94: =IF(B94="—",0,INDEX($C$66:$C$85,MATCH(LARGE($M$66:$M$85,A94),$M$66:$M$85,0))) -> 44530.2 | D94: =IF(SMALL($N$66:$N$85,A94)>=100000000000,"—",INDEX($A$66:$A$85,MATCH(SMALL($N$66:$N$85,A94),$N$66:$N$85,0))) -> Soap Bar | E94: =IF(D94="—",0,INDEX($C$66:$C$85,MATCH(SMALL($N$66:$N$85,A94),$N$66:$N$85,0))) -> 8643.1 | F94: =IF(LARGE($O$66:$O$85,A94)<=0.5,"—",INDEX($A$66:$A$85,MATCH(LARGE($O$66:$O$85,A94),$O$66:$O$85,0))) -> Dishwash Liquid 500ml | G94: =IF(F94="—",0,INDEX($I$66:$I$85,MATCH(LARGE($O$66:$O$85,A94),$O$66:$O$85,0))) -> 755.25
A95: 5 | B95: =IF(LARGE($M$66:$M$85,A95)<=0.5,"—",INDEX($A$66:$A$85,MATCH(LARGE($M$66:$M$85,A95),$M$66:$M$85,0))) -> Shampoo 340ml | C95: =IF(B95="—",0,INDEX($C$66:$C$85,MATCH(LARGE($M$66:$M$85,A95),$M$66:$M$85,0))) -> 36071.7 | D95: =IF(SMALL($N$66:$N$85,A95)>=100000000000,"—",INDEX($A$66:$A$85,MATCH(SMALL($N$66:$N$85,A95),$N$66:$N$85,0))) -> Notebook | E95: =IF(D95="—",0,INDEX($C$66:$C$85,MATCH(SMALL($N$66:$N$85,A95),$N$66:$N$85,0))) -> 9385.35 | F95: =IF(LARGE($O$66:$O$85,A95)<=0.5,"—",INDEX($A$66:$A$85,MATCH(LARGE($O$66:$O$85,A95),$O$66:$O$85,0))) -> Wheat Flour 5kg | G95: =IF(F95="—",0,INDEX($I$66:$I$85,MATCH(LARGE($O$66:$O$85,A95),$O$66:$O$85,0))) -> 573.5
A98: 7. CITY (all filters applied)
A99: City | B99: Net Sales (₹) | C99: Gross Profit (₹) | D99: Net Profit (₹) | E99: Net Qty | F99: Invoices | G99: GP Margin | H99: NP Margin | I99: Share of Net Sales | J99: Avg Order Value (₹)
A100: Ghaziabad | B100: =SUMIFS(d_NetSales,d_Category,fCat,d_City,fCity,d_Cust,fCust,d_Pay,fPay,d_City,$A100,d_Date,">="&fStart,d_Date,"<="&fEnd) -> 136753.22 | C100: =SUMIFS(d_GP,d_Category,fCat,d_City,fCity,d_Cust,fCust,d_Pay,fPay,d_City,$A100,d_Date,">="&fStart,d_Date,"<="&fEnd) -> 35579.58 | D100: =SUMIFS(d_NP,d_Category,fCat,d_City,fCity,d_Cust,fCust,d_Pay,fPay,d_City,$A100,d_Date,">="&fStart,d_Date,"<="&fEnd) -> 23154.99 | E100: =SUMIFS(d_NetQty,d_Category,fCat,d_City,fCity,d_Cust,fCust,d_Pay,fPay,d_City,$A100,d_Date,">="&fStart,d_Date,"<="&fEnd) -> 1114 | F100: =COUNTIFS(d_Category,fCat,d_City,fCity,d_Cust,fCust,d_Pay,fPay,d_City,$A100,d_Date,">="&fStart,d_Date,"<="&fEnd) -> 354 | G100: =IF(B100=0,0,C100/B100) -> 0.26017362 | H100: =IF(B100=0,0,D100/B100) -> 0.16931952 | I100: =IF($B$105=0,0,B100/$B$105) -> 0.26025421 | J100: =IF(F100=0,0,B100/F100) -> 386.30853
A101: Delhi | B101: =SUMIFS(d_NetSales,d_Category,fCat,d_City,fCity,d_Cust,fCust,d_Pay,fPay,d_City,$A101,d_Date,">="&fStart,d_Date,"<="&fEnd) -> 134972.06 | C101: =SUMIFS(d_GP,d_Category,fCat,d_City,fCity,d_Cust,fCust,d_Pay,fPay,d_City,$A101,d_Date,">="&fStart,d_Date,"<="&fEnd) -> 35236.19 | D101: =SUMIFS(d_NP,d_Category,fCat,d_City,fCity,d_Cust,fCust,d_Pay,fPay,d_City,$A101,d_Date,">="&fStart,d_Date,"<="&fEnd) -> 23259.91 | E101: =SUMIFS(d_NetQty,d_Category,fCat,d_City,fCity,d_Cust,fCust,d_Pay,fPay,d_City,$A101,d_Date,">="&fStart,d_Date,"<="&fEnd) -> 1050 | F101: =COUNTIFS(d_Category,fCat,d_City,fCity,d_Cust,fCust,d_Pay,fPay,d_City,$A101,d_Date,">="&fStart,d_Date,"<="&fEnd) -> 319 | G101: =IF(B101=0,0,C101/B101) -> 0.26106285 | H101: =IF(B101=0,0,D101/B101) -> 0.1723313 | I101: =IF($B$105=0,0,B101/$B$105) -> 0.25686449 | J101: =IF(F101=0,0,B101/F101) -> 423.10991
A102: Noida | B102: =SUMIFS(d_NetSales,d_Category,fCat,d_City,fCity,d_Cust,fCust,d_Pay,fPay,d_City,$A102,d_Date,">="&fStart,d_Date,"<="&fEnd) -> 126739.13 | C102: =SUMIFS(d_GP,d_Category,fCat,d_City,fCity,d_Cust,fCust,d_Pay,fPay,d_City,$A102,d_Date,">="&fStart,d_Date,"<="&fEnd) -> 33215.7 | D102: =SUMIFS(d_NP,d_Category,fCat,d_City,fCity,d_Cust,fCust,d_Pay,fPay,d_City,$A102,d_Date,">="&fStart,d_Date,"<="&fEnd) -> 21755.42 | E102: =SUMIFS(d_NetQty,d_Category,fCat,d_City,fCity,d_Cust,fCust,d_Pay,fPay,d_City,$A102,d_Date,">="&fStart,d_Date,"<="&fEnd) -> 996 | F102: =COUNTIFS(d_Category,fCat,d_City,fCity,d_Cust,fCust,d_Pay,fPay,d_City,$A102,d_Date,">="&fStart,d_Date,"<="&fEnd) -> 326 | G102: =IF(B102=0,0,C102/B102) -> 0.26207928 | H102: =IF(B102=0,0,D102/B102) -> 0.17165512 | I102: =IF($B$105=0,0,B102/$B$105) -> 0.24119645 | J102: =IF(F102=0,0,B102/F102) -> 388.77034
A103: Gurugram | B103: =SUMIFS(d_NetSales,d_Category,fCat,d_City,fCity,d_Cust,fCust,d_Pay,fPay,d_City,$A103,d_Date,">="&fStart,d_Date,"<="&fEnd) -> 123015.36 | C103: =SUMIFS(d_GP,d_Category,fCat,d_City,fCity,d_Cust,fCust,d_Pay,fPay,d_City,$A103,d_Date,">="&fStart,d_Date,"<="&fEnd) -> 31569.38 | D103: =SUMIFS(d_NP,d_Category,fCat,d_City,fCity,d_Cust,fCust,d_Pay,fPay,d_City,$A103,d_Date,">="&fStart,d_Date,"<="&fEnd) -> 20462.97 | E103: =SUMIFS(d_NetQty,d_Category,fCat,d_City,fCity,d_Cust,fCust,d_Pay,fPay,d_City,$A103,d_Date,">="&fStart,d_Date,"<="&fEnd) -> 994 | F103: =COUNTIFS(d_Category,fCat,d_City,fCity,d_Cust,fCust,d_Pay,fPay,d_City,$A103,d_Date,">="&fStart,d_Date,"<="&fEnd) -> 313 | G103: =IF(B103=0,0,C103/B103) -> 0.25662958 | H103: =IF(B103=0,0,D103/B103) -> 0.16634484 | I103: =IF($B$105=0,0,B103/$B$105) -> 0.23410977 | J103: =IF(F103=0,0,B103/F103) -> 393.02032
A104: Unknown | B104: =SUMIFS(d_NetSales,d_Category,fCat,d_City,fCity,d_Cust,fCust,d_Pay,fPay,d_City,$A104,d_Date,">="&fStart,d_Date,"<="&fEnd) -> 3980.4 | C104: =SUMIFS(d_GP,d_Category,fCat,d_City,fCity,d_Cust,fCust,d_Pay,fPay,d_City,$A104,d_Date,">="&fStart,d_Date,"<="&fEnd) -> 1335.43 | D104: =SUMIFS(d_NP,d_Category,fCat,d_City,fCity,d_Cust,fCust,d_Pay,fPay,d_City,$A104,d_Date,">="&fStart,d_Date,"<="&fEnd) -> 934.16 | E104: =SUMIFS(d_NetQty,d_Category,fCat,d_City,fCity,d_Cust,fCust,d_Pay,fPay,d_City,$A104,d_Date,">="&fStart,d_Date,"<="&fEnd) -> 20 | F104: =COUNTIFS(d_Category,fCat,d_City,fCity,d_Cust,fCust,d_Pay,fPay,d_City,$A104,d_Date,">="&fStart,d_Date,"<="&fEnd) -> 8 | G104: =IF(B104=0,0,C104/B104) -> 0.33550146 | H104: =IF(B104=0,0,D104/B104) -> 0.23468998 | I104: =IF($B$105=0,0,B104/$B$105) -> 0.0075750746 | J104: =IF(F104=0,0,B104/F104) -> 497.55
A105: Total | B105: =SUM(B100:B104) -> 525460.17 | C105: =SUM(C100:C104) -> 136936.28 | D105: =SUM(D100:D104) -> 89567.45 | E105: =SUM(E100:E104) -> 4174 | F105: =SUM(F100:F104) -> 1320 | G105: =IF(B105=0,0,C105/B105) -> 0.26060259 | H105: =IF(B105=0,0,D105/B105) -> 0.17045526 | I105: =SUM(I100:I104) -> 1 | J105: =IF(F105=0,0,B105/F105) -> 398.07589
A108: 8. CUSTOMER TYPE (all filters applied)
A109: Customer Type | B109: Net Sales (₹) | C109: Gross Profit (₹) | D109: Net Profit (₹) | E109: Net Qty | F109: Invoices | G109: GP Margin | H109: NP Margin | I109: Share of Net Sales | J109: Avg Order Value (₹)
A110: Member | B110: =SUMIFS(d_NetSales,d_Category,fCat,d_City,fCity,d_Cust,fCust,d_Pay,fPay,d_Cust,$A110,d_Date,">="&fStart,d_Date,"<="&fEnd) -> 125066.88 | C110: =SUMIFS(d_GP,d_Category,fCat,d_City,fCity,d_Cust,fCust,d_Pay,fPay,d_Cust,$A110,d_Date,">="&fStart,d_Date,"<="&fEnd) -> 33632.61 | D110: =SUMIFS(d_NP,d_Category,fCat,d_City,fCity,d_Cust,fCust,d_Pay,fPay,d_Cust,$A110,d_Date,">="&fStart,d_Date,"<="&fEnd) -> 22122.79 | E110: =SUMIFS(d_NetQty,d_Category,fCat,d_City,fCity,d_Cust,fCust,d_Pay,fPay,d_Cust,$A110,d_Date,">="&fStart,d_Date,"<="&fEnd) -> 987 | F110: =COUNTIFS(d_Category,fCat,d_City,fCity,d_Cust,fCust,d_Pay,fPay,d_Cust,$A110,d_Date,">="&fStart,d_Date,"<="&fEnd) -> 300 | G110: =IF(B110=0,0,C110/B110) -> 0.268917 | H110: =IF(B110=0,0,D110/B110) -> 0.17688768 | I110: =IF($B$115=0,0,B110/$B$115) -> 0.23801401 | J110: =IF(F110=0,0,B110/F110) -> 416.8896
A111: Regular | B111: =SUMIFS(d_NetSales,d_Category,fCat,d_City,fCity,d_Cust,fCust,d_Pay,fPay,d_Cust,$A111,d_Date,">="&fStart,d_Date,"<="&fEnd) -> 125432.79 | C111: =SUMIFS(d_GP,d_Category,fCat,d_City,fCity,d_Cust,fCust,d_Pay,fPay,d_Cust,$A111,d_Date,">="&fStart,d_Date,"<="&fEnd) -> 32530.33 | D111: =SUMIFS(d_NP,d_Category,fCat,d_City,fCity,d_Cust,fCust,d_Pay,fPay,d_Cust,$A111,d_Date,">="&fStart,d_Date,"<="&fEnd) -> 21277.61 | E111: =SUMIFS(d_NetQty,d_Category,fCat,d_City,fCity,d_Cust,fCust,d_Pay,fPay,d_Cust,$A111,d_Date,">="&fStart,d_Date,"<="&fEnd) -> 977 | F111: =COUNTIFS(d_Category,fCat,d_City,fCity,d_Cust,fCust,d_Pay,fPay,d_Cust,$A111,d_Date,">="&fStart,d_Date,"<="&fEnd) -> 323 | G111: =IF(B111=0,0,C111/B111) -> 0.25934471 | H111: =IF(B111=0,0,D111/B111) -> 0.16963355 | I111: =IF($B$115=0,0,B111/$B$115) -> 0.23871037 | J111: =IF(F111=0,0,B111/F111) -> 388.33681
A112: New | B112: =SUMIFS(d_NetSales,d_Category,fCat,d_City,fCity,d_Cust,fCust,d_Pay,fPay,d_Cust,$A112,d_Date,">="&fStart,d_Date,"<="&fEnd) -> 131397.23 | C112: =SUMIFS(d_GP,d_Category,fCat,d_City,fCity,d_Cust,fCust,d_Pay,fPay,d_Cust,$A112,d_Date,">="&fStart,d_Date,"<="&fEnd) -> 32909.4 | D112: =SUMIFS(d_NP,d_Category,fCat,d_City,fCity,d_Cust,fCust,d_Pay,fPay,d_Cust,$A112,d_Date,">="&fStart,d_Date,"<="&fEnd) -> 21332.54 | E112: =SUMIFS(d_NetQty,d_Category,fCat,d_City,fCity,d_Cust,fCust,d_Pay,fPay,d_Cust,$A112,d_Date,">="&fStart,d_Date,"<="&fEnd) -> 1059 | F112: =COUNTIFS(d_Category,fCat,d_City,fCity,d_Cust,fCust,d_Pay,fPay,d_Cust,$A112,d_Date,">="&fStart,d_Date,"<="&fEnd) -> 339 | G112: =IF(B112=0,0,C112/B112) -> 0.25045733 | H112: =IF(B112=0,0,D112/B112) -> 0.16235152 | I112: =IF($B$115=0,0,B112/$B$115) -> 0.25006126 | J112: =IF(F112=0,0,B112/F112) -> 387.60245
A113: Walk-in | B113: =SUMIFS(d_NetSales,d_Category,fCat,d_City,fCity,d_Cust,fCust,d_Pay,fPay,d_Cust,$A113,d_Date,">="&fStart,d_Date,"<="&fEnd) -> 140801.21 | C113: =SUMIFS(d_GP,d_Category,fCat,d_City,fCity,d_Cust,fCust,d_Pay,fPay,d_Cust,$A113,d_Date,">="&fStart,d_Date,"<="&fEnd) -> 37224.37 | D113: =SUMIFS(d_NP,d_Category,fCat,d_City,fCity,d_Cust,fCust,d_Pay,fPay,d_Cust,$A113,d_Date,">="&fStart,d_Date,"<="&fEnd) -> 24457.33 | E113: =SUMIFS(d_NetQty,d_Category,fCat,d_City,fCity,d_Cust,fCust,d_Pay,fPay,d_Cust,$A113,d_Date,">="&fStart,d_Date,"<="&fEnd) -> 1131 | F113: =COUNTIFS(d_Category,fCat,d_City,fCity,d_Cust,fCust,d_Pay,fPay,d_Cust,$A113,d_Date,">="&fStart,d_Date,"<="&fEnd) -> 350 | G113: =IF(B113=0,0,C113/B113) -> 0.26437536 | H113: =IF(B113=0,0,D113/B113) -> 0.17370114 | I113: =IF($B$115=0,0,B113/$B$115) -> 0.26795791 | J113: =IF(F113=0,0,B113/F113) -> 402.28917
A114: Unknown | B114: =SUMIFS(d_NetSales,d_Category,fCat,d_City,fCity,d_Cust,fCust,d_Pay,fPay,d_Cust,$A114,d_Date,">="&fStart,d_Date,"<="&fEnd) -> 2762.06 | C114: =SUMIFS(d_GP,d_Category,fCat,d_City,fCity,d_Cust,fCust,d_Pay,fPay,d_Cust,$A114,d_Date,">="&fStart,d_Date,"<="&fEnd) -> 639.57 | D114: =SUMIFS(d_NP,d_Category,fCat,d_City,fCity,d_Cust,fCust,d_Pay,fPay,d_Cust,$A114,d_Date,">="&fStart,d_Date,"<="&fEnd) -> 377.18 | E114: =SUMIFS(d_NetQty,d_Category,fCat,d_City,fCity,d_Cust,fCust,d_Pay,fPay,d_Cust,$A114,d_Date,">="&fStart,d_Date,"<="&fEnd) -> 20 | F114: =COUNTIFS(d_Category,fCat,d_City,fCity,d_Cust,fCust,d_Pay,fPay,d_Cust,$A114,d_Date,">="&fStart,d_Date,"<="&fEnd) -> 8 | G114: =IF(B114=0,0,C114/B114) -> 0.23155543 | H114: =IF(B114=0,0,D114/B114) -> 0.1365575 | I114: =IF($B$115=0,0,B114/$B$115) -> 0.0052564593 | J114: =IF(F114=0,0,B114/F114) -> 345.2575
A115: Total | B115: =SUM(B110:B114) -> 525460.17 | C115: =SUM(C110:C114) -> 136936.28 | D115: =SUM(D110:D114) -> 89567.45 | E115: =SUM(E110:E114) -> 4174 | F115: =SUM(F110:F114) -> 1320 | G115: =IF(B115=0,0,C115/B115) -> 0.26060259 | H115: =IF(B115=0,0,D115/B115) -> 0.17045526 | I115: =SUM(I110:I114) -> 1 | J115: =IF(F115=0,0,B115/F115) -> 398.07589
A118: 9. PAYMENT METHOD (all filters applied)
A119: Payment Method | B119: Net Sales (₹) | C119: Gross Profit (₹) | D119: Net Profit (₹) | E119: Net Qty | F119: Invoices | G119: GP Margin | H119: NP Margin | I119: Share of Net Sales | J119: Avg Order Value (₹)
A120: Card | B120: =SUMIFS(d_NetSales,d_Category,fCat,d_City,fCity,d_Cust,fCust,d_Pay,fPay,d_Pay,$A120,d_Date,">="&fStart,d_Date,"<="&fEnd) -> 128540.19 | C120: =SUMIFS(d_GP,d_Category,fCat,d_City,fCity,d_Cust,fCust,d_Pay,fPay,d_Pay,$A120,d_Date,">="&fStart,d_Date,"<="&fEnd) -> 33549.63 | D120: =SUMIFS(d_NP,d_Category,fCat,d_City,fCity,d_Cust,fCust,d_Pay,fPay,d_Pay,$A120,d_Date,">="&fStart,d_Date,"<="&fEnd) -> 22232.01 | E120: =SUMIFS(d_NetQty,d_Category,fCat,d_City,fCity,d_Cust,fCust,d_Pay,fPay,d_Pay,$A120,d_Date,">="&fStart,d_Date,"<="&fEnd) -> 1026 | F120: =COUNTIFS(d_Category,fCat,d_City,fCity,d_Cust,fCust,d_Pay,fPay,d_Pay,$A120,d_Date,">="&fStart,d_Date,"<="&fEnd) -> 329 | G120: =IF(B120=0,0,C120/B120) -> 0.26100498 | H120: =IF(B120=0,0,D120/B120) -> 0.17295766 | I120: =IF($B$125=0,0,B120/$B$125) -> 0.24462404 | J120: =IF(F120=0,0,B120/F120) -> 390.69967
A121: Cash | B121: =SUMIFS(d_NetSales,d_Category,fCat,d_City,fCity,d_Cust,fCust,d_Pay,fPay,d_Pay,$A121,d_Date,">="&fStart,d_Date,"<="&fEnd) -> 136464.81 | C121: =SUMIFS(d_GP,d_Category,fCat,d_City,fCity,d_Cust,fCust,d_Pay,fPay,d_Pay,$A121,d_Date,">="&fStart,d_Date,"<="&fEnd) -> 35624.03 | D121: =SUMIFS(d_NP,d_Category,fCat,d_City,fCity,d_Cust,fCust,d_Pay,fPay,d_Pay,$A121,d_Date,">="&fStart,d_Date,"<="&fEnd) -> 22997.32 | E121: =SUMIFS(d_NetQty,d_Category,fCat,d_City,fCity,d_Cust,fCust,d_Pay,fPay,d_Pay,$A121,d_Date,">="&fStart,d_Date,"<="&fEnd) -> 1071 | F121: =COUNTIFS(d_Category,fCat,d_City,fCity,d_Cust,fCust,d_Pay,fPay,d_Pay,$A121,d_Date,">="&fStart,d_Date,"<="&fEnd) -> 331 | G121: =IF(B121=0,0,C121/B121) -> 0.2610492 | H121: =IF(B121=0,0,D121/B121) -> 0.16852198 | I121: =IF($B$125=0,0,B121/$B$125) -> 0.25970534 | J121: =IF(F121=0,0,B121/F121) -> 412.28039
A122: UPI | B122: =SUMIFS(d_NetSales,d_Category,fCat,d_City,fCity,d_Cust,fCust,d_Pay,fPay,d_Pay,$A122,d_Date,">="&fStart,d_Date,"<="&fEnd) -> 123079.75 | C122: =SUMIFS(d_GP,d_Category,fCat,d_City,fCity,d_Cust,fCust,d_Pay,fPay,d_Pay,$A122,d_Date,">="&fStart,d_Date,"<="&fEnd) -> 31674.9 | D122: =SUMIFS(d_NP,d_Category,fCat,d_City,fCity,d_Cust,fCust,d_Pay,fPay,d_Pay,$A122,d_Date,">="&fStart,d_Date,"<="&fEnd) -> 20866.82 | E122: =SUMIFS(d_NetQty,d_Category,fCat,d_City,fCity,d_Cust,fCust,d_Pay,fPay,d_Pay,$A122,d_Date,">="&fStart,d_Date,"<="&fEnd) -> 1005 | F122: =COUNTIFS(d_Category,fCat,d_City,fCity,d_Cust,fCust,d_Pay,fPay,d_Pay,$A122,d_Date,">="&fStart,d_Date,"<="&fEnd) -> 320 | G122: =IF(B122=0,0,C122/B122) -> 0.25735265 | H122: =IF(B122=0,0,D122/B122) -> 0.16953902 | I122: =IF($B$125=0,0,B122/$B$125) -> 0.23423231 | J122: =IF(F122=0,0,B122/F122) -> 384.62422
A123: Wallet | B123: =SUMIFS(d_NetSales,d_Category,fCat,d_City,fCity,d_Cust,fCust,d_Pay,fPay,d_Pay,$A123,d_Date,">="&fStart,d_Date,"<="&fEnd) -> 132651.66 | C123: =SUMIFS(d_GP,d_Category,fCat,d_City,fCity,d_Cust,fCust,d_Pay,fPay,d_Pay,$A123,d_Date,">="&fStart,d_Date,"<="&fEnd) -> 34764.61 | D123: =SUMIFS(d_NP,d_Category,fCat,d_City,fCity,d_Cust,fCust,d_Pay,fPay,d_Pay,$A123,d_Date,">="&fStart,d_Date,"<="&fEnd) -> 22545.82 | E123: =SUMIFS(d_NetQty,d_Category,fCat,d_City,fCity,d_Cust,fCust,d_Pay,fPay,d_Pay,$A123,d_Date,">="&fStart,d_Date,"<="&fEnd) -> 1035 | F123: =COUNTIFS(d_Category,fCat,d_City,fCity,d_Cust,fCust,d_Pay,fPay,d_Pay,$A123,d_Date,">="&fStart,d_Date,"<="&fEnd) -> 329 | G123: =IF(B123=0,0,C123/B123) -> 0.26207444 | H123: =IF(B123=0,0,D123/B123) -> 0.16996259 | I123: =IF($B$125=0,0,B123/$B$125) -> 0.25244855 | J123: =IF(F123=0,0,B123/F123) -> 403.19653
...
